Workbook

Sheet Read Me
B2: Cattle Fattening TMR Management Workbook
B3: 100-Day TMR Based Fattening Program — Jahangir (v2 — expanded)
B5: What this workbook does
C6: Ye Sultan Dairy ka poora Farm Management System hai — Fattening, Qurbani, Dairy, aur Breeding, sath hi Inventory, Staff aur Accounts, sab ek hi interconnected Excel file mein. Sab sheets aapas mein linked hain — ek jagah number badlein to poori file khud update ho jati hai.
B8: Color legend (har sheet mein)
C9: Blue text = aapko yahan number/rate daalna hai (hardcoded input)
C10: Yellow fill = ye cell zaroor fill karein (rate, weight, date waghera)
C11: Black text = formula hai, ise edit na karein
C12: Green text = doosri sheet se link hai
B14: Sheet order aur kya karna hai
B15: FOUNDATION
B16: 1. Ingredient Database | C16: 56 ingredients — Rate per kg (column J) yahan daalein.
B17: 2. Ration Formulator | C17: Concentrate aur Roughage Mix dropdown se banate hain, jitne chahein ingredients.
B18: 3. Animal Register | C18: Ek hi register — Fattening, Qurbani, Dairy, Breeding Stock sab. Purpose column se pehchana jata hai.
B19: 4. Animal Profile | C19: Kisi bhi Animal ID ko dropdown se chunein — poora record ek jagah dikh jata hai.
B20: QURBANI
B21: 5. Qurbani Module | C21: Qurbani animals khud yahan aa jate hain. Sale/Invoice Log (side mein) bharein to Profit/Loss khud nikalta hai.
B22: DAIRY
B23: 6. Dairy Module | C23: Dairy animals khud yahan aa jate hain, milk average ke sath.
B24: 7. Milk Production Log | C24: Roz ki milking (morning/evening) yahan likhein.
B25: 8. Milk Customers | C25: Doodh ke regular customers aur unki daily order/rate.
B26: BREEDING
B27: 9. Breeding Module | C27: Breeding Stock animals khud yahan aa jate hain, latest breeding status ke sath.
B28: 10. Breeding Log | C28: Har breeding event — Expected Calving Date khud +283 din calculate hoti hai.
B29: 11. Calving Log | C29: Naya calf paida hote hi yahan likhein, phir Animal Register mein bhi register karein.
B30: 12. Weaning Log | C30: Calf ki weaning date aur weight.
B31: FATTENING (roz ka kaam)
B32: 13. Daily Feeding | C32: Roz Animal ID aur current weight daalein — feed quantity aur energy khud calculate hoti hai.
B33: 14. Weight Log | C33: Har weighing (daily/weekly/fortnightly) yahan record karein — kabhi delete na karein.
B34: 15. Weight & Growth Tracker | C34: Har animal ka latest weight, gain, ADG ek nazar mein.
B35: 16. Health Log | C35: Vaccination, deworming, treatment — ek animal ya ek sath kai animals.
B36: 17. Feed Purchase Log | C36: Ingredient khareedte waqt yahan likhein — Feed Stock khud update hota hai.
B37: 18. Cost Tracker | C37: Roz jo ingredient use hua uski quantity — cost khud calculate hota hai.
B38: 19. Feed Stock | C38: Godam ka stock, kam hone par alert.
B39: INVENTORY, STAFF, ACCOUNTS
B40: 20. General Inventory | C40: Medicines, dairy equipment, farm tools.
B41: 21. Fattening Customers | C41: Fattened cattle ke buyers (butchers/wholesalers).
B42: 22. Fattening Sales Log | C42: Jab Fattening animal bike, yahan likhein — Profit/Loss khud nikalta hai.
B43: 23. Staff Module | C43: Har mulazim ki details aur salary.
B44: 24. Salary Payments | C44: Har mahine ki salary payment yahan likhein.
B45: 25. Ledger | C45: Poori file ka Income/Expense summary — kuch type nahi karna, khud aata hai.
B46: 26. Dashboard | C46: Fattening/Qurbani program ka live summary — status, cost, FCR.
B48: Body Condition Score (BCS) | C48: Weight Log mein 1 (bohat kamzor) se 5 (bohat mota) scale par score karein, 0.5 ke steps mein.
B49: Ehtiyaat — Sorghum/Sudan/Bajra fodder | C49: Choti umar ya sukhi/stress wali sorghum, sudan grass, ya bajra green fodder mein zeher (prussic acid) ban sakta hai — ehtiyaat rakhein.
B50: Important assumption | C50: Meat/Dressing % = 58% — Dashboard ke Planning Target box mein change kar sakte hain.

Sheet Dashboard
A1: FATTENING PROGRAM DASHBOARD
A2: 100-Day TMR Fattening Program — Live Summary
A4: LIVE OPERATIONS SUMMARY
A5: ACTIVE ANIMALS | C5: AVG DAYS ON FEED | E5: AVG DAYS REMAINING | G5: FEED STOCK ALERTS
A6: =COUNTIF('Animal Register'!Q:Q,"Active") -> 1 | C6: =IF(COUNTIF('Animal Register'!Q:Q,"Active")=0,"-",ROUND(AVERAGEIF('Animal Register'!Q:Q,"Active",'Animal Register'!O:O),0)) -> 9 | E6: =IF(ISNUMBER(C6),100-C6,"-") -> 91 | G6: =COUNTIF('Feed Stock'!G:G,"Reorder Now") -> 0
A8: AVG START WEIGHT (kg) | C8: AVG CURRENT WEIGHT (kg) | E8: AVG GAIN SO FAR (kg) | G8: TOTAL FEED COST (Rs)
A9: =IF(COUNTIF('Animal Register'!Q:Q,"Active")=0,"-",ROUND(AVERAGEIF('Animal Register'!Q:Q,"Active",'Animal Register'!I:I),1)) -> 212 | C9: =IF(COUNTIF('Animal Register'!Q:Q,"Active")=0,"-",ROUND(AVERAGEIF('Animal Register'!Q:Q,"Active",'Animal Register'!S:S),1)) -> 212 | E9: =IF(AND(ISNUMBER(A9),ISNUMBER(C9)),ROUND(C9-A9,1),"-") -> 0 | G9: ='Cost Tracker'!J4 -> 0
A11: FCR (kg DM feed / kg gain) | C11: COST PER KG GAIN (Rs) | E11: AVG BCS (LATEST) | G11: ANIMALS SOLD
A12: =IF(SUM('Weight & Growth Tracker'!I5:I74)=0,"-",ROUND(SUM('Daily Feeding'!F5:F104)/SUM('Weight & Growth Tracker'!I5:I74),2)) -> - | C12: =IF(SUM('Weight & Growth Tracker'!I5:I74)=0,"-",ROUND('Cost Tracker'!J4/SUM('Weight & Growth Tracker'!I5:I74),0)) -> - | E12: =IFERROR(ROUND(AVERAGEIF('Weight & Growth Tracker'!G5:G74,"<>-"),1),"-") -> 2.5 | G12: =COUNTIF('Animal Register'!Q:Q,"Sold") -> 0
A15: PLANNING TARGET (Editable — based on 58% dressing practice)
A16: Target Final Live Weight (kg) | D16: Dressing % | F16: Expected Meat Output (kg)
A17: 328 | D17: 0.58 | F17: =IF(AND(ISNUMBER(A17),ISNUMBER(D17)),ROUND(A17*D17,1),"-") -> 190.2
K21: Chart data (auto — do not edit)
K22: Stage | L22: Weight (kg)
K23: Start | L23: =A9 -> 212
K24: Current | L24: =C9 -> 212
K25: Target Final | L25: =A17 -> 328

Sheet Ingredient Database
A1: INGREDIENT MASTER DATABASE (DM basis for CP / TDN / Energy / NDF)
A3: ID | B3: Ingredient Name | C3: Category | D3: Sub-Category | E3: DM % | F3: CP % | G3: TDN % | H3: Energy - ME (Mcal/kg) | I3: NDF (Fiber) % | J3: Rate per kg (Rs)
A4: 1 | B4: Maize Grain (Crushed) | C4: Concentrate | D4: Grain | E4: 0.88 | F4: 0.09 | G4: 0.82 | H4: =IF($D4="Dry Straw/Stover",$G4*2.65,IF($C4="Roughage",$G4*3.31,$G4*3.62)) -> 2.9684 | I4: 0.1
A5: 2 | B5: Wheat Grain (Crushed) | C5: Concentrate | D5: Grain | E5: 0.88 | F5: 0.12 | G5: 0.82 | H5: =IF($D5="Dry Straw/Stover",$G5*2.65,IF($C5="Roughage",$G5*3.31,$G5*3.62)) -> 2.9684 | I5: 0.12
A6: 3 | B6: Barley Grain (Crushed) | C6: Concentrate | D6: Grain | E6: 0.88 | F6: 0.115 | G6: 0.75 | H6: =IF($D6="Dry Straw/Stover",$G6*2.65,IF($C6="Roughage",$G6*3.31,$G6*3.62)) -> 2.715 | I6: 0.18
A7: 4 | B7: Sorghum Grain (Jowar) | C7: Concentrate | D7: Grain | E7: 0.88 | F7: 0.1 | G7: 0.78 | H7: =IF($D7="Dry Straw/Stover",$G7*2.65,IF($C7="Roughage",$G7*3.31,$G7*3.62)) -> 2.8236 | I7: 0.12
A8: 5 | B8: Pearl Millet Grain (Bajra) | C8: Concentrate | D8: Grain | E8: 0.88 | F8: 0.115 | G8: 0.75 | H8: =IF($D8="Dry Straw/Stover",$G8*2.65,IF($C8="Roughage",$G8*3.31,$G8*3.62)) -> 2.715 | I8: 0.15
A9: 6 | B9: Broken Rice (Rice Kani) | C9: Concentrate | D9: Grain | E9: 0.88 | F9: 0.08 | G9: 0.8 | H9: =IF($D9="Dry Straw/Stover",$G9*2.65,IF($C9="Roughage",$G9*3.31,$G9*3.62)) -> 2.896 | I9: 0.08
A10: 7 | B10: Cottonseed Cake (Banaula Khal) | C10: Concentrate | D10: Oilseed Cake | E10: 0.9 | F10: 0.22 | G10: 0.68 | H10: =IF($D10="Dry Straw/Stover",$G10*2.65,IF($C10="Roughage",$G10*3.31,$G10*3.62)) -> 2.4616 | I10: 0.35
A11: 8 | B11: Cottonseed Meal (Solvent Extracted) | C11: Concentrate | D11: Oilseed Cake | E11: 0.9 | F11: 0.28 | G11: 0.65 | H11: =IF($D11="Dry Straw/Stover",$G11*2.65,IF($C11="Roughage",$G11*3.31,$G11*3.62)) -> 2.353 | I11: 0.3
A12: 9 | B12: Canola / Sarson Cake | C12: Concentrate | D12: Oilseed Cake | E12: 0.9 | F12: 0.36 | G12: 0.7 | H12: =IF($D12="Dry Straw/Stover",$G12*2.65,IF($C12="Roughage",$G12*3.31,$G12*3.62)) -> 2.534 | I12: 0.25
A13: 10 | B13: Sunflower Cake | C13: Concentrate | D13: Oilseed Cake | E13: 0.9 | F13: 0.3 | G13: 0.65 | H13: =IF($D13="Dry Straw/Stover",$G13*2.65,IF($C13="Roughage",$G13*3.31,$G13*3.62)) -> 2.353 | I13: 0.38
A14: 11 | B14: Sunflower Meal (Decorticated) | C14: Concentrate | D14: Oilseed Cake | E14: 0.9 | F14: 0.36 | G14: 0.68 | H14: =IF($D14="Dry Straw/Stover",$G14*2.65,IF($C14="Roughage",$G14*3.31,$G14*3.62)) -> 2.4616 | I14: 0.28
A15: 12 | B15: Soybean Meal | C15: Concentrate | D15: Oilseed Cake | E15: 0.89 | F15: 0.46 | G15: 0.82 | H15: =IF($D15="Dry Straw/Stover",$G15*2.65,IF($C15="Roughage",$G15*3.31,$G15*3.62)) -> 2.9684 | I15: 0.12
... A59: 56 | B59: Sugarcane Bagasse | C59: Roughage | D59: Dry Straw/Stover | E59: 0.9 | F59: 0.02 | G59: 0.35 | H59: =IF($D59="Dry Straw/Stover",$G59*2.65,IF($C59="Roughage",$G59*3.31,$G59*3.62)) -> 0.9275 | I59: 0.85

Sheet Ration Formulator
A1: RATION FORMULATOR
A3: A) PHASE REFERENCE — Day Range & Concentrate:Roughage Ratio
A4: Phase | B4: Day From | C4: Day To | D4: Concentrate % (of DM) | E4: Roughage % (of DM)
A5: Phase 1 - Adaptation | B5: 1 | C5: 33 | D5: 0.45 | E5: 0.55
A6: Phase 2 - Growth | B6: 34 | C6: 66 | D6: 0.6 | E6: 0.4
A7: Phase 3 - Finishing | B7: 67 | C7: 100 | D7: 0.75 | E7: 0.25
A9: B) CONCENTRATE MIX — Blend Composition (constant across all phases, dropdown se chunein)
A10: Ingredient (dropdown) | B10: % Inclusion in Mix | C10: CP Contribution | D10: TDN Contribution | E10: DM Contribution | F10: Energy Contribution (Mcal)
A11: Maize Grain (Crushed) | B11: 0.25 | C11: =IF($A11="",0,$B11*IFERROR(INDEX('Ingredient Database'!$F:$F,MATCH($A11,'Ingredient Database'!$B:$B,0)),0)) -> 0.0225 | D11: =IF($A11="",0,$B11*IFERROR(INDEX('Ingredient Database'!$G:$G,MATCH($A11,'Ingredient Database'!$B:$B,0)),0)) -> 0.205 | E11: =IF($A11="",0,$B11*IFERROR(INDEX('Ingredient Database'!$E:$E,MATCH($A11,'Ingredient Database'!$B:$B,0)),0)) -> 0.22 | F11: =IF($A11="",0,$B11*IFERROR(INDEX('Ingredient Database'!$H:$H,MATCH($A11,'Ingredient Database'!$B:$B,0)),0)) -> 0.7421
A12: Wheat Bran (Chokar) | B12: 0.12 | C12: =IF($A12="",0,$B12*IFERROR(INDEX('Ingredient Database'!$F:$F,MATCH($A12,'Ingredient Database'!$B:$B,0)),0)) -> 0.018 | D12: =IF($A12="",0,$B12*IFERROR(INDEX('Ingredient Database'!$G:$G,MATCH($A12,'Ingredient Database'!$B:$B,0)),0)) -> 0.0816 | E12: =IF($A12="",0,$B12*IFERROR(INDEX('Ingredient Database'!$E:$E,MATCH($A12,'Ingredient Database'!$B:$B,0)),0)) -> 0.1056 | F12: =IF($A12="",0,$B12*IFERROR(INDEX('Ingredient Database'!$H:$H,MATCH($A12,'Ingredient Database'!$B:$B,0)),0)) -> 0.295392
A13: Cottonseed Cake (Banaula Khal) | B13: 0.25 | C13: =IF($A13="",0,$B13*IFERROR(INDEX('Ingredient Database'!$F:$F,MATCH($A13,'Ingredient Database'!$B:$B,0)),0)) -> 0.055 | D13: =IF($A13="",0,$B13*IFERROR(INDEX('Ingredient Database'!$G:$G,MATCH($A13,'Ingredient Database'!$B:$B,0)),0)) -> 0.17 | E13: =IF($A13="",0,$B13*IFERROR(INDEX('Ingredient Database'!$E:$E,MATCH($A13,'Ingredient Database'!$B:$B,0)),0)) -> 0.225 | F13: =IF($A13="",0,$B13*IFERROR(INDEX('Ingredient Database'!$H:$H,MATCH($A13,'Ingredient Database'!$B:$B,0)),0)) -> 0.6154
A14: Canola / Sarson Cake | B14: 0.15 | C14: =IF($A14="",0,$B14*IFERROR(INDEX('Ingredient Database'!$F:$F,MATCH($A14,'Ingredient Database'!$B:$B,0)),0)) -> 0.054 | D14: =IF($A14="",0,$B14*IFERROR(INDEX('Ingredient Database'!$G:$G,MATCH($A14,'Ingredient Database'!$B:$B,0)),0)) -> 0.105 | E14: =IF($A14="",0,$B14*IFERROR(INDEX('Ingredient Database'!$E:$E,MATCH($A14,'Ingredient Database'!$B:$B,0)),0)) -> 0.135 | F14: =IF($A14="",0,$B14*IFERROR(INDEX('Ingredient Database'!$H:$H,MATCH($A14,'Ingredient Database'!$B:$B,0)),0)) -> 0.3801
A15: Rice Polish | B15: 0.1 | C15: =IF($A15="",0,$B15*IFERROR(INDEX('Ingredient Database'!$F:$F,MATCH($A15,'Ingredient Database'!$B:$B,0)),0)) -> 0.0125 | D15: =IF($A15="",0,$B15*IFERROR(INDEX('Ingredient Database'!$G:$G,MATCH($A15,'Ingredient Database'!$B:$B,0)),0)) -> 0.072 | E15: =IF($A15="",0,$B15*IFERROR(INDEX('Ingredient Database'!$E:$E,MATCH($A15,'Ingredient Database'!$B:$B,0)),0)) -> 0.09 | F15: =IF($A15="",0,$B15*IFERROR(INDEX('Ingredient Database'!$H:$H,MATCH($A15,'Ingredient Database'!$B:$B,0)),0)) -> 0.26064
A16: Molasses (Shakar) | B16: 0.08 | C16: =IF($A16="",0,$B16*IFERROR(INDEX('Ingredient Database'!$F:$F,MATCH($A16,'Ingredient Database'!$B:$B,0)),0)) -> 0.0032 | D16: =IF($A16="",0,$B16*IFERROR(INDEX('Ingredient Database'!$G:$G,MATCH($A16,'Ingredient Database'!$B:$B,0)),0)) -> 0.0576 | E16: =IF($A16="",0,$B16*IFERROR(INDEX('Ingredient Database'!$E:$E,MATCH($A16,'Ingredient Database'!$B:$B,0)),0)) -> 0.06 | F16: =IF($A16="",0,$B16*IFERROR(INDEX('Ingredient Database'!$H:$H,MATCH($A16,'Ingredient Database'!$B:$B,0)),0)) -> 0.208512
A17: Mineral Mixture | B17: 0.03 | C17: =IF($A17="",0,$B17*IFERROR(INDEX('Ingredient Database'!$F:$F,MATCH($A17,'Ingredient Database'!$B:$B,0)),0)) -> 0 | D17: =IF($A17="",0,$B17*IFERROR(INDEX('Ingredient Database'!$G:$G,MATCH($A17,'Ingredient Database'!$B:$B,0)),0)) -> 0 | E17: =IF($A17="",0,$B17*IFERROR(INDEX('Ingredient Database'!$E:$E,MATCH($A17,'Ingredient Database'!$B:$B,0)),0)) -> 0.0294 | F17: =IF($A17="",0,$B17*IFERROR(INDEX('Ingredient Database'!$H:$H,MATCH($A17,'Ingredient Database'!$B:$B,0)),0)) -> 0
A18: Salt | B18: 0.02 | C18: =IF($A18="",0,$B18*IFERROR(INDEX('Ingredient Database'!$F:$F,MATCH($A18,'Ingredient Database'!$B:$B,0)),0)) -> 0 | D18: =IF($A18="",0,$B18*IFERROR(INDEX('Ingredient Database'!$G:$G,MATCH($A18,'Ingredient Database'!$B:$B,0)),0)) -> 0 | E18: =IF($A18="",0,$B18*IFERROR(INDEX('Ingredient Database'!$E:$E,MATCH($A18,'Ingredient Database'!$B:$B,0)),0)) -> 0.0198 | F18: =IF($A18="",0,$B18*IFERROR(INDEX('Ingredient Database'!$H:$H,MATCH($A18,'Ingredient Database'!$B:$B,0)),0)) -> 0
C19: =IF($A19="",0,$B19*IFERROR(INDEX('Ingredient Database'!$F:$F,MATCH($A19,'Ingredient Database'!$B:$B,0)),0)) -> 0 | D19: =IF($A19="",0,$B19*IFERROR(INDEX('Ingredient Database'!$G:$G,MATCH($A19,'Ingredient Database'!$B:$B,0)),0)) -> 0 | E19: =IF($A19="",0,$B19*IFERROR(INDEX('Ingredient Database'!$E:$E,MATCH($A19,'Ingredient Database'!$B:$B,0)),0)) -> 0 | F19: =IF($A19="",0,$B19*IFERROR(INDEX('Ingredient Database'!$H:$H,MATCH($A19,'Ingredient Database'!$B:$B,0)),0)) -> 0
C20: =IF($A20="",0,$B20*IFERROR(INDEX('Ingredient Database'!$F:$F,MATCH($A20,'Ingredient Database'!$B:$B,0)),0)) -> 0 | D20: =IF($A20="",0,$B20*IFERROR(INDEX('Ingredient Database'!$G:$G,MATCH($A20,'Ingredient Database'!$B:$B,0)),0)) -> 0 | E20: =IF($A20="",0,$B20*IFERROR(INDEX('Ingredient Database'!$E:$E,MATCH($A20,'Ingredient Database'!$B:$B,0)),0)) -> 0 | F20: =IF($A20="",0,$B20*IFERROR(INDEX('Ingredient Database'!$H:$H,MATCH($A20,'Ingredient Database'!$B:$B,0)),0)) -> 0
A21: TOTAL / BLEND VALUE | B21: =SUM(B11:B20) -> 1 | C21: =SUM(C11:C20) -> 0.1652 | D21: =SUM(D11:D20) -> 0.6912 | E21: =SUM(E11:E20) -> 0.8848 | F21: =SUM(F11:F20) -> 2.502144
A23: C) ROUGHAGE MIX — Flexible Blend per Phase (dropdown se jitne chahein ingredients mix karein)
A24: Phase 1 - Adaptation
A25: Ingredient (dropdown) | B25: % of Total Roughage | C25: CP Contribution | D25: TDN Contribution | E25: DM Contribution | F25: Energy Contribution (Mcal)
A26: Maize Silage | B26: 0.5 | C26: =IF($A26="",0,$B26*IFERROR(INDEX('Ingredient Database'!$F:$F,MATCH($A26,'Ingredient Database'!$B:$B,0)),0)) -> 0.04 | D26: =IF($A26="",0,$B26*IFERROR(INDEX('Ingredient Database'!$G:$G,MATCH($A26,'Ingredient Database'!$B:$B,0)),0)) -> 0.34 | E26: =IF($A26="",0,$B26*IFERROR(INDEX('Ingredient Database'!$E:$E,MATCH($A26,'Ingredient Database'!$B:$B,0)),0)) -> 0.16 | F26: =IF($A26="",0,$B26*IFERROR(INDEX('Ingredient Database'!$H:$H,MATCH($A26,'Ingredient Database'!$B:$B,0)),0)) -> 1.1254
A27: Wheat Straw (Bhoosa) | B27: 0.5 | C27: =IF($A27="",0,$B27*IFERROR(INDEX('Ingredient Database'!$F:$F,MATCH($A27,'Ingredient Database'!$B:$B,0)),0)) -> 0.02 | D27: =IF($A27="",0,$B27*IFERROR(INDEX('Ingredient Database'!$G:$G,MATCH($A27,'Ingredient Database'!$B:$B,0)),0)) -> 0.21 | E27: =IF($A27="",0,$B27*IFERROR(INDEX('Ingredient Database'!$E:$E,MATCH($A27,'Ingredient Database'!$B:$B,0)),0)) -> 0.45 | F27: =IF($A27="",0,$B27*IFERROR(INDEX('Ingredient Database'!$H:$H,MATCH($A27,'Ingredient Database'!$B:$B,0)),0)) -> 0.5565
C28: =IF($A28="",0,$B28*IFERROR(INDEX('Ingredient Database'!$F:$F,MATCH($A28,'Ingredient Database'!$B:$B,0)),0)) -> 0 | D28: =IF($A28="",0,$B28*IFERROR(INDEX('Ingredient Database'!$G:$G,MATCH($A28,'Ingredient Database'!$B:$B,0)),0)) -> 0 | E28: =IF($A28="",0,$B28*IFERROR(INDEX('Ingredient Database'!$E:$E,MATCH($A28,'Ingredient Database'!$B:$B,0)),0)) -> 0 | F28: =IF($A28="",0,$B28*IFERROR(INDEX('Ingredient Database'!$H:$H,MATCH($A28,'Ingredient Database'!$B:$B,0)),0)) -> 0
C29: =IF($A29="",0,$B29*IFERROR(INDEX('Ingredient Database'!$F:$F,MATCH($A29,'Ingredient Database'!$B:$B,0)),0)) -> 0 | D29: =IF($A29="",0,$B29*IFERROR(INDEX('Ingredient Database'!$G:$G,MATCH($A29,'Ingredient Database'!$B:$B,0)),0)) -> 0 | E29: =IF($A29="",0,$B29*IFERROR(INDEX('Ingredient Database'!$E:$E,MATCH($A29,'Ingredient Database'!$B:$B,0)),0)) -> 0 | F29: =IF($A29="",0,$B29*IFERROR(INDEX('Ingredient Database'!$H:$H,MATCH($A29,'Ingredient Database'!$B:$B,0)),0)) -> 0
C30: =IF($A30="",0,$B30*IFERROR(INDEX('Ingredient Database'!$F:$F,MATCH($A30,'Ingredient Database'!$B:$B,0)),0)) -> 0 | D30: =IF($A30="",0,$B30*IFERROR(INDEX('Ingredient Database'!$G:$G,MATCH($A30,'Ingredient Database'!$B:$B,0)),0)) -> 0 | E30: =IF($A30="",0,$B30*IFERROR(INDEX('Ingredient Database'!$E:$E,MATCH($A30,'Ingredient Database'!$B:$B,0)),0)) -> 0 | F30: =IF($A30="",0,$B30*IFERROR(INDEX('Ingredient Database'!$H:$H,MATCH($A30,'Ingredient Database'!$B:$B,0)),0)) -> 0
C31: =IF($A31="",0,$B31*IFERROR(INDEX('Ingredient Database'!$F:$F,MATCH($A31,'Ingredient Database'!$B:$B,0)),0)) -> 0 | D31: =IF($A31="",0,$B31*IFERROR(INDEX('Ingredient Database'!$G:$G,MATCH($A31,'Ingredient Database'!$B:$B,0)),0)) -> 0 | E31: =IF($A31="",0,$B31*IFERROR(INDEX('Ingredient Database'!$E:$E,MATCH($A31,'Ingredient Database'!$B:$B,0)),0)) -> 0 | F31: =IF($A31="",0,$B31*IFERROR(INDEX('Ingredient Database'!$H:$H,MATCH($A31,'Ingredient Database'!$B:$B,0)),0)) -> 0
A32: TOTAL | B32: =SUM(B26:B31) -> 1 | C32: =SUM(C26:C31) -> 0.06 | D32: =SUM(D26:D31) -> 0.55 | E32: =SUM(E26:E31) -> 0.61 | F32: =SUM(F26:F31) -> 1.6819
A34: Phase 2 - Growth
A35: Ingredient (dropdown) | B35: % of Total Roughage | C35: CP Contribution | D35: TDN Contribution | E35: DM Contribution | F35: Energy Contribution (Mcal)
A36: Maize Silage | B36: 0.65 | C36: =IF($A36="",0,$B36*IFERROR(INDEX('Ingredient Database'!$F:$F,MATCH($A36,'Ingredient Database'!$B:$B,0)),0)) -> 0.052 | D36: =IF($A36="",0,$B36*IFERROR(INDEX('Ingredient Database'!$G:$G,MATCH($A36,'Ingredient Database'!$B:$B,0)),0)) -> 0.442 | E36: =IF($A36="",0,$B36*IFERROR(INDEX('Ingredient Database'!$E:$E,MATCH($A36,'Ingredient Database'!$B:$B,0)),0)) -> 0.208 | F36: =IF($A36="",0,$B36*IFERROR(INDEX('Ingredient Database'!$H:$H,MATCH($A36,'Ingredient Database'!$B:$B,0)),0)) -> 1.46302
A37: Wheat Straw (Bhoosa) | B37: 0.35 | C37: =IF($A37="",0,$B37*IFERROR(INDEX('Ingredient Database'!$F:$F,MATCH($A37,'Ingredient Database'!$B:$B,0)),0)) -> 0.014 | D37: =IF($A37="",0,$B37*IFERROR(INDEX('Ingredient Database'!$G:$G,MATCH($A37,'Ingredient Database'!$B:$B,0)),0)) -> 0.147 | E37: =IF($A37="",0,$B37*IFERROR(INDEX('Ingredient Database'!$E:$E,MATCH($A37,'Ingredient Database'!$B:$B,0)),0)) -> 0.315 | F37: =IF($A37="",0,$B37*IFERROR(INDEX('Ingredient Database'!$H:$H,MATCH($A37,'Ingredient Database'!$B:$B,0)),0)) -> 0.38955
C38: =IF($A38="",0,$B38*IFERROR(INDEX('Ingredient Database'!$F:$F,MATCH($A38,'Ingredient Database'!$B:$B,0)),0)) -> 0 | D38: =IF($A38="",0,$B38*IFERROR(INDEX('Ingredient Database'!$G:$G,MATCH($A38,'Ingredient Database'!$B:$B,0)),0)) -> 0 | E38: =IF($A38="",0,$B38*IFERROR(INDEX('Ingredient Database'!$E:$E,MATCH($A38,'Ingredient Database'!$B:$B,0)),0)) -> 0 | F38: =IF($A38="",0,$B38*IFERROR(INDEX('Ingredient Database'!$H:$H,MATCH($A38,'Ingredient Database'!$B:$B,0)),0)) -> 0
C39: =IF($A39="",0,$B39*IFERROR(INDEX('Ingredient Database'!$F:$F,MATCH($A39,'Ingredient Database'!$B:$B,0)),0)) -> 0 | D39: =IF($A39="",0,$B39*IFERROR(INDEX('Ingredient Database'!$G:$G,MATCH($A39,'Ingredient Database'!$B:$B,0)),0)) -> 0 | E39: =IF($A39="",0,$B39*IFERROR(INDEX('Ingredient Database'!$E:$E,MATCH($A39,'Ingredient Database'!$B:$B,0)),0)) -> 0 | F39: =IF($A39="",0,$B39*IFERROR(INDEX('Ingredient Database'!$H:$H,MATCH($A39,'Ingredient Database'!$B:$B,0)),0)) -> 0
C40: =IF($A40="",0,$B40*IFERROR(INDEX('Ingredient Database'!$F:$F,MATCH($A40,'Ingredient Database'!$B:$B,0)),0)) -> 0 | D40: =IF($A40="",0,$B40*IFERROR(INDEX('Ingredient Database'!$G:$G,MATCH($A40,'Ingredient Database'!$B:$B,0)),0)) -> 0 | E40: =IF($A40="",0,$B40*IFERROR(INDEX('Ingredient Database'!$E:$E,MATCH($A40,'Ingredient Database'!$B:$B,0)),0)) -> 0 | F40: =IF($A40="",0,$B40*IFERROR(INDEX('Ingredient Database'!$H:$H,MATCH($A40,'Ingredient Database'!$B:$B,0)),0)) -> 0
C41: =IF($A41="",0,$B41*IFERROR(INDEX('Ingredient Database'!$F:$F,MATCH($A41,'Ingredient Database'!$B:$B,0)),0)) -> 0 | D41: =IF($A41="",0,$B41*IFERROR(INDEX('Ingredient Database'!$G:$G,MATCH($A41,'Ingredient Database'!$B:$B,0)),0)) -> 0 | E41: =IF($A41="",0,$B41*IFERROR(INDEX('Ingredient Database'!$E:$E,MATCH($A41,'Ingredient Database'!$B:$B,0)),0)) -> 0 | F41: =IF($A41="",0,$B41*IFERROR(INDEX('Ingredient Database'!$H:$H,MATCH($A41,'Ingredient Database'!$B:$B,0)),0)) -> 0
A42: TOTAL | B42: =SUM(B36:B41) -> 1 | C42: =SUM(C36:C41) -> 0.066 | D42: =SUM(D36:D41) -> 0.589 | E42: =SUM(E36:E41) -> 0.523 | F42: =SUM(F36:F41) -> 1.85257
A44: Phase 3 - Finishing
A45: Ingredient (dropdown) | B45: % of Total Roughage | C45: CP Contribution | D45: TDN Contribution | E45: DM Contribution | F45: Energy Contribution (Mcal)
A46: Maize Silage | B46: 0.8 | C46: =IF($A46="",0,$B46*IFERROR(INDEX('Ingredient Database'!$F:$F,MATCH($A46,'Ingredient Database'!$B:$B,0)),0)) -> 0.064 | D46: =IF($A46="",0,$B46*IFERROR(INDEX('Ingredient Database'!$G:$G,MATCH($A46,'Ingredient Database'!$B:$B,0)),0)) -> 0.544 | E46: =IF($A46="",0,$B46*IFERROR(INDEX('Ingredient Database'!$E:$E,MATCH($A46,'Ingredient Database'!$B:$B,0)),0)) -> 0.256 | F46: =IF($A46="",0,$B46*IFERROR(INDEX('Ingredient Database'!$H:$H,MATCH($A46,'Ingredient Database'!$B:$B,0)),0)) -> 1.80064
A47: Wheat Straw (Bhoosa) | B47: 0.2 | C47: =IF($A47="",0,$B47*IFERROR(INDEX('Ingredient Database'!$F:$F,MATCH($A47,'Ingredient Database'!$B:$B,0)),0)) -> 0.008 | D47: =IF($A47="",0,$B47*IFERROR(INDEX('Ingredient Database'!$G:$G,MATCH($A47,'Ingredient Database'!$B:$B,0)),0)) -> 0.084 | E47: =IF($A47="",0,$B47*IFERROR(INDEX('Ingredient Database'!$E:$E,MATCH($A47,'Ingredient Database'!$B:$B,0)),0)) -> 0.18 | F47: =IF($A47="",0,$B47*IFERROR(INDEX('Ingredient Database'!$H:$H,MATCH($A47,'Ingredient Database'!$B:$B,0)),0)) -> 0.2226
C48: =IF($A48="",0,$B48*IFERROR(INDEX('Ingredient Database'!$F:$F,MATCH($A48,'Ingredient Database'!$B:$B,0)),0)) -> 0 | D48: =IF($A48="",0,$B48*IFERROR(INDEX('Ingredient Database'!$G:$G,MATCH($A48,'Ingredient Database'!$B:$B,0)),0)) -> 0 | E48: =IF($A48="",0,$B48*IFERROR(INDEX('Ingredient Database'!$E:$E,MATCH($A48,'Ingredient Database'!$B:$B,0)),0)) -> 0 | F48: =IF($A48="",0,$B48*IFERROR(INDEX('Ingredient Database'!$H:$H,MATCH($A48,'Ingredient Database'!$B:$B,0)),0)) -> 0
C49: =IF($A49="",0,$B49*IFERROR(INDEX('Ingredient Database'!$F:$F,MATCH($A49,'Ingredient Database'!$B:$B,0)),0)) -> 0 | D49: =IF($A49="",0,$B49*IFERROR(INDEX('Ingredient Database'!$G:$G,MATCH($A49,'Ingredient Database'!$B:$B,0)),0)) -> 0 | E49: =IF($A49="",0,$B49*IFERROR(INDEX('Ingredient Database'!$E:$E,MATCH($A49,'Ingredient Database'!$B:$B,0)),0)) -> 0 | F49: =IF($A49="",0,$B49*IFERROR(INDEX('Ingredient Database'!$H:$H,MATCH($A49,'Ingredient Database'!$B:$B,0)),0)) -> 0
C50: =IF($A50="",0,$B50*IFERROR(INDEX('Ingredient Database'!$F:$F,MATCH($A50,'Ingredient Database'!$B:$B,0)),0)) -> 0 | D50: =IF($A50="",0,$B50*IFERROR(INDEX('Ingredient Database'!$G:$G,MATCH($A50,'Ingredient Database'!$B:$B,0)),0)) -> 0 | E50: =IF($A50="",0,$B50*IFERROR(INDEX('Ingredient Database'!$E:$E,MATCH($A50,'Ingredient Database'!$B:$B,0)),0)) -> 0 | F50: =IF($A50="",0,$B50*IFERROR(INDEX('Ingredient Database'!$H:$H,MATCH($A50,'Ingredient Database'!$B:$B,0)),0)) -> 0
C51: =IF($A51="",0,$B51*IFERROR(INDEX('Ingredient Database'!$F:$F,MATCH($A51,'Ingredient Database'!$B:$B,0)),0)) -> 0 | D51: =IF($A51="",0,$B51*IFERROR(INDEX('Ingredient Database'!$G:$G,MATCH($A51,'Ingredient Database'!$B:$B,0)),0)) -> 0 | E51: =IF($A51="",0,$B51*IFERROR(INDEX('Ingredient Database'!$E:$E,MATCH($A51,'Ingredient Database'!$B:$B,0)),0)) -> 0 | F51: =IF($A51="",0,$B51*IFERROR(INDEX('Ingredient Database'!$H:$H,MATCH($A51,'Ingredient Database'!$B:$B,0)),0)) -> 0
A52: TOTAL | B52: =SUM(B46:B51) -> 1 | C52: =SUM(C46:C51) -> 0.072 | D52: =SUM(D46:D51) -> 0.628 | E52: =SUM(E46:E51) -> 0.436 | F52: =SUM(F46:F51) -> 2.02324
A54: C-Summary) Roughage Blend Value by Phase (auto, from tables above)
A55: Phase | B55: Roughage CP % | C55: Roughage TDN % | D55: Roughage DM % | E55: Roughage Energy (Mcal/kg)
A56: Phase 1 - Adaptation | B56: =C32 -> 0.06 | C56: =D32 -> 0.55 | D56: =E32 -> 0.61 | E56: =F32 -> 1.6819
A57: Phase 2 - Growth | B57: =C42 -> 0.066 | C57: =D42 -> 0.589 | D57: =E42 -> 0.523 | E57: =F42 -> 1.85257
A58: Phase 3 - Finishing | B58: =C52 -> 0.072 | C58: =D52 -> 0.628 | D58: =E52 -> 0.436 | E58: =F52 -> 2.02324
A60: D) FULL TMR RATION — Combined Nutrient Value vs Target (by Phase)
A61: Phase | B61: Concentrate % of DM | C61: Roughage % of DM | D61: Ration CP % | E61: Ration TDN % | F61: Ration DM % | G61: Ration Energy (Mcal/kg) | H61: Target CP % | I61: Target TDN % | J61: Status
A62: =A5 -> Phase 1 - Adaptation | B62: =D5 -> 0.45 | C62: =E5 -> 0.55 | D62: =B62*$C$21+C62*B56 -> 0.10734 | E62: =B62*$D$21+C62*C56 -> 0.61354 | F62: =B62*$E$21+C62*D56 -> 0.73366 | G62: =B62*$F$21+C62*E56 -> 2.0510098 | H62: 0.11 | I62: 0.61 | J62: =IF(AND(D62>=H62*0.95,E62>=I62*0.95),"OK - Target Met","Adjust Blend") -> OK - Target Met
A63: =A6 -> Phase 2 - Growth | B63: =D6 -> 0.6 | C63: =E6 -> 0.4 | D63: =B63*$C$21+C63*B57 -> 0.12552 | E63: =B63*$D$21+C63*C57 -> 0.65032 | F63: =B63*$E$21+C63*D57 -> 0.74008 | G63: =B63*$F$21+C63*E57 -> 2.2423144 | H63: 0.125 | I63: 0.65 | J63: =IF(AND(D63>=H63*0.95,E63>=I63*0.95),"OK - Target Met","Adjust Blend") -> OK - Target Met
A64: =A7 -> Phase 3 - Finishing | B64: =D7 -> 0.75 | C64: =E7 -> 0.25 | D64: =B64*$C$21+C64*B58 -> 0.1419 | E64: =B64*$D$21+C64*C58 -> 0.6754 | F64: =B64*$E$21+C64*D58 -> 0.7726 | G64: =B64*$F$21+C64*E58 -> 2.382418 | H64: 0.14 | I64: 0.675 | J64: =IF(AND(D64>=H64*0.95,E64>=I64*0.95),"OK - Target Met","Adjust Blend") -> OK - Target Met
A65: Note: Target CP/TDN yellow cells mein aap apna desired target daal sakte hain — Status column khud bata dega. Roughage Mix tables mein har phase ka % Total 100% hona chahiye (agar nahi hai to us row ka Total cell laal ho jayega).

Sheet Animal Register
A1: ANIMAL REGISTER
A2: Ek hi register — Purpose column se Fattening/Qurbani/Dairy/Breeding Stock decide hota hai. Apna tag-number convention (jaise MB66, MC217) Animal ID mein use kar sakte hain.
A4: Animal ID | B4: Purpose | C4: Breed | D4: Sex | E4: Source | F4: Date of Birth / Acquired | G4: Sire ID | H4: Dam ID | I4: Acquisition / Birth Weight (kg) | J4: Acquisition Cost (Rs) | K4: Program Start Date | L4: Program Duration (days) | M4: Target ADG (g/day) | N4: Program End Date | O4: Days on Feed | P4: Current Phase | Q4: Status | R4: Notes | S4: Current Weight (kg) | T4: Gain So Far (kg) | U4: Qurbani Rank | V4: Dairy Rank | W4: Breeding Rank
A5: A-01 | B5: Fattening | C5: Mix Breed | D5: Male | E5: Purchased - Mandi | F5: 46240 | I5: 212 | J5: 48000 | K5: 46240 | L5: 100 | M5: 1150 | N5: =IF(OR($K5="",$L5=""),"",$K5+$L5) -> 46340 | O5: =IF(OR($K5="",$L5=""),"",IF($Q5="Sold",$L5,MIN($L5,MAX(0,TODAY()-$K5)))) -> 9 | P5: =IF(OR($K5="",$L5=""),"",IF(O5<=$L5*0.33,"Phase 1 - Adaptation",IF(O5<=$L5*0.66,"Phase 2 - Growth","Phase 3 - Finishing"))) -> Phase 1 - Adaptation | Q5: Active | R5: Example row - apna data yahan se neeche likhna shuru karein | S5: =IF($A5="","",IF(SUMPRODUCT(MAX(('Weight Log'!$A$5:$A$154=$A5)*('Weight Log'!$C$5:$C$154)))=0,$I5,SUMPRODUCT(MAX(('Weight Log'!$A$5:$A$154=$A5)*('Weight Log'!$C$5:$C$154))))) -> 212 | T5: =IF($A5="","",S5-I5) -> 0 | U5: =IF($B5="Qurbani",COUNTIF($B$5:$B5,"Qurbani"),"") | V5: =IF($B5="Dairy",COUNTIF($B$5:$B5,"Dairy"),"") | W5: =IF($B5="Breeding Stock",COUNTIF($B$5:$B5,"Breeding Stock"),"")
N6: =IF(OR($K6="",$L6=""),"",$K6+$L6) | O6: =IF(OR($K6="",$L6=""),"",IF($Q6="Sold",$L6,MIN($L6,MAX(0,TODAY()-$K6)))) | P6: =IF(OR($K6="",$L6=""),"",IF(O6<=$L6*0.33,"Phase 1 - Adaptation",IF(O6<=$L6*0.66,"Phase 2 - Growth","Phase 3 - Finishing"))) | S6: =IF($A6="","",IF(SUMPRODUCT(MAX(('Weight Log'!$A$5:$A$154=$A6)*('Weight Log'!$C$5:$C$154)))=0,$I6,SUMPRODUCT(MAX(('Weight Log'!$A$5:$A$154=$A6)*('Weight Log'!$C$5:$C$154))))) | T6: =IF($A6="","",S6-I6) | U6: =IF($B6="Qurbani",COUNTIF($B$5:$B6,"Qurbani"),"") | V6: =IF($B6="Dairy",COUNTIF($B$5:$B6,"Dairy"),"") | W6: =IF($B6="Breeding Stock",COUNTIF($B$5:$B6,"Breeding Stock"),"")
N7: =IF(OR($K7="",$L7=""),"",$K7+$L7) | O7: =IF(OR($K7="",$L7=""),"",IF($Q7="Sold",$L7,MIN($L7,MAX(0,TODAY()-$K7)))) | P7: =IF(OR($K7="",$L7=""),"",IF(O7<=$L7*0.33,"Phase 1 - Adaptation",IF(O7<=$L7*0.66,"Phase 2 - Growth","Phase 3 - Finishing"))) | S7: =IF($A7="","",IF(SUMPRODUCT(MAX(('Weight Log'!$A$5:$A$154=$A7)*('Weight Log'!$C$5:$C$154)))=0,$I7,SUMPRODUCT(MAX(('Weight Log'!$A$5:$A$154=$A7)*('Weight Log'!$C$5:$C$154))))) | T7: =IF($A7="","",S7-I7) | U7: =IF($B7="Qurbani",COUNTIF($B$5:$B7,"Qurbani"),"") | V7: =IF($B7="Dairy",COUNTIF($B$5:$B7,"Dairy"),"") | W7: =IF($B7="Breeding Stock",COUNTIF($B$5:$B7,"Breeding Stock"),"")
N8: =IF(OR($K8="",$L8=""),"",$K8+$L8) | O8: =IF(OR($K8="",$L8=""),"",IF($Q8="Sold",$L8,MIN($L8,MAX(0,TODAY()-$K8)))) | P8: =IF(OR($K8="",$L8=""),"",IF(O8<=$L8*0.33,"Phase 1 - Adaptation",IF(O8<=$L8*0.66,"Phase 2 - Growth","Phase 3 - Finishing"))) | S8: =IF($A8="","",IF(SUMPRODUCT(MAX(('Weight Log'!$A$5:$A$154=$A8)*('Weight Log'!$C$5:$C$154)))=0,$I8,SUMPRODUCT(MAX(('Weight Log'!$A$5:$A$154=$A8)*('Weight Log'!$C$5:$C$154))))) | T8: =IF($A8="","",S8-I8) | U8: =IF($B8="Qurbani",COUNTIF($B$5:$B8,"Qurbani"),"") | V8: =IF($B8="Dairy",COUNTIF($B$5:$B8,"Dairy"),"") | W8: =IF($B8="Breeding Stock",COUNTIF($B$5:$B8,"Breeding Stock"),"")
N9: =IF(OR($K9="",$L9=""),"",$K9+$L9) | O9: =IF(OR($K9="",$L9=""),"",IF($Q9="Sold",$L9,MIN($L9,MAX(0,TODAY()-$K9)))) | P9: =IF(OR($K9="",$L9=""),"",IF(O9<=$L9*0.33,"Phase 1 - Adaptation",IF(O9<=$L9*0.66,"Phase 2 - Growth","Phase 3 - Finishing"))) | S9: =IF($A9="","",IF(SUMPRODUCT(MAX(('Weight Log'!$A$5:$A$154=$A9)*('Weight Log'!$C$5:$C$154)))=0,$I9,SUMPRODUCT(MAX(('Weight Log'!$A$5:$A$154=$A9)*('Weight Log'!$C$5:$C$154))))) | T9: =IF($A9="","",S9-I9) | U9: =IF($B9="Qurbani",COUNTIF($B$5:$B9,"Qurbani"),"") | V9: =IF($B9="Dairy",COUNTIF($B$5:$B9,"Dairy"),"") | W9: =IF($B9="Breeding Stock",COUNTIF($B$5:$B9,"Breeding Stock"),"")
N10: =IF(OR($K10="",$L10=""),"",$K10+$L10) | O10: =IF(OR($K10="",$L10=""),"",IF($Q10="Sold",$L10,MIN($L10,MAX(0,TODAY()-$K10)))) | P10: =IF(OR($K10="",$L10=""),"",IF(O10<=$L10*0.33,"Phase 1 - Adaptation",IF(O10<=$L10*0.66,"Phase 2 - Growth","Phase 3 - Finishing"))) | S10: =IF($A10="","",IF(SUMPRODUCT(MAX(('Weight Log'!$A$5:$A$154=$A10)*('Weight Log'!$C$5:$C$154)))=0,$I10,SUMPRODUCT(MAX(('Weight Log'!$A$5:$A$154=$A10)*('Weight Log'!$C$5:$C$154))))) | T10: =IF($A10="","",S10-I10) | U10: =IF($B10="Qurbani",COUNTIF($B$5:$B10,"Qurbani"),"") | V10: =IF($B10="Dairy",COUNTIF($B$5:$B10,"Dairy"),"") | W10: =IF($B10="Breeding Stock",COUNTIF($B$5:$B10,"Breeding Stock"),"")
N11: =IF(OR($K11="",$L11=""),"",$K11+$L11) | O11: =IF(OR($K11="",$L11=""),"",IF($Q11="Sold",$L11,MIN($L11,MAX(0,TODAY()-$K11)))) | P11: =IF(OR($K11="",$L11=""),"",IF(O11<=$L11*0.33,"Phase 1 - Adaptation",IF(O11<=$L11*0.66,"Phase 2 - Growth","Phase 3 - Finishing"))) | S11: =IF($A11="","",IF(SUMPRODUCT(MAX(('Weight Log'!$A$5:$A$154=$A11)*('Weight Log'!$C$5:$C$154)))=0,$I11,SUMPRODUCT(MAX(('Weight Log'!$A$5:$A$154=$A11)*('Weight Log'!$C$5:$C$154))))) | T11: =IF($A11="","",S11-I11) | U11: =IF($B11="Qurbani",COUNTIF($B$5:$B11,"Qurbani"),"") | V11: =IF($B11="Dairy",COUNTIF($B$5:$B11,"Dairy"),"") | W11: =IF($B11="Breeding Stock",COUNTIF($B$5:$B11,"Breeding Stock"),"")
N12: =IF(OR($K12="",$L12=""),"",$K12+$L12) | O12: =IF(OR($K12="",$L12=""),"",IF($Q12="Sold",$L12,MIN($L12,MAX(0,TODAY()-$K12)))) | P12: =IF(OR($K12="",$L12=""),"",IF(O12<=$L12*0.33,"Phase 1 - Adaptation",IF(O12<=$L12*0.66,"Phase 2 - Growth","Phase 3 - Finishing"))) | S12: =IF($A12="","",IF(SUMPRODUCT(MAX(('Weight Log'!$A$5:$A$154=$A12)*('Weight Log'!$C$5:$C$154)))=0,$I12,SUMPRODUCT(MAX(('Weight Log'!$A$5:$A$154=$A12)*('Weight Log'!$C$5:$C$154))))) | T12: =IF($A12="","",S12-I12) | U12: =IF($B12="Qurbani",COUNTIF($B$5:$B12,"Qurbani"),"") | V12: =IF($B12="Dairy",COUNTIF($B$5:$B12,"Dairy"),"") | W12: =IF($B12="Breeding Stock",COUNTIF($B$5:$B12,"Breeding Stock"),"")
N13: =IF(OR($K13="",$L13=""),"",$K13+$L13) | O13: =IF(OR($K13="",$L13=""),"",IF($Q13="Sold",$L13,MIN($L13,MAX(0,TODAY()-$K13)))) | P13: =IF(OR($K13="",$L13=""),"",IF(O13<=$L13*0.33,"Phase 1 - Adaptation",IF(O13<=$L13*0.66,"Phase 2 - Growth","Phase 3 - Finishing"))) | S13: =IF($A13="","",IF(SUMPRODUCT(MAX(('Weight Log'!$A$5:$A$154=$A13)*('Weight Log'!$C$5:$C$154)))=0,$I13,SUMPRODUCT(MAX(('Weight Log'!$A$5:$A$154=$A13)*('Weight Log'!$C$5:$C$154))))) | T13: =IF($A13="","",S13-I13) | U13: =IF($B13="Qurbani",COUNTIF($B$5:$B13,"Qurbani"),"") | V13: =IF($B13="Dairy",COUNTIF($B$5:$B13,"Dairy"),"") | W13: =IF($B13="Breeding Stock",COUNTIF($B$5:$B13,"Breeding Stock"),"")
N14: =IF(OR($K14="",$L14=""),"",$K14+$L14) | O14: =IF(OR($K14="",$L14=""),"",IF($Q14="Sold",$L14,MIN($L14,MAX(0,TODAY()-$K14)))) | P14: =IF(OR($K14="",$L14=""),"",IF(O14<=$L14*0.33,"Phase 1 - Adaptation",IF(O14<=$L14*0.66,"Phase 2 - Growth","Phase 3 - Finishing"))) | S14: =IF($A14="","",IF(SUMPRODUCT(MAX(('Weight Log'!$A$5:$A$154=$A14)*('Weight Log'!$C$5:$C$154)))=0,$I14,SUMPRODUCT(MAX(('Weight Log'!$A$5:$A$154=$A14)*('Weight Log'!$C$5:$C$154))))) | T14: =IF($A14="","",S14-I14) | U14: =IF($B14="Qurbani",COUNTIF($B$5:$B14,"Qurbani"),"") | V14: =IF($B14="Dairy",COUNTIF($B$5:$B14,"Dairy"),"") | W14: =IF($B14="Breeding Stock",COUNTIF($B$5:$B14,"Breeding Stock"),"")
N15: =IF(OR($K15="",$L15=""),"",$K15+$L15) | O15: =IF(OR($K15="",$L15=""),"",IF($Q15="Sold",$L15,MIN($L15,MAX(0,TODAY()-$K15)))) | P15: =IF(OR($K15="",$L15=""),"",IF(O15<=$L15*0.33,"Phase 1 - Adaptation",IF(O15<=$L15*0.66,"Phase 2 - Growth","Phase 3 - Finishing"))) | S15: =IF($A15="","",IF(SUMPRODUCT(MAX(('Weight Log'!$A$5:$A$154=$A15)*('Weight Log'!$C$5:$C$154)))=0,$I15,SUMPRODUCT(MAX(('Weight Log'!$A$5:$A$154=$A15)*('Weight Log'!$C$5:$C$154))))) | T15: =IF($A15="","",S15-I15) | U15: =IF($B15="Qurbani",COUNTIF($B$5:$B15,"Qurbani"),"") | V15: =IF($B15="Dairy",COUNTIF($B$5:$B15,"Dairy"),"") | W15: =IF($B15="Breeding Stock",COUNTIF($B$5:$B15,"Breeding Stock"),"")
N16: =IF(OR($K16="",$L16=""),"",$K16+$L16) | O16: =IF(OR($K16="",$L16=""),"",IF($Q16="Sold",$L16,MIN($L16,MAX(0,TODAY()-$K16)))) | P16: =IF(OR($K16="",$L16=""),"",IF(O16<=$L16*0.33,"Phase 1 - Adaptation",IF(O16<=$L16*0.66,"Phase 2 - Growth","Phase 3 - Finishing"))) | S16: =IF($A16="","",IF(SUMPRODUCT(MAX(('Weight Log'!$A$5:$A$154=$A16)*('Weight Log'!$C$5:$C$154)))=0,$I16,SUMPRODUCT(MAX(('Weight Log'!$A$5:$A$154=$A16)*('Weight Log'!$C$5:$C$154))))) | T16: =IF($A16="","",S16-I16) | U16: =IF($B16="Qurbani",COUNTIF($B$5:$B16,"Qurbani"),"") | V16: =IF($B16="Dairy",COUNTIF($B$5:$B16,"Dairy"),"") | W16: =IF($B16="Breeding Stock",COUNTIF($B$5:$B16,"Breeding Stock"),"")
N17: =IF(OR($K17="",$L17=""),"",$K17+$L17) | O17: =IF(OR($K17="",$L17=""),"",IF($Q17="Sold",$L17,MIN($L17,MAX(0,TODAY()-$K17)))) | P17: =IF(OR($K17="",$L17=""),"",IF(O17<=$L17*0.33,"Phase 1 - Adaptation",IF(O17<=$L17*0.66,"Phase 2 - Growth","Phase 3 - Finishing"))) | S17: =IF($A17="","",IF(SUMPRODUCT(MAX(('Weight Log'!$A$5:$A$154=$A17)*('Weight Log'!$C$5:$C$154)))=0,$I17,SUMPRODUCT(MAX(('Weight Log'!$A$5:$A$154=$A17)*('Weight Log'!$C$5:$C$154))))) | T17: =IF($A17="","",S17-I17) | U17: =IF($B17="Qurbani",COUNTIF($B$5:$B17,"Qurbani"),"") | V17: =IF($B17="Dairy",COUNTIF($B$5:$B17,"Dairy"),"") | W17: =IF($B17="Breeding Stock",COUNTIF($B$5:$B17,"Breeding Stock"),"")
... N74: =IF(OR($K74="",$L74=""),"",$K74+$L74) | O74: =IF(OR($K74="",$L74=""),"",IF($Q74="Sold",$L74,MIN($L74,MAX(0,TODAY()-$K74)))) | P74: =IF(OR($K74="",$L74=""),"",IF(O74<=$L74*0.33,"Phase 1 - Adaptation",IF(O74<=$L74*0.66,"Phase 2 - Growth","Phase 3 - Finishing"))) | S74: =IF($A74="","",IF(SUMPRODUCT(MAX(('Weight Log'!$A$5:$A$154=$A74)*('Weight Log'!$C$5:$C$154)))=0,$I74,SUMPRODUCT(MAX(('Weight Log'!$A$5:$A$154=$A74)*('Weight Log'!$C$5:$C$154))))) | T74: =IF($A74="","",S74-I74) | U74: =IF($B74="Qurbani",COUNTIF($B$5:$B74,"Qurbani"),"") | V74: =IF($B74="Dairy",COUNTIF($B$5:$B74,"Dairy"),"") | W74: =IF($B74="Breeding Stock",COUNTIF($B$5:$B74,"Breeding Stock"),"")

Sheet Animal Profile
A1: ANIMAL PROFILE
A2: Neeche dropdown se Animal ID chunein — is animal ka poora record khud aa jayega.
A4: Select Animal ID: | B4: A-01
A6: BASIC INFO
A7: Purpose | B7: =IF($B$4="","",IFERROR(INDEX('Animal Register'!$B:$B,MATCH($B$4,'Animal Register'!$A:$A,0)),"-")) -> Fattening
A8: Breed | B8: =IF($B$4="","",IFERROR(INDEX('Animal Register'!$C:$C,MATCH($B$4,'Animal Register'!$A:$A,0)),"-")) -> Mix Breed
A9: Sex | B9: =IF($B$4="","",IFERROR(INDEX('Animal Register'!$D:$D,MATCH($B$4,'Animal Register'!$A:$A,0)),"-")) -> Male
A10: Source | B10: =IF($B$4="","",IFERROR(INDEX('Animal Register'!$E:$E,MATCH($B$4,'Animal Register'!$A:$A,0)),"-")) -> Purchased - Mandi
A11: Date of Birth / Acquired | B11: =IF($B$4="","",IFERROR(INDEX('Animal Register'!$F:$F,MATCH($B$4,'Animal Register'!$A:$A,0)),"-")) -> 46240
A12: Sire ID | B12: =IF($B$4="","",IF(IFERROR(INDEX('Animal Register'!$G:$G,MATCH($B$4,'Animal Register'!$A:$A,0)),"")="","-",INDEX('Animal Register'!$G:$G,MATCH($B$4,'Animal Register'!$A:$A,0)))) -> -
A13: Dam ID | B13: =IF($B$4="","",IF(IFERROR(INDEX('Animal Register'!$H:$H,MATCH($B$4,'Animal Register'!$A:$A,0)),"")="","-",INDEX('Animal Register'!$H:$H,MATCH($B$4,'Animal Register'!$A:$A,0)))) -> -
A14: Acquisition Cost (Rs) | B14: =IF($B$4="","",IFERROR(INDEX('Animal Register'!$J:$J,MATCH($B$4,'Animal Register'!$A:$A,0)),"-")) -> 48000
A15: Status | B15: =IF($B$4="","",IFERROR(INDEX('Animal Register'!$Q:$Q,MATCH($B$4,'Animal Register'!$A:$A,0)),"-")) -> Active
A16: Notes | B16: =IF($B$4="","",IFERROR(INDEX('Animal Register'!$R:$R,MATCH($B$4,'Animal Register'!$A:$A,0)),"-")) -> Example row - apna data yahan se neeche likhna shuru karein
A18: FATTENING / QURBANI PROGRAM (Dairy/Breeding Stock ke liye khali rahega)
A19: Program Start Date | B19: =IF($B$4="","",IFERROR(INDEX('Animal Register'!$K:$K,MATCH($B$4,'Animal Register'!$A:$A,0)),"-")) -> 46240
A20: Program Duration (days) | B20: =IF($B$4="","",IFERROR(INDEX('Animal Register'!$L:$L,MATCH($B$4,'Animal Register'!$A:$A,0)),"-")) -> 100
A21: Program End Date | B21: =IF($B$4="","",IFERROR(INDEX('Animal Register'!$N:$N,MATCH($B$4,'Animal Register'!$A:$A,0)),"-")) -> 46340
A22: Days on Feed | B22: =IF($B$4="","",IFERROR(INDEX('Animal Register'!$O:$O,MATCH($B$4,'Animal Register'!$A:$A,0)),"-")) -> 9
A23: Current Phase | B23: =IF($B$4="","",IFERROR(INDEX('Animal Register'!$P:$P,MATCH($B$4,'Animal Register'!$A:$A,0)),"-")) -> Phase 1 - Adaptation
A25: WEIGHT SUMMARY
A26: Acquisition / Birth Weight (kg) | B26: =IF($B$4="","",IFERROR(INDEX('Animal Register'!$I:$I,MATCH($B$4,'Animal Register'!$A:$A,0)),"-")) -> 212
A27: Current Weight (kg) | B27: =IF($B$4="","",IFERROR(INDEX('Animal Register'!$S:$S,MATCH($B$4,'Animal Register'!$A:$A,0)),"-")) -> 212
A28: Total Gain (kg) | B28: =IF($B$4="","",IFERROR(INDEX('Animal Register'!$T:$T,MATCH($B$4,'Animal Register'!$A:$A,0)),"-")) -> 0
A29: Target ADG (g/day) | B29: =IF($B$4="","",IFERROR(INDEX('Animal Register'!$M:$M,MATCH($B$4,'Animal Register'!$A:$A,0)),"-")) -> 1150
A30: Overall ADG (g/day) | B30: =IF($B$4="","",IFERROR(INDEX('Weight & Growth Tracker'!$J:$J,MATCH($B$4,'Weight & Growth Tracker'!$A:$A,0)),"-")) -> 0
A31: Last Weighing Date | B31: =IF($B$4="","",IFERROR(INDEX('Weight & Growth Tracker'!$F:$F,MATCH($B$4,'Weight & Growth Tracker'!$A:$A,0)),"-")) -> 46240
A32: Latest BCS | B32: =IF($B$4="","",IFERROR(INDEX('Weight & Growth Tracker'!$G:$G,MATCH($B$4,'Weight & Growth Tracker'!$A:$A,0)),"-")) -> 2.5
A33: Growth Status | B33: =IF($B$4="","",IFERROR(INDEX('Weight & Growth Tracker'!$L:$L,MATCH($B$4,'Weight & Growth Tracker'!$A:$A,0)),"-")) -> Behind Target
A35: FEEDING SUMMARY
A36: Total Days Fed (entries logged) | B36: =IF($B$4="","",COUNTIF('Daily Feeding'!$B:$B,$B$4)) -> 1
A37: Total DM Feed Consumed (kg) | B37: =IF($B$4="","",ROUND(SUMIF('Daily Feeding'!$B:$B,$B$4,'Daily Feeding'!$I:$I)+SUMIF('Daily Feeding'!$B:$B,$B$4,'Daily Feeding'!$J:$J),1)) -> 6.4
A38: Avg Daily Energy Intake (Mcal) | B38: =IF($B$4="","",IFERROR(ROUND(AVERAGEIF('Daily Feeding'!$B:$B,$B$4,'Daily Feeding'!$M:$M),2),"-")) -> 13.04
A39: Total Feed Cost - this animal (Rs) | B39: =IF($B$4="","",ROUND(SUMIF('Cost Tracker'!$B:$B,$B$4,'Cost Tracker'!$F:$F),0)) -> 0
A41: HEALTH SUMMARY
A42: Total Treatments (count) | B42: =IF($B$4="","",COUNTIF('Health Log'!$A:$A,$B$4)) -> 1
A43: Last Treatment Date | B43: =IF($B$4="","",IF(SUMPRODUCT(MAX(('Health Log'!$A$4:$A$103=$B$4)*ROW('Health Log'!$A$4:$A$103)))=0,"-",INDEX('Health Log'!$B:$B,SUMPRODUCT(MAX(('Health Log'!$A$4:$A$103=$B$4)*ROW('Health Log'!$A$4:$A$103)))))) -> 46240
A44: Last Treatment Type | B44: =IF($B$4="","",IF(SUMPRODUCT(MAX(('Health Log'!$A$4:$A$103=$B$4)*ROW('Health Log'!$A$4:$A$103)))=0,"-",INDEX('Health Log'!$C:$C,SUMPRODUCT(MAX(('Health Log'!$A$4:$A$103=$B$4)*ROW('Health Log'!$A$4:$A$103)))))) -> Deworming
A45: Last Product / Medicine Used | B45: =IF($B$4="","",IF(SUMPRODUCT(MAX(('Health Log'!$A$4:$A$103=$B$4)*ROW('Health Log'!$A$4:$A$103)))=0,"-",INDEX('Health Log'!$D:$D,SUMPRODUCT(MAX(('Health Log'!$A$4:$A$103=$B$4)*ROW('Health Log'!$A$4:$A$103)))))) -> Example - apna medicine naam likhein
A46: Overdue Reminders (count) | B46: =IF($B$4="","",COUNTIFS('Health Log'!$A:$A,$B$4,'Health Log'!$F:$F,"<>",'Health Log'!$F:$F,"<"&TODAY())) -> 0

Sheet Qurbani Module
A1: QURBANI MODULE
A2: Animal Register mein jo bhi Purpose='Qurbani' likha jayega, wo yahan khud aa jayega. Naye Qurbani animals hamesha Animal Register ke aakhir mein add karein (beech mein insert na karein).
Q3: SALE / INVOICE LOG (yahan input karein)
A4: Animal ID | B4: Breed | C4: Purchase Date | D4: Purchase Weight (kg) | E4: Purchase Cost (Rs) | F4: Current Weight (kg) | G4: Days on Feed | H4: Target Sale Date | I4: Current Phase | J4: Sale Date | K4: Sale Weight (kg) | L4: Sale Price (Rs) | M4: Invoice No. | N4: Profit / Loss (Rs) | Q4: Animal ID | R4: Sale Date | S4: Sale Weight (kg) | T4: Sale Price (Rs) | U4: Invoice No.
A5: =IFERROR(INDEX('Animal Register'!$A:$A,MATCH(1,'Animal Register'!$U:$U,0)),"") | B5: =IF($A5="","",INDEX('Animal Register'!$C:$C,MATCH($A5,'Animal Register'!$A:$A,0))) | C5: =IF($A5="","",INDEX('Animal Register'!$K:$K,MATCH($A5,'Animal Register'!$A:$A,0))) | D5: =IF($A5="","",INDEX('Animal Register'!$I:$I,MATCH($A5,'Animal Register'!$A:$A,0))) | E5: =IF($A5="","",INDEX('Animal Register'!$J:$J,MATCH($A5,'Animal Register'!$A:$A,0))) | F5: =IF($A5="","",INDEX('Animal Register'!$S:$S,MATCH($A5,'Animal Register'!$A:$A,0))) | G5: =IF($A5="","",INDEX('Animal Register'!$O:$O,MATCH($A5,'Animal Register'!$A:$A,0))) | H5: =IF($A5="","",INDEX('Animal Register'!$N:$N,MATCH($A5,'Animal Register'!$A:$A,0))) | I5: =IF($A5="","",INDEX('Animal Register'!$P:$P,MATCH($A5,'Animal Register'!$A:$A,0))) | J5: =IF($A5="","",IFERROR(INDEX($R$5:$R$104,MATCH($A5,$Q$5:$Q$104,0)),"-")) | K5: =IF($A5="","",IFERROR(INDEX($S$5:$S$104,MATCH($A5,$Q$5:$Q$104,0)),"-")) | L5: =IF($A5="","",IFERROR(INDEX($T$5:$T$104,MATCH($A5,$Q$5:$Q$104,0)),"-")) | M5: =IF($A5="","",IFERROR(INDEX($U$5:$U$104,MATCH($A5,$Q$5:$Q$104,0)),"-")) | N5: =IF($A5="","",IF(ISNUMBER(L5),L5-E5,"-"))
A6: =IFERROR(INDEX('Animal Register'!$A:$A,MATCH(2,'Animal Register'!$U:$U,0)),"") | B6: =IF($A6="","",INDEX('Animal Register'!$C:$C,MATCH($A6,'Animal Register'!$A:$A,0))) | C6: =IF($A6="","",INDEX('Animal Register'!$K:$K,MATCH($A6,'Animal Register'!$A:$A,0))) | D6: =IF($A6="","",INDEX('Animal Register'!$I:$I,MATCH($A6,'Animal Register'!$A:$A,0))) | E6: =IF($A6="","",INDEX('Animal Register'!$J:$J,MATCH($A6,'Animal Register'!$A:$A,0))) | F6: =IF($A6="","",INDEX('Animal Register'!$S:$S,MATCH($A6,'Animal Register'!$A:$A,0))) | G6: =IF($A6="","",INDEX('Animal Register'!$O:$O,MATCH($A6,'Animal Register'!$A:$A,0))) | H6: =IF($A6="","",INDEX('Animal Register'!$N:$N,MATCH($A6,'Animal Register'!$A:$A,0))) | I6: =IF($A6="","",INDEX('Animal Register'!$P:$P,MATCH($A6,'Animal Register'!$A:$A,0))) | J6: =IF($A6="","",IFERROR(INDEX($R$5:$R$104,MATCH($A6,$Q$5:$Q$104,0)),"-")) | K6: =IF($A6="","",IFERROR(INDEX($S$5:$S$104,MATCH($A6,$Q$5:$Q$104,0)),"-")) | L6: =IF($A6="","",IFERROR(INDEX($T$5:$T$104,MATCH($A6,$Q$5:$Q$104,0)),"-")) | M6: =IF($A6="","",IFERROR(INDEX($U$5:$U$104,MATCH($A6,$Q$5:$Q$104,0)),"-")) | N6: =IF($A6="","",IF(ISNUMBER(L6),L6-E6,"-"))
A7: =IFERROR(INDEX('Animal Register'!$A:$A,MATCH(3,'Animal Register'!$U:$U,0)),"") | B7: =IF($A7="","",INDEX('Animal Register'!$C:$C,MATCH($A7,'Animal Register'!$A:$A,0))) | C7: =IF($A7="","",INDEX('Animal Register'!$K:$K,MATCH($A7,'Animal Register'!$A:$A,0))) | D7: =IF($A7="","",INDEX('Animal Register'!$I:$I,MATCH($A7,'Animal Register'!$A:$A,0))) | E7: =IF($A7="","",INDEX('Animal Register'!$J:$J,MATCH($A7,'Animal Register'!$A:$A,0))) | F7: =IF($A7="","",INDEX('Animal Register'!$S:$S,MATCH($A7,'Animal Register'!$A:$A,0))) | G7: =IF($A7="","",INDEX('Animal Register'!$O:$O,MATCH($A7,'Animal Register'!$A:$A,0))) | H7: =IF($A7="","",INDEX('Animal Register'!$N:$N,MATCH($A7,'Animal Register'!$A:$A,0))) | I7: =IF($A7="","",INDEX('Animal Register'!$P:$P,MATCH($A7,'Animal Register'!$A:$A,0))) | J7: =IF($A7="","",IFERROR(INDEX($R$5:$R$104,MATCH($A7,$Q$5:$Q$104,0)),"-")) | K7: =IF($A7="","",IFERROR(INDEX($S$5:$S$104,MATCH($A7,$Q$5:$Q$104,0)),"-")) | L7: =IF($A7="","",IFERROR(INDEX($T$5:$T$104,MATCH($A7,$Q$5:$Q$104,0)),"-")) | M7: =IF($A7="","",IFERROR(INDEX($U$5:$U$104,MATCH($A7,$Q$5:$Q$104,0)),"-")) | N7: =IF($A7="","",IF(ISNUMBER(L7),L7-E7,"-"))
A8: =IFERROR(INDEX('Animal Register'!$A:$A,MATCH(4,'Animal Register'!$U:$U,0)),"") | B8: =IF($A8="","",INDEX('Animal Register'!$C:$C,MATCH($A8,'Animal Register'!$A:$A,0))) | C8: =IF($A8="","",INDEX('Animal Register'!$K:$K,MATCH($A8,'Animal Register'!$A:$A,0))) | D8: =IF($A8="","",INDEX('Animal Register'!$I:$I,MATCH($A8,'Animal Register'!$A:$A,0))) | E8: =IF($A8="","",INDEX('Animal Register'!$J:$J,MATCH($A8,'Animal Register'!$A:$A,0))) | F8: =IF($A8="","",INDEX('Animal Register'!$S:$S,MATCH($A8,'Animal Register'!$A:$A,0))) | G8: =IF($A8="","",INDEX('Animal Register'!$O:$O,MATCH($A8,'Animal Register'!$A:$A,0))) | H8: =IF($A8="","",INDEX('Animal Register'!$N:$N,MATCH($A8,'Animal Register'!$A:$A,0))) | I8: =IF($A8="","",INDEX('Animal Register'!$P:$P,MATCH($A8,'Animal Register'!$A:$A,0))) | J8: =IF($A8="","",IFERROR(INDEX($R$5:$R$104,MATCH($A8,$Q$5:$Q$104,0)),"-")) | K8: =IF($A8="","",IFERROR(INDEX($S$5:$S$104,MATCH($A8,$Q$5:$Q$104,0)),"-")) | L8: =IF($A8="","",IFERROR(INDEX($T$5:$T$104,MATCH($A8,$Q$5:$Q$104,0)),"-")) | M8: =IF($A8="","",IFERROR(INDEX($U$5:$U$104,MATCH($A8,$Q$5:$Q$104,0)),"-")) | N8: =IF($A8="","",IF(ISNUMBER(L8),L8-E8,"-"))
A9: =IFERROR(INDEX('Animal Register'!$A:$A,MATCH(5,'Animal Register'!$U:$U,0)),"") | B9: =IF($A9="","",INDEX('Animal Register'!$C:$C,MATCH($A9,'Animal Register'!$A:$A,0))) | C9: =IF($A9="","",INDEX('Animal Register'!$K:$K,MATCH($A9,'Animal Register'!$A:$A,0))) | D9: =IF($A9="","",INDEX('Animal Register'!$I:$I,MATCH($A9,'Animal Register'!$A:$A,0))) | E9: =IF($A9="","",INDEX('Animal Register'!$J:$J,MATCH($A9,'Animal Register'!$A:$A,0))) | F9: =IF($A9="","",INDEX('Animal Register'!$S:$S,MATCH($A9,'Animal Register'!$A:$A,0))) | G9: =IF($A9="","",INDEX('Animal Register'!$O:$O,MATCH($A9,'Animal Register'!$A:$A,0))) | H9: =IF($A9="","",INDEX('Animal Register'!$N:$N,MATCH($A9,'Animal Register'!$A:$A,0))) | I9: =IF($A9="","",INDEX('Animal Register'!$P:$P,MATCH($A9,'Animal Register'!$A:$A,0))) | J9: =IF($A9="","",IFERROR(INDEX($R$5:$R$104,MATCH($A9,$Q$5:$Q$104,0)),"-")) | K9: =IF($A9="","",IFERROR(INDEX($S$5:$S$104,MATCH($A9,$Q$5:$Q$104,0)),"-")) | L9: =IF($A9="","",IFERROR(INDEX($T$5:$T$104,MATCH($A9,$Q$5:$Q$104,0)),"-")) | M9: =IF($A9="","",IFERROR(INDEX($U$5:$U$104,MATCH($A9,$Q$5:$Q$104,0)),"-")) | N9: =IF($A9="","",IF(ISNUMBER(L9),L9-E9,"-"))
A10: =IFERROR(INDEX('Animal Register'!$A:$A,MATCH(6,'Animal Register'!$U:$U,0)),"") | B10: =IF($A10="","",INDEX('Animal Register'!$C:$C,MATCH($A10,'Animal Register'!$A:$A,0))) | C10: =IF($A10="","",INDEX('Animal Register'!$K:$K,MATCH($A10,'Animal Register'!$A:$A,0))) | D10: =IF($A10="","",INDEX('Animal Register'!$I:$I,MATCH($A10,'Animal Register'!$A:$A,0))) | E10: =IF($A10="","",INDEX('Animal Register'!$J:$J,MATCH($A10,'Animal Register'!$A:$A,0))) | F10: =IF($A10="","",INDEX('Animal Register'!$S:$S,MATCH($A10,'Animal Register'!$A:$A,0))) | G10: =IF($A10="","",INDEX('Animal Register'!$O:$O,MATCH($A10,'Animal Register'!$A:$A,0))) | H10: =IF($A10="","",INDEX('Animal Register'!$N:$N,MATCH($A10,'Animal Register'!$A:$A,0))) | I10: =IF($A10="","",INDEX('Animal Register'!$P:$P,MATCH($A10,'Animal Register'!$A:$A,0))) | J10: =IF($A10="","",IFERROR(INDEX($R$5:$R$104,MATCH($A10,$Q$5:$Q$104,0)),"-")) | K10: =IF($A10="","",IFERROR(INDEX($S$5:$S$104,MATCH($A10,$Q$5:$Q$104,0)),"-")) | L10: =IF($A10="","",IFERROR(INDEX($T$5:$T$104,MATCH($A10,$Q$5:$Q$104,0)),"-")) | M10: =IF($A10="","",IFERROR(INDEX($U$5:$U$104,MATCH($A10,$Q$5:$Q$104,0)),"-")) | N10: =IF($A10="","",IF(ISNUMBER(L10),L10-E10,"-"))
A11: =IFERROR(INDEX('Animal Register'!$A:$A,MATCH(7,'Animal Register'!$U:$U,0)),"") | B11: =IF($A11="","",INDEX('Animal Register'!$C:$C,MATCH($A11,'Animal Register'!$A:$A,0))) | C11: =IF($A11="","",INDEX('Animal Register'!$K:$K,MATCH($A11,'Animal Register'!$A:$A,0))) | D11: =IF($A11="","",INDEX('Animal Register'!$I:$I,MATCH($A11,'Animal Register'!$A:$A,0))) | E11: =IF($A11="","",INDEX('Animal Register'!$J:$J,MATCH($A11,'Animal Register'!$A:$A,0))) | F11: =IF($A11="","",INDEX('Animal Register'!$S:$S,MATCH($A11,'Animal Register'!$A:$A,0))) | G11: =IF($A11="","",INDEX('Animal Register'!$O:$O,MATCH($A11,'Animal Register'!$A:$A,0))) | H11: =IF($A11="","",INDEX('Animal Register'!$N:$N,MATCH($A11,'Animal Register'!$A:$A,0))) | I11: =IF($A11="","",INDEX('Animal Register'!$P:$P,MATCH($A11,'Animal Register'!$A:$A,0))) | J11: =IF($A11="","",IFERROR(INDEX($R$5:$R$104,MATCH($A11,$Q$5:$Q$104,0)),"-")) | K11: =IF($A11="","",IFERROR(INDEX($S$5:$S$104,MATCH($A11,$Q$5:$Q$104,0)),"-")) | L11: =IF($A11="","",IFERROR(INDEX($T$5:$T$104,MATCH($A11,$Q$5:$Q$104,0)),"-")) | M11: =IF($A11="","",IFERROR(INDEX($U$5:$U$104,MATCH($A11,$Q$5:$Q$104,0)),"-")) | N11: =IF($A11="","",IF(ISNUMBER(L11),L11-E11,"-"))
A12: =IFERROR(INDEX('Animal Register'!$A:$A,MATCH(8,'Animal Register'!$U:$U,0)),"") | B12: =IF($A12="","",INDEX('Animal Register'!$C:$C,MATCH($A12,'Animal Register'!$A:$A,0))) | C12: =IF($A12="","",INDEX('Animal Register'!$K:$K,MATCH($A12,'Animal Register'!$A:$A,0))) | D12: =IF($A12="","",INDEX('Animal Register'!$I:$I,MATCH($A12,'Animal Register'!$A:$A,0))) | E12: =IF($A12="","",INDEX('Animal Register'!$J:$J,MATCH($A12,'Animal Register'!$A:$A,0))) | F12: =IF($A12="","",INDEX('Animal Register'!$S:$S,MATCH($A12,'Animal Register'!$A:$A,0))) | G12: =IF($A12="","",INDEX('Animal Register'!$O:$O,MATCH($A12,'Animal Register'!$A:$A,0))) | H12: =IF($A12="","",INDEX('Animal Register'!$N:$N,MATCH($A12,'Animal Register'!$A:$A,0))) | I12: =IF($A12="","",INDEX('Animal Register'!$P:$P,MATCH($A12,'Animal Register'!$A:$A,0))) | J12: =IF($A12="","",IFERROR(INDEX($R$5:$R$104,MATCH($A12,$Q$5:$Q$104,0)),"-")) | K12: =IF($A12="","",IFERROR(INDEX($S$5:$S$104,MATCH($A12,$Q$5:$Q$104,0)),"-")) | L12: =IF($A12="","",IFERROR(INDEX($T$5:$T$104,MATCH($A12,$Q$5:$Q$104,0)),"-")) | M12: =IF($A12="","",IFERROR(INDEX($U$5:$U$104,MATCH($A12,$Q$5:$Q$104,0)),"-")) | N12: =IF($A12="","",IF(ISNUMBER(L12),L12-E12,"-"))
A13: =IFERROR(INDEX('Animal Register'!$A:$A,MATCH(9,'Animal Register'!$U:$U,0)),"") | B13: =IF($A13="","",INDEX('Animal Register'!$C:$C,MATCH($A13,'Animal Register'!$A:$A,0))) | C13: =IF($A13="","",INDEX('Animal Register'!$K:$K,MATCH($A13,'Animal Register'!$A:$A,0))) | D13: =IF($A13="","",INDEX('Animal Register'!$I:$I,MATCH($A13,'Animal Register'!$A:$A,0))) | E13: =IF($A13="","",INDEX('Animal Register'!$J:$J,MATCH($A13,'Animal Register'!$A:$A,0))) | F13: =IF($A13="","",INDEX('Animal Register'!$S:$S,MATCH($A13,'Animal Register'!$A:$A,0))) | G13: =IF($A13="","",INDEX('Animal Register'!$O:$O,MATCH($A13,'Animal Register'!$A:$A,0))) | H13: =IF($A13="","",INDEX('Animal Register'!$N:$N,MATCH($A13,'Animal Register'!$A:$A,0))) | I13: =IF($A13="","",INDEX('Animal Register'!$P:$P,MATCH($A13,'Animal Register'!$A:$A,0))) | J13: =IF($A13="","",IFERROR(INDEX($R$5:$R$104,MATCH($A13,$Q$5:$Q$104,0)),"-")) | K13: =IF($A13="","",IFERROR(INDEX($S$5:$S$104,MATCH($A13,$Q$5:$Q$104,0)),"-")) | L13: =IF($A13="","",IFERROR(INDEX($T$5:$T$104,MATCH($A13,$Q$5:$Q$104,0)),"-")) | M13: =IF($A13="","",IFERROR(INDEX($U$5:$U$104,MATCH($A13,$Q$5:$Q$104,0)),"-")) | N13: =IF($A13="","",IF(ISNUMBER(L13),L13-E13,"-"))
A14: =IFERROR(INDEX('Animal Register'!$A:$A,MATCH(10,'Animal Register'!$U:$U,0)),"") | B14: =IF($A14="","",INDEX('Animal Register'!$C:$C,MATCH($A14,'Animal Register'!$A:$A,0))) | C14: =IF($A14="","",INDEX('Animal Register'!$K:$K,MATCH($A14,'Animal Register'!$A:$A,0))) | D14: =IF($A14="","",INDEX('Animal Register'!$I:$I,MATCH($A14,'Animal Register'!$A:$A,0))) | E14: =IF($A14="","",INDEX('Animal Register'!$J:$J,MATCH($A14,'Animal Register'!$A:$A,0))) | F14: =IF($A14="","",INDEX('Animal Register'!$S:$S,MATCH($A14,'Animal Register'!$A:$A,0))) | G14: =IF($A14="","",INDEX('Animal Register'!$O:$O,MATCH($A14,'Animal Register'!$A:$A,0))) | H14: =IF($A14="","",INDEX('Animal Register'!$N:$N,MATCH($A14,'Animal Register'!$A:$A,0))) | I14: =IF($A14="","",INDEX('Animal Register'!$P:$P,MATCH($A14,'Animal Register'!$A:$A,0))) | J14: =IF($A14="","",IFERROR(INDEX($R$5:$R$104,MATCH($A14,$Q$5:$Q$104,0)),"-")) | K14: =IF($A14="","",IFERROR(INDEX($S$5:$S$104,MATCH($A14,$Q$5:$Q$104,0)),"-")) | L14: =IF($A14="","",IFERROR(INDEX($T$5:$T$104,MATCH($A14,$Q$5:$Q$104,0)),"-")) | M14: =IF($A14="","",IFERROR(INDEX($U$5:$U$104,MATCH($A14,$Q$5:$Q$104,0)),"-")) | N14: =IF($A14="","",IF(ISNUMBER(L14),L14-E14,"-"))
A15: =IFERROR(INDEX('Animal Register'!$A:$A,MATCH(11,'Animal Register'!$U:$U,0)),"") | B15: =IF($A15="","",INDEX('Animal Register'!$C:$C,MATCH($A15,'Animal Register'!$A:$A,0))) | C15: =IF($A15="","",INDEX('Animal Register'!$K:$K,MATCH($A15,'Animal Register'!$A:$A,0))) | D15: =IF($A15="","",INDEX('Animal Register'!$I:$I,MATCH($A15,'Animal Register'!$A:$A,0))) | E15: =IF($A15="","",INDEX('Animal Register'!$J:$J,MATCH($A15,'Animal Register'!$A:$A,0))) | F15: =IF($A15="","",INDEX('Animal Register'!$S:$S,MATCH($A15,'Animal Register'!$A:$A,0))) | G15: =IF($A15="","",INDEX('Animal Register'!$O:$O,MATCH($A15,'Animal Register'!$A:$A,0))) | H15: =IF($A15="","",INDEX('Animal Register'!$N:$N,MATCH($A15,'Animal Register'!$A:$A,0))) | I15: =IF($A15="","",INDEX('Animal Register'!$P:$P,MATCH($A15,'Animal Register'!$A:$A,0))) | J15: =IF($A15="","",IFERROR(INDEX($R$5:$R$104,MATCH($A15,$Q$5:$Q$104,0)),"-")) | K15: =IF($A15="","",IFERROR(INDEX($S$5:$S$104,MATCH($A15,$Q$5:$Q$104,0)),"-")) | L15: =IF($A15="","",IFERROR(INDEX($T$5:$T$104,MATCH($A15,$Q$5:$Q$104,0)),"-")) | M15: =IF($A15="","",IFERROR(INDEX($U$5:$U$104,MATCH($A15,$Q$5:$Q$104,0)),"-")) | N15: =IF($A15="","",IF(ISNUMBER(L15),L15-E15,"-"))
A16: =IFERROR(INDEX('Animal Register'!$A:$A,MATCH(12,'Animal Register'!$U:$U,0)),"") | B16: =IF($A16="","",INDEX('Animal Register'!$C:$C,MATCH($A16,'Animal Register'!$A:$A,0))) | C16: =IF($A16="","",INDEX('Animal Register'!$K:$K,MATCH($A16,'Animal Register'!$A:$A,0))) | D16: =IF($A16="","",INDEX('Animal Register'!$I:$I,MATCH($A16,'Animal Register'!$A:$A,0))) | E16: =IF($A16="","",INDEX('Animal Register'!$J:$J,MATCH($A16,'Animal Register'!$A:$A,0))) | F16: =IF($A16="","",INDEX('Animal Register'!$S:$S,MATCH($A16,'Animal Register'!$A:$A,0))) | G16: =IF($A16="","",INDEX('Animal Register'!$O:$O,MATCH($A16,'Animal Register'!$A:$A,0))) | H16: =IF($A16="","",INDEX('Animal Register'!$N:$N,MATCH($A16,'Animal Register'!$A:$A,0))) | I16: =IF($A16="","",INDEX('Animal Register'!$P:$P,MATCH($A16,'Animal Register'!$A:$A,0))) | J16: =IF($A16="","",IFERROR(INDEX($R$5:$R$104,MATCH($A16,$Q$5:$Q$104,0)),"-")) | K16: =IF($A16="","",IFERROR(INDEX($S$5:$S$104,MATCH($A16,$Q$5:$Q$104,0)),"-")) | L16: =IF($A16="","",IFERROR(INDEX($T$5:$T$104,MATCH($A16,$Q$5:$Q$104,0)),"-")) | M16: =IF($A16="","",IFERROR(INDEX($U$5:$U$104,MATCH($A16,$Q$5:$Q$104,0)),"-")) | N16: =IF($A16="","",IF(ISNUMBER(L16),L16-E16,"-"))
A17: =IFERROR(INDEX('Animal Register'!$A:$A,MATCH(13,'Animal Register'!$U:$U,0)),"") | B17: =IF($A17="","",INDEX('Animal Register'!$C:$C,MATCH($A17,'Animal Register'!$A:$A,0))) | C17: =IF($A17="","",INDEX('Animal Register'!$K:$K,MATCH($A17,'Animal Register'!$A:$A,0))) | D17: =IF($A17="","",INDEX('Animal Register'!$I:$I,MATCH($A17,'Animal Register'!$A:$A,0))) | E17: =IF($A17="","",INDEX('Animal Register'!$J:$J,MATCH($A17,'Animal Register'!$A:$A,0))) | F17: =IF($A17="","",INDEX('Animal Register'!$S:$S,MATCH($A17,'Animal Register'!$A:$A,0))) | G17: =IF($A17="","",INDEX('Animal Register'!$O:$O,MATCH($A17,'Animal Register'!$A:$A,0))) | H17: =IF($A17="","",INDEX('Animal Register'!$N:$N,MATCH($A17,'Animal Register'!$A:$A,0))) | I17: =IF($A17="","",INDEX('Animal Register'!$P:$P,MATCH($A17,'Animal Register'!$A:$A,0))) | J17: =IF($A17="","",IFERROR(INDEX($R$5:$R$104,MATCH($A17,$Q$5:$Q$104,0)),"-")) | K17: =IF($A17="","",IFERROR(INDEX($S$5:$S$104,MATCH($A17,$Q$5:$Q$104,0)),"-")) | L17: =IF($A17="","",IFERROR(INDEX($T$5:$T$104,MATCH($A17,$Q$5:$Q$104,0)),"-")) | M17: =IF($A17="","",IFERROR(INDEX($U$5:$U$104,MATCH($A17,$Q$5:$Q$104,0)),"-")) | N17: =IF($A17="","",IF(ISNUMBER(L17),L17-E17,"-"))
A18: =IFERROR(INDEX('Animal Register'!$A:$A,MATCH(14,'Animal Register'!$U:$U,0)),"") | B18: =IF($A18="","",INDEX('Animal Register'!$C:$C,MATCH($A18,'Animal Register'!$A:$A,0))) | C18: =IF($A18="","",INDEX('Animal Register'!$K:$K,MATCH($A18,'Animal Register'!$A:$A,0))) | D18: =IF($A18="","",INDEX('Animal Register'!$I:$I,MATCH($A18,'Animal Register'!$A:$A,0))) | E18: =IF($A18="","",INDEX('Animal Register'!$J:$J,MATCH($A18,'Animal Register'!$A:$A,0))) | F18: =IF($A18="","",INDEX('Animal Register'!$S:$S,MATCH($A18,'Animal Register'!$A:$A,0))) | G18: =IF($A18="","",INDEX('Animal Register'!$O:$O,MATCH($A18,'Animal Register'!$A:$A,0))) | H18: =IF($A18="","",INDEX('Animal Register'!$N:$N,MATCH($A18,'Animal Register'!$A:$A,0))) | I18: =IF($A18="","",INDEX('Animal Register'!$P:$P,MATCH($A18,'Animal Register'!$A:$A,0))) | J18: =IF($A18="","",IFERROR(INDEX($R$5:$R$104,MATCH($A18,$Q$5:$Q$104,0)),"-")) | K18: =IF($A18="","",IFERROR(INDEX($S$5:$S$104,MATCH($A18,$Q$5:$Q$104,0)),"-")) | L18: =IF($A18="","",IFERROR(INDEX($T$5:$T$104,MATCH($A18,$Q$5:$Q$104,0)),"-")) | M18: =IF($A18="","",IFERROR(INDEX($U$5:$U$104,MATCH($A18,$Q$5:$Q$104,0)),"-")) | N18: =IF($A18="","",IF(ISNUMBER(L18),L18-E18,"-"))
A19: =IFERROR(INDEX('Animal Register'!$A:$A,MATCH(15,'Animal Register'!$U:$U,0)),"") | B19: =IF($A19="","",INDEX('Animal Register'!$C:$C,MATCH($A19,'Animal Register'!$A:$A,0))) | C19: =IF($A19="","",INDEX('Animal Register'!$K:$K,MATCH($A19,'Animal Register'!$A:$A,0))) | D19: =IF($A19="","",INDEX('Animal Register'!$I:$I,MATCH($A19,'Animal Register'!$A:$A,0))) | E19: =IF($A19="","",INDEX('Animal Register'!$J:$J,MATCH($A19,'Animal Register'!$A:$A,0))) | F19: =IF($A19="","",INDEX('Animal Register'!$S:$S,MATCH($A19,'Animal Register'!$A:$A,0))) | G19: =IF($A19="","",INDEX('Animal Register'!$O:$O,MATCH($A19,'Animal Register'!$A:$A,0))) | H19: =IF($A19="","",INDEX('Animal Register'!$N:$N,MATCH($A19,'Animal Register'!$A:$A,0))) | I19: =IF($A19="","",INDEX('Animal Register'!$P:$P,MATCH($A19,'Animal Register'!$A:$A,0))) | J19: =IF($A19="","",IFERROR(INDEX($R$5:$R$104,MATCH($A19,$Q$5:$Q$104,0)),"-")) | K19: =IF($A19="","",IFERROR(INDEX($S$5:$S$104,MATCH($A19,$Q$5:$Q$104,0)),"-")) | L19: =IF($A19="","",IFERROR(INDEX($T$5:$T$104,MATCH($A19,$Q$5:$Q$104,0)),"-")) | M19: =IF($A19="","",IFERROR(INDEX($U$5:$U$104,MATCH($A19,$Q$5:$Q$104,0)),"-")) | N19: =IF($A19="","",IF(ISNUMBER(L19),L19-E19,"-"))
A20: =IFERROR(INDEX('Animal Register'!$A:$A,MATCH(16,'Animal Register'!$U:$U,0)),"") | B20: =IF($A20="","",INDEX('Animal Register'!$C:$C,MATCH($A20,'Animal Register'!$A:$A,0))) | C20: =IF($A20="","",INDEX('Animal Register'!$K:$K,MATCH($A20,'Animal Register'!$A:$A,0))) | D20: =IF($A20="","",INDEX('Animal Register'!$I:$I,MATCH($A20,'Animal Register'!$A:$A,0))) | E20: =IF($A20="","",INDEX('Animal Register'!$J:$J,MATCH($A20,'Animal Register'!$A:$A,0))) | F20: =IF($A20="","",INDEX('Animal Register'!$S:$S,MATCH($A20,'Animal Register'!$A:$A,0))) | G20: =IF($A20="","",INDEX('Animal Register'!$O:$O,MATCH($A20,'Animal Register'!$A:$A,0))) | H20: =IF($A20="","",INDEX('Animal Register'!$N:$N,MATCH($A20,'Animal Register'!$A:$A,0))) | I20: =IF($A20="","",INDEX('Animal Register'!$P:$P,MATCH($A20,'Animal Register'!$A:$A,0))) | J20: =IF($A20="","",IFERROR(INDEX($R$5:$R$104,MATCH($A20,$Q$5:$Q$104,0)),"-")) | K20: =IF($A20="","",IFERROR(INDEX($S$5:$S$104,MATCH($A20,$Q$5:$Q$104,0)),"-")) | L20: =IF($A20="","",IFERROR(INDEX($T$5:$T$104,MATCH($A20,$Q$5:$Q$104,0)),"-")) | M20: =IF($A20="","",IFERROR(INDEX($U$5:$U$104,MATCH($A20,$Q$5:$Q$104,0)),"-")) | N20: =IF($A20="","",IF(ISNUMBER(L20),L20-E20,"-"))
A21: =IFERROR(INDEX('Animal Register'!$A:$A,MATCH(17,'Animal Register'!$U:$U,0)),"") | B21: =IF($A21="","",INDEX('Animal Register'!$C:$C,MATCH($A21,'Animal Register'!$A:$A,0))) | C21: =IF($A21="","",INDEX('Animal Register'!$K:$K,MATCH($A21,'Animal Register'!$A:$A,0))) | D21: =IF($A21="","",INDEX('Animal Register'!$I:$I,MATCH($A21,'Animal Register'!$A:$A,0))) | E21: =IF($A21="","",INDEX('Animal Register'!$J:$J,MATCH($A21,'Animal Register'!$A:$A,0))) | F21: =IF($A21="","",INDEX('Animal Register'!$S:$S,MATCH($A21,'Animal Register'!$A:$A,0))) | G21: =IF($A21="","",INDEX('Animal Register'!$O:$O,MATCH($A21,'Animal Register'!$A:$A,0))) | H21: =IF($A21="","",INDEX('Animal Register'!$N:$N,MATCH($A21,'Animal Register'!$A:$A,0))) | I21: =IF($A21="","",INDEX('Animal Register'!$P:$P,MATCH($A21,'Animal Register'!$A:$A,0))) | J21: =IF($A21="","",IFERROR(INDEX($R$5:$R$104,MATCH($A21,$Q$5:$Q$104,0)),"-")) | K21: =IF($A21="","",IFERROR(INDEX($S$5:$S$104,MATCH($A21,$Q$5:$Q$104,0)),"-")) | L21: =IF($A21="","",IFERROR(INDEX($T$5:$T$104,MATCH($A21,$Q$5:$Q$104,0)),"-")) | M21: =IF($A21="","",IFERROR(INDEX($U$5:$U$104,MATCH($A21,$Q$5:$Q$104,0)),"-")) | N21: =IF($A21="","",IF(ISNUMBER(L21),L21-E21,"-"))
A22: =IFERROR(INDEX('Animal Register'!$A:$A,MATCH(18,'Animal Register'!$U:$U,0)),"") | B22: =IF($A22="","",INDEX('Animal Register'!$C:$C,MATCH($A22,'Animal Register'!$A:$A,0))) | C22: =IF($A22="","",INDEX('Animal Register'!$K:$K,MATCH($A22,'Animal Register'!$A:$A,0))) | D22: =IF($A22="","",INDEX('Animal Register'!$I:$I,MATCH($A22,'Animal Register'!$A:$A,0))) | E22: =IF($A22="","",INDEX('Animal Register'!$J:$J,MATCH($A22,'Animal Register'!$A:$A,0))) | F22: =IF($A22="","",INDEX('Animal Register'!$S:$S,MATCH($A22,'Animal Register'!$A:$A,0))) | G22: =IF($A22="","",INDEX('Animal Register'!$O:$O,MATCH($A22,'Animal Register'!$A:$A,0))) | H22: =IF($A22="","",INDEX('Animal Register'!$N:$N,MATCH($A22,'Animal Register'!$A:$A,0))) | I22: =IF($A22="","",INDEX('Animal Register'!$P:$P,MATCH($A22,'Animal Register'!$A:$A,0))) | J22: =IF($A22="","",IFERROR(INDEX($R$5:$R$104,MATCH($A22,$Q$5:$Q$104,0)),"-")) | K22: =IF($A22="","",IFERROR(INDEX($S$5:$S$104,MATCH($A22,$Q$5:$Q$104,0)),"-")) | L22: =IF($A22="","",IFERROR(INDEX($T$5:$T$104,MATCH($A22,$Q$5:$Q$104,0)),"-")) | M22: =IF($A22="","",IFERROR(INDEX($U$5:$U$104,MATCH($A22,$Q$5:$Q$104,0)),"-")) | N22: =IF($A22="","",IF(ISNUMBER(L22),L22-E22,"-"))
A23: =IFERROR(INDEX('Animal Register'!$A:$A,MATCH(19,'Animal Register'!$U:$U,0)),"") | B23: =IF($A23="","",INDEX('Animal Register'!$C:$C,MATCH($A23,'Animal Register'!$A:$A,0))) | C23: =IF($A23="","",INDEX('Animal Register'!$K:$K,MATCH($A23,'Animal Register'!$A:$A,0))) | D23: =IF($A23="","",INDEX('Animal Register'!$I:$I,MATCH($A23,'Animal Register'!$A:$A,0))) | E23: =IF($A23="","",INDEX('Animal Register'!$J:$J,MATCH($A23,'Animal Register'!$A:$A,0))) | F23: =IF($A23="","",INDEX('Animal Register'!$S:$S,MATCH($A23,'Animal Register'!$A:$A,0))) | G23: =IF($A23="","",INDEX('Animal Register'!$O:$O,MATCH($A23,'Animal Register'!$A:$A,0))) | H23: =IF($A23="","",INDEX('Animal Register'!$N:$N,MATCH($A23,'Animal Register'!$A:$A,0))) | I23: =IF($A23="","",INDEX('Animal Register'!$P:$P,MATCH($A23,'Animal Register'!$A:$A,0))) | J23: =IF($A23="","",IFERROR(INDEX($R$5:$R$104,MATCH($A23,$Q$5:$Q$104,0)),"-")) | K23: =IF($A23="","",IFERROR(INDEX($S$5:$S$104,MATCH($A23,$Q$5:$Q$104,0)),"-")) | L23: =IF($A23="","",IFERROR(INDEX($T$5:$T$104,MATCH($A23,$Q$5:$Q$104,0)),"-")) | M23: =IF($A23="","",IFERROR(INDEX($U$5:$U$104,MATCH($A23,$Q$5:$Q$104,0)),"-")) | N23: =IF($A23="","",IF(ISNUMBER(L23),L23-E23,"-"))
A24: =IFERROR(INDEX('Animal Register'!$A:$A,MATCH(20,'Animal Register'!$U:$U,0)),"") | B24: =IF($A24="","",INDEX('Animal Register'!$C:$C,MATCH($A24,'Animal Register'!$A:$A,0))) | C24: =IF($A24="","",INDEX('Animal Register'!$K:$K,MATCH($A24,'Animal Register'!$A:$A,0))) | D24: =IF($A24="","",INDEX('Animal Register'!$I:$I,MATCH($A24,'Animal Register'!$A:$A,0))) | E24: =IF($A24="","",INDEX('Animal Register'!$J:$J,MATCH($A24,'Animal Register'!$A:$A,0))) | F24: =IF($A24="","",INDEX('Animal Register'!$S:$S,MATCH($A24,'Animal Register'!$A:$A,0))) | G24: =IF($A24="","",INDEX('Animal Register'!$O:$O,MATCH($A24,'Animal Register'!$A:$A,0))) | H24: =IF($A24="","",INDEX('Animal Register'!$N:$N,MATCH($A24,'Animal Register'!$A:$A,0))) | I24: =IF($A24="","",INDEX('Animal Register'!$P:$P,MATCH($A24,'Animal Register'!$A:$A,0))) | J24: =IF($A24="","",IFERROR(INDEX($R$5:$R$104,MATCH($A24,$Q$5:$Q$104,0)),"-")) | K24: =IF($A24="","",IFERROR(INDEX($S$5:$S$104,MATCH($A24,$Q$5:$Q$104,0)),"-")) | L24: =IF($A24="","",IFERROR(INDEX($T$5:$T$104,MATCH($A24,$Q$5:$Q$104,0)),"-")) | M24: =IF($A24="","",IFERROR(INDEX($U$5:$U$104,MATCH($A24,$Q$5:$Q$104,0)),"-")) | N24: =IF($A24="","",IF(ISNUMBER(L24),L24-E24,"-"))
A25: =IFERROR(INDEX('Animal Register'!$A:$A,MATCH(21,'Animal Register'!$U:$U,0)),"") | B25: =IF($A25="","",INDEX('Animal Register'!$C:$C,MATCH($A25,'Animal Register'!$A:$A,0))) | C25: =IF($A25="","",INDEX('Animal Register'!$K:$K,MATCH($A25,'Animal Register'!$A:$A,0))) | D25: =IF($A25="","",INDEX('Animal Register'!$I:$I,MATCH($A25,'Animal Register'!$A:$A,0))) | E25: =IF($A25="","",INDEX('Animal Register'!$J:$J,MATCH($A25,'Animal Register'!$A:$A,0))) | F25: =IF($A25="","",INDEX('Animal Register'!$S:$S,MATCH($A25,'Animal Register'!$A:$A,0))) | G25: =IF($A25="","",INDEX('Animal Register'!$O:$O,MATCH($A25,'Animal Register'!$A:$A,0))) | H25: =IF($A25="","",INDEX('Animal Register'!$N:$N,MATCH($A25,'Animal Register'!$A:$A,0))) | I25: =IF($A25="","",INDEX('Animal Register'!$P:$P,MATCH($A25,'Animal Register'!$A:$A,0))) | J25: =IF($A25="","",IFERROR(INDEX($R$5:$R$104,MATCH($A25,$Q$5:$Q$104,0)),"-")) | K25: =IF($A25="","",IFERROR(INDEX($S$5:$S$104,MATCH($A25,$Q$5:$Q$104,0)),"-")) | L25: =IF($A25="","",IFERROR(INDEX($T$5:$T$104,MATCH($A25,$Q$5:$Q$104,0)),"-")) | M25: =IF($A25="","",IFERROR(INDEX($U$5:$U$104,MATCH($A25,$Q$5:$Q$104,0)),"-")) | N25: =IF($A25="","",IF(ISNUMBER(L25),L25-E25,"-"))
A26: =IFERROR(INDEX('Animal Register'!$A:$A,MATCH(22,'Animal Register'!$U:$U,0)),"") | B26: =IF($A26="","",INDEX('Animal Register'!$C:$C,MATCH($A26,'Animal Register'!$A:$A,0))) | C26: =IF($A26="","",INDEX('Animal Register'!$K:$K,MATCH($A26,'Animal Register'!$A:$A,0))) | D26: =IF($A26="","",INDEX('Animal Register'!$I:$I,MATCH($A26,'Animal Register'!$A:$A,0))) | E26: =IF($A26="","",INDEX('Animal Register'!$J:$J,MATCH($A26,'Animal Register'!$A:$A,0))) | F26: =IF($A26="","",INDEX('Animal Register'!$S:$S,MATCH($A26,'Animal Register'!$A:$A,0))) | G26: =IF($A26="","",INDEX('Animal Register'!$O:$O,MATCH($A26,'Animal Register'!$A:$A,0))) | H26: =IF($A26="","",INDEX('Animal Register'!$N:$N,MATCH($A26,'Animal Register'!$A:$A,0))) | I26: =IF($A26="","",INDEX('Animal Register'!$P:$P,MATCH($A26,'Animal Register'!$A:$A,0))) | J26: =IF($A26="","",IFERROR(INDEX($R$5:$R$104,MATCH($A26,$Q$5:$Q$104,0)),"-")) | K26: =IF($A26="","",IFERROR(INDEX($S$5:$S$104,MATCH($A26,$Q$5:$Q$104,0)),"-")) | L26: =IF($A26="","",IFERROR(INDEX($T$5:$T$104,MATCH($A26,$Q$5:$Q$104,0)),"-")) | M26: =IF($A26="","",IFERROR(INDEX($U$5:$U$104,MATCH($A26,$Q$5:$Q$104,0)),"-")) | N26: =IF($A26="","",IF(ISNUMBER(L26),L26-E26,"-"))
A27: =IFERROR(INDEX('Animal Register'!$A:$A,MATCH(23,'Animal Register'!$U:$U,0)),"") | B27: =IF($A27="","",INDEX('Animal Register'!$C:$C,MATCH($A27,'Animal Register'!$A:$A,0))) | C27: =IF($A27="","",INDEX('Animal Register'!$K:$K,MATCH($A27,'Animal Register'!$A:$A,0))) | D27: =IF($A27="","",INDEX('Animal Register'!$I:$I,MATCH($A27,'Animal Register'!$A:$A,0))) | E27: =IF($A27="","",INDEX('Animal Register'!$J:$J,MATCH($A27,'Animal Register'!$A:$A,0))) | F27: =IF($A27="","",INDEX('Animal Register'!$S:$S,MATCH($A27,'Animal Register'!$A:$A,0))) | G27: =IF($A27="","",INDEX('Animal Register'!$O:$O,MATCH($A27,'Animal Register'!$A:$A,0))) | H27: =IF($A27="","",INDEX('Animal Register'!$N:$N,MATCH($A27,'Animal Register'!$A:$A,0))) | I27: =IF($A27="","",INDEX('Animal Register'!$P:$P,MATCH($A27,'Animal Register'!$A:$A,0))) | J27: =IF($A27="","",IFERROR(INDEX($R$5:$R$104,MATCH($A27,$Q$5:$Q$104,0)),"-")) | K27: =IF($A27="","",IFERROR(INDEX($S$5:$S$104,MATCH($A27,$Q$5:$Q$104,0)),"-")) | L27: =IF($A27="","",IFERROR(INDEX($T$5:$T$104,MATCH($A27,$Q$5:$Q$104,0)),"-")) | M27: =IF($A27="","",IFERROR(INDEX($U$5:$U$104,MATCH($A27,$Q$5:$Q$104,0)),"-")) | N27: =IF($A27="","",IF(ISNUMBER(L27),L27-E27,"-"))
A28: =IFERROR(INDEX('Animal Register'!$A:$A,MATCH(24,'Animal Register'!$U:$U,0)),"") | B28: =IF($A28="","",INDEX('Animal Register'!$C:$C,MATCH($A28,'Animal Register'!$A:$A,0))) | C28: =IF($A28="","",INDEX('Animal Register'!$K:$K,MATCH($A28,'Animal Register'!$A:$A,0))) | D28: =IF($A28="","",INDEX('Animal Register'!$I:$I,MATCH($A28,'Animal Register'!$A:$A,0))) | E28: =IF($A28="","",INDEX('Animal Register'!$J:$J,MATCH($A28,'Animal Register'!$A:$A,0))) | F28: =IF($A28="","",INDEX('Animal Register'!$S:$S,MATCH($A28,'Animal Register'!$A:$A,0))) | G28: =IF($A28="","",INDEX('Animal Register'!$O:$O,MATCH($A28,'Animal Register'!$A:$A,0))) | H28: =IF($A28="","",INDEX('Animal Register'!$N:$N,MATCH($A28,'Animal Register'!$A:$A,0))) | I28: =IF($A28="","",INDEX('Animal Register'!$P:$P,MATCH($A28,'Animal Register'!$A:$A,0))) | J28: =IF($A28="","",IFERROR(INDEX($R$5:$R$104,MATCH($A28,$Q$5:$Q$104,0)),"-")) | K28: =IF($A28="","",IFERROR(INDEX($S$5:$S$104,MATCH($A28,$Q$5:$Q$104,0)),"-")) | L28: =IF($A28="","",IFERROR(INDEX($T$5:$T$104,MATCH($A28,$Q$5:$Q$104,0)),"-")) | M28: =IF($A28="","",IFERROR(INDEX($U$5:$U$104,MATCH($A28,$Q$5:$Q$104,0)),"-")) | N28: =IF($A28="","",IF(ISNUMBER(L28),L28-E28,"-"))
A29: =IFERROR(INDEX('Animal Register'!$A:$A,MATCH(25,'Animal Register'!$U:$U,0)),"") | B29: =IF($A29="","",INDEX('Animal Register'!$C:$C,MATCH($A29,'Animal Register'!$A:$A,0))) | C29: =IF($A29="","",INDEX('Animal Register'!$K:$K,MATCH($A29,'Animal Register'!$A:$A,0))) | D29: =IF($A29="","",INDEX('Animal Register'!$I:$I,MATCH($A29,'Animal Register'!$A:$A,0))) | E29: =IF($A29="","",INDEX('Animal Register'!$J:$J,MATCH($A29,'Animal Register'!$A:$A,0))) | F29: =IF($A29="","",INDEX('Animal Register'!$S:$S,MATCH($A29,'Animal Register'!$A:$A,0))) | G29: =IF($A29="","",INDEX('Animal Register'!$O:$O,MATCH($A29,'Animal Register'!$A:$A,0))) | H29: =IF($A29="","",INDEX('Animal Register'!$N:$N,MATCH($A29,'Animal Register'!$A:$A,0))) | I29: =IF($A29="","",INDEX('Animal Register'!$P:$P,MATCH($A29,'Animal Register'!$A:$A,0))) | J29: =IF($A29="","",IFERROR(INDEX($R$5:$R$104,MATCH($A29,$Q$5:$Q$104,0)),"-")) | K29: =IF($A29="","",IFERROR(INDEX($S$5:$S$104,MATCH($A29,$Q$5:$Q$104,0)),"-")) | L29: =IF($A29="","",IFERROR(INDEX($T$5:$T$104,MATCH($A29,$Q$5:$Q$104,0)),"-")) | M29: =IF($A29="","",IFERROR(INDEX($U$5:$U$104,MATCH($A29,$Q$5:$Q$104,0)),"-")) | N29: =IF($A29="","",IF(ISNUMBER(L29),L29-E29,"-"))
A30: =IFERROR(INDEX('Animal Register'!$A:$A,MATCH(26,'Animal Register'!$U:$U,0)),"") | B30: =IF($A30="","",INDEX('Animal Register'!$C:$C,MATCH($A30,'Animal Register'!$A:$A,0))) | C30: =IF($A30="","",INDEX('Animal Register'!$K:$K,MATCH($A30,'Animal Register'!$A:$A,0))) | D30: =IF($A30="","",INDEX('Animal Register'!$I:$I,MATCH($A30,'Animal Register'!$A:$A,0))) | E30: =IF($A30="","",INDEX('Animal Register'!$J:$J,MATCH($A30,'Animal Register'!$A:$A,0))) | F30: =IF($A30="","",INDEX('Animal Register'!$S:$S,MATCH($A30,'Animal Register'!$A:$A,0))) | G30: =IF($A30="","",INDEX('Animal Register'!$O:$O,MATCH($A30,'Animal Register'!$A:$A,0))) | H30: =IF($A30="","",INDEX('Animal Register'!$N:$N,MATCH($A30,'Animal Register'!$A:$A,0))) | I30: =IF($A30="","",INDEX('Animal Register'!$P:$P,MATCH($A30,'Animal Register'!$A:$A,0))) | J30: =IF($A30="","",IFERROR(INDEX($R$5:$R$104,MATCH($A30,$Q$5:$Q$104,0)),"-")) | K30: =IF($A30="","",IFERROR(INDEX($S$5:$S$104,MATCH($A30,$Q$5:$Q$104,0)),"-")) | L30: =IF($A30="","",IFERROR(INDEX($T$5:$T$104,MATCH($A30,$Q$5:$Q$104,0)),"-")) | M30: =IF($A30="","",IFERROR(INDEX($U$5:$U$104,MATCH($A30,$Q$5:$Q$104,0)),"-")) | N30: =IF($A30="","",IF(ISNUMBER(L30),L30-E30,"-"))
A31: =IFERROR(INDEX('Animal Register'!$A:$A,MATCH(27,'Animal Register'!$U:$U,0)),"") | B31: =IF($A31="","",INDEX('Animal Register'!$C:$C,MATCH($A31,'Animal Register'!$A:$A,0))) | C31: =IF($A31="","",INDEX('Animal Register'!$K:$K,MATCH($A31,'Animal Register'!$A:$A,0))) | D31: =IF($A31="","",INDEX('Animal Register'!$I:$I,MATCH($A31,'Animal Register'!$A:$A,0))) | E31: =IF($A31="","",INDEX('Animal Register'!$J:$J,MATCH($A31,'Animal Register'!$A:$A,0))) | F31: =IF($A31="","",INDEX('Animal Register'!$S:$S,MATCH($A31,'Animal Register'!$A:$A,0))) | G31: =IF($A31="","",INDEX('Animal Register'!$O:$O,MATCH($A31,'Animal Register'!$A:$A,0))) | H31: =IF($A31="","",INDEX('Animal Register'!$N:$N,MATCH($A31,'Animal Register'!$A:$A,0))) | I31: =IF($A31="","",INDEX('Animal Register'!$P:$P,MATCH($A31,'Animal Register'!$A:$A,0))) | J31: =IF($A31="","",IFERROR(INDEX($R$5:$R$104,MATCH($A31,$Q$5:$Q$104,0)),"-")) | K31: =IF($A31="","",IFERROR(INDEX($S$5:$S$104,MATCH($A31,$Q$5:$Q$104,0)),"-")) | L31: =IF($A31="","",IFERROR(INDEX($T$5:$T$104,MATCH($A31,$Q$5:$Q$104,0)),"-")) | M31: =IF($A31="","",IFERROR(INDEX($U$5:$U$104,MATCH($A31,$Q$5:$Q$104,0)),"-")) | N31: =IF($A31="","",IF(ISNUMBER(L31),L31-E31,"-"))
A32: =IFERROR(INDEX('Animal Register'!$A:$A,MATCH(28,'Animal Register'!$U:$U,0)),"") | B32: =IF($A32="","",INDEX('Animal Register'!$C:$C,MATCH($A32,'Animal Register'!$A:$A,0))) | C32: =IF($A32="","",INDEX('Animal Register'!$K:$K,MATCH($A32,'Animal Register'!$A:$A,0))) | D32: =IF($A32="","",INDEX('Animal Register'!$I:$I,MATCH($A32,'Animal Register'!$A:$A,0))) | E32: =IF($A32="","",INDEX('Animal Register'!$J:$J,MATCH($A32,'Animal Register'!$A:$A,0))) | F32: =IF($A32="","",INDEX('Animal Register'!$S:$S,MATCH($A32,'Animal Register'!$A:$A,0))) | G32: =IF($A32="","",INDEX('Animal Register'!$O:$O,MATCH($A32,'Animal Register'!$A:$A,0))) | H32: =IF($A32="","",INDEX('Animal Register'!$N:$N,MATCH($A32,'Animal Register'!$A:$A,0))) | I32: =IF($A32="","",INDEX('Animal Register'!$P:$P,MATCH($A32,'Animal Register'!$A:$A,0))) | J32: =IF($A32="","",IFERROR(INDEX($R$5:$R$104,MATCH($A32,$Q$5:$Q$104,0)),"-")) | K32: =IF($A32="","",IFERROR(INDEX($S$5:$S$104,MATCH($A32,$Q$5:$Q$104,0)),"-")) | L32: =IF($A32="","",IFERROR(INDEX($T$5:$T$104,MATCH($A32,$Q$5:$Q$104,0)),"-")) | M32: =IF($A32="","",IFERROR(INDEX($U$5:$U$104,MATCH($A32,$Q$5:$Q$104,0)),"-")) | N32: =IF($A32="","",IF(ISNUMBER(L32),L32-E32,"-"))
A33: =IFERROR(INDEX('Animal Register'!$A:$A,MATCH(29,'Animal Register'!$U:$U,0)),"") | B33: =IF($A33="","",INDEX('Animal Register'!$C:$C,MATCH($A33,'Animal Register'!$A:$A,0))) | C33: =IF($A33="","",INDEX('Animal Register'!$K:$K,MATCH($A33,'Animal Register'!$A:$A,0))) | D33: =IF($A33="","",INDEX('Animal Register'!$I:$I,MATCH($A33,'Animal Register'!$A:$A,0))) | E33: =IF($A33="","",INDEX('Animal Register'!$J:$J,MATCH($A33,'Animal Register'!$A:$A,0))) | F33: =IF($A33="","",INDEX('Animal Register'!$S:$S,MATCH($A33,'Animal Register'!$A:$A,0))) | G33: =IF($A33="","",INDEX('Animal Register'!$O:$O,MATCH($A33,'Animal Register'!$A:$A,0))) | H33: =IF($A33="","",INDEX('Animal Register'!$N:$N,MATCH($A33,'Animal Register'!$A:$A,0))) | I33: =IF($A33="","",INDEX('Animal Register'!$P:$P,MATCH($A33,'Animal Register'!$A:$A,0))) | J33: =IF($A33="","",IFERROR(INDEX($R$5:$R$104,MATCH($A33,$Q$5:$Q$104,0)),"-")) | K33: =IF($A33="","",IFERROR(INDEX($S$5:$S$104,MATCH($A33,$Q$5:$Q$104,0)),"-")) | L33: =IF($A33="","",IFERROR(INDEX($T$5:$T$104,MATCH($A33,$Q$5:$Q$104,0)),"-")) | M33: =IF($A33="","",IFERROR(INDEX($U$5:$U$104,MATCH($A33,$Q$5:$Q$104,0)),"-")) | N33: =IF($A33="","",IF(ISNUMBER(L33),L33-E33,"-"))
A34: =IFERROR(INDEX('Animal Register'!$A:$A,MATCH(30,'Animal Register'!$U:$U,0)),"") | B34: =IF($A34="","",INDEX('Animal Register'!$C:$C,MATCH($A34,'Animal Register'!$A:$A,0))) | C34: =IF($A34="","",INDEX('Animal Register'!$K:$K,MATCH($A34,'Animal Register'!$A:$A,0))) | D34: =IF($A34="","",INDEX('Animal Register'!$I:$I,MATCH($A34,'Animal Register'!$A:$A,0))) | E34: =IF($A34="","",INDEX('Animal Register'!$J:$J,MATCH($A34,'Animal Register'!$A:$A,0))) | F34: =IF($A34="","",INDEX('Animal Register'!$S:$S,MATCH($A34,'Animal Register'!$A:$A,0))) | G34: =IF($A34="","",INDEX('Animal Register'!$O:$O,MATCH($A34,'Animal Register'!$A:$A,0))) | H34: =IF($A34="","",INDEX('Animal Register'!$N:$N,MATCH($A34,'Animal Register'!$A:$A,0))) | I34: =IF($A34="","",INDEX('Animal Register'!$P:$P,MATCH($A34,'Animal Register'!$A:$A,0))) | J34: =IF($A34="","",IFERROR(INDEX($R$5:$R$104,MATCH($A34,$Q$5:$Q$104,0)),"-")) | K34: =IF($A34="","",IFERROR(INDEX($S$5:$S$104,MATCH($A34,$Q$5:$Q$104,0)),"-")) | L34: =IF($A34="","",IFERROR(INDEX($T$5:$T$104,MATCH($A34,$Q$5:$Q$104,0)),"-")) | M34: =IF($A34="","",IFERROR(INDEX($U$5:$U$104,MATCH($A34,$Q$5:$Q$104,0)),"-")) | N34: =IF($A34="","",IF(ISNUMBER(L34),L34-E34,"-"))
A35: =IFERROR(INDEX('Animal Register'!$A:$A,MATCH(31,'Animal Register'!$U:$U,0)),"") | B35: =IF($A35="","",INDEX('Animal Register'!$C:$C,MATCH($A35,'Animal Register'!$A:$A,0))) | C35: =IF($A35="","",INDEX('Animal Register'!$K:$K,MATCH($A35,'Animal Register'!$A:$A,0))) | D35: =IF($A35="","",INDEX('Animal Register'!$I:$I,MATCH($A35,'Animal Register'!$A:$A,0))) | E35: =IF($A35="","",INDEX('Animal Register'!$J:$J,MATCH($A35,'Animal Register'!$A:$A,0))) | F35: =IF($A35="","",INDEX('Animal Register'!$S:$S,MATCH($A35,'Animal Register'!$A:$A,0))) | G35: =IF($A35="","",INDEX('Animal Register'!$O:$O,MATCH($A35,'Animal Register'!$A:$A,0))) | H35: =IF($A35="","",INDEX('Animal Register'!$N:$N,MATCH($A35,'Animal Register'!$A:$A,0))) | I35: =IF($A35="","",INDEX('Animal Register'!$P:$P,MATCH($A35,'Animal Register'!$A:$A,0))) | J35: =IF($A35="","",IFERROR(INDEX($R$5:$R$104,MATCH($A35,$Q$5:$Q$104,0)),"-")) | K35: =IF($A35="","",IFERROR(INDEX($S$5:$S$104,MATCH($A35,$Q$5:$Q$104,0)),"-")) | L35: =IF($A35="","",IFERROR(INDEX($T$5:$T$104,MATCH($A35,$Q$5:$Q$104,0)),"-")) | M35: =IF($A35="","",IFERROR(INDEX($U$5:$U$104,MATCH($A35,$Q$5:$Q$104,0)),"-")) | N35: =IF($A35="","",IF(ISNUMBER(L35),L35-E35,"-"))
A36: =IFERROR(INDEX('Animal Register'!$A:$A,MATCH(32,'Animal Register'!$U:$U,0)),"") | B36: =IF($A36="","",INDEX('Animal Register'!$C:$C,MATCH($A36,'Animal Register'!$A:$A,0))) | C36: =IF($A36="","",INDEX('Animal Register'!$K:$K,MATCH($A36,'Animal Register'!$A:$A,0))) | D36: =IF($A36="","",INDEX('Animal Register'!$I:$I,MATCH($A36,'Animal Register'!$A:$A,0))) | E36: =IF($A36="","",INDEX('Animal Register'!$J:$J,MATCH($A36,'Animal Register'!$A:$A,0))) | F36: =IF($A36="","",INDEX('Animal Register'!$S:$S,MATCH($A36,'Animal Register'!$A:$A,0))) | G36: =IF($A36="","",INDEX('Animal Register'!$O:$O,MATCH($A36,'Animal Register'!$A:$A,0))) | H36: =IF($A36="","",INDEX('Animal Register'!$N:$N,MATCH($A36,'Animal Register'!$A:$A,0))) | I36: =IF($A36="","",INDEX('Animal Register'!$P:$P,MATCH($A36,'Animal Register'!$A:$A,0))) | J36: =IF($A36="","",IFERROR(INDEX($R$5:$R$104,MATCH($A36,$Q$5:$Q$104,0)),"-")) | K36: =IF($A36="","",IFERROR(INDEX($S$5:$S$104,MATCH($A36,$Q$5:$Q$104,0)),"-")) | L36: =IF($A36="","",IFERROR(INDEX($T$5:$T$104,MATCH($A36,$Q$5:$Q$104,0)),"-")) | M36: =IF($A36="","",IFERROR(INDEX($U$5:$U$104,MATCH($A36,$Q$5:$Q$104,0)),"-")) | N36: =IF($A36="","",IF(ISNUMBER(L36),L36-E36,"-"))
A37: =IFERROR(INDEX('Animal Register'!$A:$A,MATCH(33,'Animal Register'!$U:$U,0)),"") | B37: =IF($A37="","",INDEX('Animal Register'!$C:$C,MATCH($A37,'Animal Register'!$A:$A,0))) | C37: =IF($A37="","",INDEX('Animal Register'!$K:$K,MATCH($A37,'Animal Register'!$A:$A,0))) | D37: =IF($A37="","",INDEX('Animal Register'!$I:$I,MATCH($A37,'Animal Register'!$A:$A,0))) | E37: =IF($A37="","",INDEX('Animal Register'!$J:$J,MATCH($A37,'Animal Register'!$A:$A,0))) | F37: =IF($A37="","",INDEX('Animal Register'!$S:$S,MATCH($A37,'Animal Register'!$A:$A,0))) | G37: =IF($A37="","",INDEX('Animal Register'!$O:$O,MATCH($A37,'Animal Register'!$A:$A,0))) | H37: =IF($A37="","",INDEX('Animal Register'!$N:$N,MATCH($A37,'Animal Register'!$A:$A,0))) | I37: =IF($A37="","",INDEX('Animal Register'!$P:$P,MATCH($A37,'Animal Register'!$A:$A,0))) | J37: =IF($A37="","",IFERROR(INDEX($R$5:$R$104,MATCH($A37,$Q$5:$Q$104,0)),"-")) | K37: =IF($A37="","",IFERROR(INDEX($S$5:$S$104,MATCH($A37,$Q$5:$Q$104,0)),"-")) | L37: =IF($A37="","",IFERROR(INDEX($T$5:$T$104,MATCH($A37,$Q$5:$Q$104,0)),"-")) | M37: =IF($A37="","",IFERROR(INDEX($U$5:$U$104,MATCH($A37,$Q$5:$Q$104,0)),"-")) | N37: =IF($A37="","",IF(ISNUMBER(L37),L37-E37,"-"))
A38: =IFERROR(INDEX('Animal Register'!$A:$A,MATCH(34,'Animal Register'!$U:$U,0)),"") | B38: =IF($A38="","",INDEX('Animal Register'!$C:$C,MATCH($A38,'Animal Register'!$A:$A,0))) | C38: =IF($A38="","",INDEX('Animal Register'!$K:$K,MATCH($A38,'Animal Register'!$A:$A,0))) | D38: =IF($A38="","",INDEX('Animal Register'!$I:$I,MATCH($A38,'Animal Register'!$A:$A,0))) | E38: =IF($A38="","",INDEX('Animal Register'!$J:$J,MATCH($A38,'Animal Register'!$A:$A,0))) | F38: =IF($A38="","",INDEX('Animal Register'!$S:$S,MATCH($A38,'Animal Register'!$A:$A,0))) | G38: =IF($A38="","",INDEX('Animal Register'!$O:$O,MATCH($A38,'Animal Register'!$A:$A,0))) | H38: =IF($A38="","",INDEX('Animal Register'!$N:$N,MATCH($A38,'Animal Register'!$A:$A,0))) | I38: =IF($A38="","",INDEX('Animal Register'!$P:$P,MATCH($A38,'Animal Register'!$A:$A,0))) | J38: =IF($A38="","",IFERROR(INDEX($R$5:$R$104,MATCH($A38,$Q$5:$Q$104,0)),"-")) | K38: =IF($A38="","",IFERROR(INDEX($S$5:$S$104,MATCH($A38,$Q$5:$Q$104,0)),"-")) | L38: =IF($A38="","",IFERROR(INDEX($T$5:$T$104,MATCH($A38,$Q$5:$Q$104,0)),"-")) | M38: =IF($A38="","",IFERROR(INDEX($U$5:$U$104,MATCH($A38,$Q$5:$Q$104,0)),"-")) | N38: =IF($A38="","",IF(ISNUMBER(L38),L38-E38,"-"))
A39: =IFERROR(INDEX('Animal Register'!$A:$A,MATCH(35,'Animal Register'!$U:$U,0)),"") | B39: =IF($A39="","",INDEX('Animal Register'!$C:$C,MATCH($A39,'Animal Register'!$A:$A,0))) | C39: =IF($A39="","",INDEX('Animal Register'!$K:$K,MATCH($A39,'Animal Register'!$A:$A,0))) | D39: =IF($A39="","",INDEX('Animal Register'!$I:$I,MATCH($A39,'Animal Register'!$A:$A,0))) | E39: =IF($A39="","",INDEX('Animal Register'!$J:$J,MATCH($A39,'Animal Register'!$A:$A,0))) | F39: =IF($A39="","",INDEX('Animal Register'!$S:$S,MATCH($A39,'Animal Register'!$A:$A,0))) | G39: =IF($A39="","",INDEX('Animal Register'!$O:$O,MATCH($A39,'Animal Register'!$A:$A,0))) | H39: =IF($A39="","",INDEX('Animal Register'!$N:$N,MATCH($A39,'Animal Register'!$A:$A,0))) | I39: =IF($A39="","",INDEX('Animal Register'!$P:$P,MATCH($A39,'Animal Register'!$A:$A,0))) | J39: =IF($A39="","",IFERROR(INDEX($R$5:$R$104,MATCH($A39,$Q$5:$Q$104,0)),"-")) | K39: =IF($A39="","",IFERROR(INDEX($S$5:$S$104,MATCH($A39,$Q$5:$Q$104,0)),"-")) | L39: =IF($A39="","",IFERROR(INDEX($T$5:$T$104,MATCH($A39,$Q$5:$Q$104,0)),"-")) | M39: =IF($A39="","",IFERROR(INDEX($U$5:$U$104,MATCH($A39,$Q$5:$Q$104,0)),"-")) | N39: =IF($A39="","",IF(ISNUMBER(L39),L39-E39,"-"))
A40: =IFERROR(INDEX('Animal Register'!$A:$A,MATCH(36,'Animal Register'!$U:$U,0)),"") | B40: =IF($A40="","",INDEX('Animal Register'!$C:$C,MATCH($A40,'Animal Register'!$A:$A,0))) | C40: =IF($A40="","",INDEX('Animal Register'!$K:$K,MATCH($A40,'Animal Register'!$A:$A,0))) | D40: =IF($A40="","",INDEX('Animal Register'!$I:$I,MATCH($A40,'Animal Register'!$A:$A,0))) | E40: =IF($A40="","",INDEX('Animal Register'!$J:$J,MATCH($A40,'Animal Register'!$A:$A,0))) | F40: =IF($A40="","",INDEX('Animal Register'!$S:$S,MATCH($A40,'Animal Register'!$A:$A,0))) | G40: =IF($A40="","",INDEX('Animal Register'!$O:$O,MATCH($A40,'Animal Register'!$A:$A,0))) | H40: =IF($A40="","",INDEX('Animal Register'!$N:$N,MATCH($A40,'Animal Register'!$A:$A,0))) | I40: =IF($A40="","",INDEX('Animal Register'!$P:$P,MATCH($A40,'Animal Register'!$A:$A,0))) | J40: =IF($A40="","",IFERROR(INDEX($R$5:$R$104,MATCH($A40,$Q$5:$Q$104,0)),"-")) | K40: =IF($A40="","",IFERROR(INDEX($S$5:$S$104,MATCH($A40,$Q$5:$Q$104,0)),"-")) | L40: =IF($A40="","",IFERROR(INDEX($T$5:$T$104,MATCH($A40,$Q$5:$Q$104,0)),"-")) | M40: =IF($A40="","",IFERROR(INDEX($U$5:$U$104,MATCH($A40,$Q$5:$Q$104,0)),"-")) | N40: =IF($A40="","",IF(ISNUMBER(L40),L40-E40,"-"))
A41: =IFERROR(INDEX('Animal Register'!$A:$A,MATCH(37,'Animal Register'!$U:$U,0)),"") | B41: =IF($A41="","",INDEX('Animal Register'!$C:$C,MATCH($A41,'Animal Register'!$A:$A,0))) | C41: =IF($A41="","",INDEX('Animal Register'!$K:$K,MATCH($A41,'Animal Register'!$A:$A,0))) | D41: =IF($A41="","",INDEX('Animal Register'!$I:$I,MATCH($A41,'Animal Register'!$A:$A,0))) | E41: =IF($A41="","",INDEX('Animal Register'!$J:$J,MATCH($A41,'Animal Register'!$A:$A,0))) | F41: =IF($A41="","",INDEX('Animal Register'!$S:$S,MATCH($A41,'Animal Register'!$A:$A,0))) | G41: =IF($A41="","",INDEX('Animal Register'!$O:$O,MATCH($A41,'Animal Register'!$A:$A,0))) | H41: =IF($A41="","",INDEX('Animal Register'!$N:$N,MATCH($A41,'Animal Register'!$A:$A,0))) | I41: =IF($A41="","",INDEX('Animal Register'!$P:$P,MATCH($A41,'Animal Register'!$A:$A,0))) | J41: =IF($A41="","",IFERROR(INDEX($R$5:$R$104,MATCH($A41,$Q$5:$Q$104,0)),"-")) | K41: =IF($A41="","",IFERROR(INDEX($S$5:$S$104,MATCH($A41,$Q$5:$Q$104,0)),"-")) | L41: =IF($A41="","",IFERROR(INDEX($T$5:$T$104,MATCH($A41,$Q$5:$Q$104,0)),"-")) | M41: =IF($A41="","",IFERROR(INDEX($U$5:$U$104,MATCH($A41,$Q$5:$Q$104,0)),"-")) | N41: =IF($A41="","",IF(ISNUMBER(L41),L41-E41,"-"))
A42: =IFERROR(INDEX('Animal Register'!$A:$A,MATCH(38,'Animal Register'!$U:$U,0)),"") | B42: =IF($A42="","",INDEX('Animal Register'!$C:$C,MATCH($A42,'Animal Register'!$A:$A,0))) | C42: =IF($A42="","",INDEX('Animal Register'!$K:$K,MATCH($A42,'Animal Register'!$A:$A,0))) | D42: =IF($A42="","",INDEX('Animal Register'!$I:$I,MATCH($A42,'Animal Register'!$A:$A,0))) | E42: =IF($A42="","",INDEX('Animal Register'!$J:$J,MATCH($A42,'Animal Register'!$A:$A,0))) | F42: =IF($A42="","",INDEX('Animal Register'!$S:$S,MATCH($A42,'Animal Register'!$A:$A,0))) | G42: =IF($A42="","",INDEX('Animal Register'!$O:$O,MATCH($A42,'Animal Register'!$A:$A,0))) | H42: =IF($A42="","",INDEX('Animal Register'!$N:$N,MATCH($A42,'Animal Register'!$A:$A,0))) | I42: =IF($A42="","",INDEX('Animal Register'!$P:$P,MATCH($A42,'Animal Register'!$A:$A,0))) | J42: =IF($A42="","",IFERROR(INDEX($R$5:$R$104,MATCH($A42,$Q$5:$Q$104,0)),"-")) | K42: =IF($A42="","",IFERROR(INDEX($S$5:$S$104,MATCH($A42,$Q$5:$Q$104,0)),"-")) | L42: =IF($A42="","",IFERROR(INDEX($T$5:$T$104,MATCH($A42,$Q$5:$Q$104,0)),"-")) | M42: =IF($A42="","",IFERROR(INDEX($U$5:$U$104,MATCH($A42,$Q$5:$Q$104,0)),"-")) | N42: =IF($A42="","",IF(ISNUMBER(L42),L42-E42,"-"))
A43: =IFERROR(INDEX('Animal Register'!$A:$A,MATCH(39,'Animal Register'!$U:$U,0)),"") | B43: =IF($A43="","",INDEX('Animal Register'!$C:$C,MATCH($A43,'Animal Register'!$A:$A,0))) | C43: =IF($A43="","",INDEX('Animal Register'!$K:$K,MATCH($A43,'Animal Register'!$A:$A,0))) | D43: =IF($A43="","",INDEX('Animal Register'!$I:$I,MATCH($A43,'Animal Register'!$A:$A,0))) | E43: =IF($A43="","",INDEX('Animal Register'!$J:$J,MATCH($A43,'Animal Register'!$A:$A,0))) | F43: =IF($A43="","",INDEX('Animal Register'!$S:$S,MATCH($A43,'Animal Register'!$A:$A,0))) | G43: =IF($A43="","",INDEX('Animal Register'!$O:$O,MATCH($A43,'Animal Register'!$A:$A,0))) | H43: =IF($A43="","",INDEX('Animal Register'!$N:$N,MATCH($A43,'Animal Register'!$A:$A,0))) | I43: =IF($A43="","",INDEX('Animal Register'!$P:$P,MATCH($A43,'Animal Register'!$A:$A,0))) | J43: =IF($A43="","",IFERROR(INDEX($R$5:$R$104,MATCH($A43,$Q$5:$Q$104,0)),"-")) | K43: =IF($A43="","",IFERROR(INDEX($S$5:$S$104,MATCH($A43,$Q$5:$Q$104,0)),"-")) | L43: =IF($A43="","",IFERROR(INDEX($T$5:$T$104,MATCH($A43,$Q$5:$Q$104,0)),"-")) | M43: =IF($A43="","",IFERROR(INDEX($U$5:$U$104,MATCH($A43,$Q$5:$Q$104,0)),"-")) | N43: =IF($A43="","",IF(ISNUMBER(L43),L43-E43,"-"))
A44: =IFERROR(INDEX('Animal Register'!$A:$A,MATCH(40,'Animal Register'!$U:$U,0)),"") | B44: =IF($A44="","",INDEX('Animal Register'!$C:$C,MATCH($A44,'Animal Register'!$A:$A,0))) | C44: =IF($A44="","",INDEX('Animal Register'!$K:$K,MATCH($A44,'Animal Register'!$A:$A,0))) | D44: =IF($A44="","",INDEX('Animal Register'!$I:$I,MATCH($A44,'Animal Register'!$A:$A,0))) | E44: =IF($A44="","",INDEX('Animal Register'!$J:$J,MATCH($A44,'Animal Register'!$A:$A,0))) | F44: =IF($A44="","",INDEX('Animal Register'!$S:$S,MATCH($A44,'Animal Register'!$A:$A,0))) | G44: =IF($A44="","",INDEX('Animal Register'!$O:$O,MATCH($A44,'Animal Register'!$A:$A,0))) | H44: =IF($A44="","",INDEX('Animal Register'!$N:$N,MATCH($A44,'Animal Register'!$A:$A,0))) | I44: =IF($A44="","",INDEX('Animal Register'!$P:$P,MATCH($A44,'Animal Register'!$A:$A,0))) | J44: =IF($A44="","",IFERROR(INDEX($R$5:$R$104,MATCH($A44,$Q$5:$Q$104,0)),"-")) | K44: =IF($A44="","",IFERROR(INDEX($S$5:$S$104,MATCH($A44,$Q$5:$Q$104,0)),"-")) | L44: =IF($A44="","",IFERROR(INDEX($T$5:$T$104,MATCH($A44,$Q$5:$Q$104,0)),"-")) | M44: =IF($A44="","",IFERROR(INDEX($U$5:$U$104,MATCH($A44,$Q$5:$Q$104,0)),"-")) | N44: =IF($A44="","",IF(ISNUMBER(L44),L44-E44,"-"))
A45: =IFERROR(INDEX('Animal Register'!$A:$A,MATCH(41,'Animal Register'!$U:$U,0)),"") | B45: =IF($A45="","",INDEX('Animal Register'!$C:$C,MATCH($A45,'Animal Register'!$A:$A,0))) | C45: =IF($A45="","",INDEX('Animal Register'!$K:$K,MATCH($A45,'Animal Register'!$A:$A,0))) | D45: =IF($A45="","",INDEX('Animal Register'!$I:$I,MATCH($A45,'Animal Register'!$A:$A,0))) | E45: =IF($A45="","",INDEX('Animal Register'!$J:$J,MATCH($A45,'Animal Register'!$A:$A,0))) | F45: =IF($A45="","",INDEX('Animal Register'!$S:$S,MATCH($A45,'Animal Register'!$A:$A,0))) | G45: =IF($A45="","",INDEX('Animal Register'!$O:$O,MATCH($A45,'Animal Register'!$A:$A,0))) | H45: =IF($A45="","",INDEX('Animal Register'!$N:$N,MATCH($A45,'Animal Register'!$A:$A,0))) | I45: =IF($A45="","",INDEX('Animal Register'!$P:$P,MATCH($A45,'Animal Register'!$A:$A,0))) | J45: =IF($A45="","",IFERROR(INDEX($R$5:$R$104,MATCH($A45,$Q$5:$Q$104,0)),"-")) | K45: =IF($A45="","",IFERROR(INDEX($S$5:$S$104,MATCH($A45,$Q$5:$Q$104,0)),"-")) | L45: =IF($A45="","",IFERROR(INDEX($T$5:$T$104,MATCH($A45,$Q$5:$Q$104,0)),"-")) | M45: =IF($A45="","",IFERROR(INDEX($U$5:$U$104,MATCH($A45,$Q$5:$Q$104,0)),"-")) | N45: =IF($A45="","",IF(ISNUMBER(L45),L45-E45,"-"))
A46: =IFERROR(INDEX('Animal Register'!$A:$A,MATCH(42,'Animal Register'!$U:$U,0)),"") | B46: =IF($A46="","",INDEX('Animal Register'!$C:$C,MATCH($A46,'Animal Register'!$A:$A,0))) | C46: =IF($A46="","",INDEX('Animal Register'!$K:$K,MATCH($A46,'Animal Register'!$A:$A,0))) | D46: =IF($A46="","",INDEX('Animal Register'!$I:$I,MATCH($A46,'Animal Register'!$A:$A,0))) | E46: =IF($A46="","",INDEX('Animal Register'!$J:$J,MATCH($A46,'Animal Register'!$A:$A,0))) | F46: =IF($A46="","",INDEX('Animal Register'!$S:$S,MATCH($A46,'Animal Register'!$A:$A,0))) | G46: =IF($A46="","",INDEX('Animal Register'!$O:$O,MATCH($A46,'Animal Register'!$A:$A,0))) | H46: =IF($A46="","",INDEX('Animal Register'!$N:$N,MATCH($A46,'Animal Register'!$A:$A,0))) | I46: =IF($A46="","",INDEX('Animal Register'!$P:$P,MATCH($A46,'Animal Register'!$A:$A,0))) | J46: =IF($A46="","",IFERROR(INDEX($R$5:$R$104,MATCH($A46,$Q$5:$Q$104,0)),"-")) | K46: =IF($A46="","",IFERROR(INDEX($S$5:$S$104,MATCH($A46,$Q$5:$Q$104,0)),"-")) | L46: =IF($A46="","",IFERROR(INDEX($T$5:$T$104,MATCH($A46,$Q$5:$Q$104,0)),"-")) | M46: =IF($A46="","",IFERROR(INDEX($U$5:$U$104,MATCH($A46,$Q$5:$Q$104,0)),"-")) | N46: =IF($A46="","",IF(ISNUMBER(L46),L46-E46,"-"))
A47: =IFERROR(INDEX('Animal Register'!$A:$A,MATCH(43,'Animal Register'!$U:$U,0)),"") | B47: =IF($A47="","",INDEX('Animal Register'!$C:$C,MATCH($A47,'Animal Register'!$A:$A,0))) | C47: =IF($A47="","",INDEX('Animal Register'!$K:$K,MATCH($A47,'Animal Register'!$A:$A,0))) | D47: =IF($A47="","",INDEX('Animal Register'!$I:$I,MATCH($A47,'Animal Register'!$A:$A,0))) | E47: =IF($A47="","",INDEX('Animal Register'!$J:$J,MATCH($A47,'Animal Register'!$A:$A,0))) | F47: =IF($A47="","",INDEX('Animal Register'!$S:$S,MATCH($A47,'Animal Register'!$A:$A,0))) | G47: =IF($A47="","",INDEX('Animal Register'!$O:$O,MATCH($A47,'Animal Register'!$A:$A,0))) | H47: =IF($A47="","",INDEX('Animal Register'!$N:$N,MATCH($A47,'Animal Register'!$A:$A,0))) | I47: =IF($A47="","",INDEX('Animal Register'!$P:$P,MATCH($A47,'Animal Register'!$A:$A,0))) | J47: =IF($A47="","",IFERROR(INDEX($R$5:$R$104,MATCH($A47,$Q$5:$Q$104,0)),"-")) | K47: =IF($A47="","",IFERROR(INDEX($S$5:$S$104,MATCH($A47,$Q$5:$Q$104,0)),"-")) | L47: =IF($A47="","",IFERROR(INDEX($T$5:$T$104,MATCH($A47,$Q$5:$Q$104,0)),"-")) | M47: =IF($A47="","",IFERROR(INDEX($U$5:$U$104,MATCH($A47,$Q$5:$Q$104,0)),"-")) | N47: =IF($A47="","",IF(ISNUMBER(L47),L47-E47,"-"))
A48: =IFERROR(INDEX('Animal Register'!$A:$A,MATCH(44,'Animal Register'!$U:$U,0)),"") | B48: =IF($A48="","",INDEX('Animal Register'!$C:$C,MATCH($A48,'Animal Register'!$A:$A,0))) | C48: =IF($A48="","",INDEX('Animal Register'!$K:$K,MATCH($A48,'Animal Register'!$A:$A,0))) | D48: =IF($A48="","",INDEX('Animal Register'!$I:$I,MATCH($A48,'Animal Register'!$A:$A,0))) | E48: =IF($A48="","",INDEX('Animal Register'!$J:$J,MATCH($A48,'Animal Register'!$A:$A,0))) | F48: =IF($A48="","",INDEX('Animal Register'!$S:$S,MATCH($A48,'Animal Register'!$A:$A,0))) | G48: =IF($A48="","",INDEX('Animal Register'!$O:$O,MATCH($A48,'Animal Register'!$A:$A,0))) | H48: =IF($A48="","",INDEX('Animal Register'!$N:$N,MATCH($A48,'Animal Register'!$A:$A,0))) | I48: =IF($A48="","",INDEX('Animal Register'!$P:$P,MATCH($A48,'Animal Register'!$A:$A,0))) | J48: =IF($A48="","",IFERROR(INDEX($R$5:$R$104,MATCH($A48,$Q$5:$Q$104,0)),"-")) | K48: =IF($A48="","",IFERROR(INDEX($S$5:$S$104,MATCH($A48,$Q$5:$Q$104,0)),"-")) | L48: =IF($A48="","",IFERROR(INDEX($T$5:$T$104,MATCH($A48,$Q$5:$Q$104,0)),"-")) | M48: =IF($A48="","",IFERROR(INDEX($U$5:$U$104,MATCH($A48,$Q$5:$Q$104,0)),"-")) | N48: =IF($A48="","",IF(ISNUMBER(L48),L48-E48,"-"))
A49: =IFERROR(INDEX('Animal Register'!$A:$A,MATCH(45,'Animal Register'!$U:$U,0)),"") | B49: =IF($A49="","",INDEX('Animal Register'!$C:$C,MATCH($A49,'Animal Register'!$A:$A,0))) | C49: =IF($A49="","",INDEX('Animal Register'!$K:$K,MATCH($A49,'Animal Register'!$A:$A,0))) | D49: =IF($A49="","",INDEX('Animal Register'!$I:$I,MATCH($A49,'Animal Register'!$A:$A,0))) | E49: =IF($A49="","",INDEX('Animal Register'!$J:$J,MATCH($A49,'Animal Register'!$A:$A,0))) | F49: =IF($A49="","",INDEX('Animal Register'!$S:$S,MATCH($A49,'Animal Register'!$A:$A,0))) | G49: =IF($A49="","",INDEX('Animal Register'!$O:$O,MATCH($A49,'Animal Register'!$A:$A,0))) | H49: =IF($A49="","",INDEX('Animal Register'!$N:$N,MATCH($A49,'Animal Register'!$A:$A,0))) | I49: =IF($A49="","",INDEX('Animal Register'!$P:$P,MATCH($A49,'Animal Register'!$A:$A,0))) | J49: =IF($A49="","",IFERROR(INDEX($R$5:$R$104,MATCH($A49,$Q$5:$Q$104,0)),"-")) | K49: =IF($A49="","",IFERROR(INDEX($S$5:$S$104,MATCH($A49,$Q$5:$Q$104,0)),"-")) | L49: =IF($A49="","",IFERROR(INDEX($T$5:$T$104,MATCH($A49,$Q$5:$Q$104,0)),"-")) | M49: =IF($A49="","",IFERROR(INDEX($U$5:$U$104,MATCH($A49,$Q$5:$Q$104,0)),"-")) | N49: =IF($A49="","",IF(ISNUMBER(L49),L49-E49,"-"))
A50: =IFERROR(INDEX('Animal Register'!$A:$A,MATCH(46,'Animal Register'!$U:$U,0)),"") | B50: =IF($A50="","",INDEX('Animal Register'!$C:$C,MATCH($A50,'Animal Register'!$A:$A,0))) | C50: =IF($A50="","",INDEX('Animal Register'!$K:$K,MATCH($A50,'Animal Register'!$A:$A,0))) | D50: =IF($A50="","",INDEX('Animal Register'!$I:$I,MATCH($A50,'Animal Register'!$A:$A,0))) | E50: =IF($A50="","",INDEX('Animal Register'!$J:$J,MATCH($A50,'Animal Register'!$A:$A,0))) | F50: =IF($A50="","",INDEX('Animal Register'!$S:$S,MATCH($A50,'Animal Register'!$A:$A,0))) | G50: =IF($A50="","",INDEX('Animal Register'!$O:$O,MATCH($A50,'Animal Register'!$A:$A,0))) | H50: =IF($A50="","",INDEX('Animal Register'!$N:$N,MATCH($A50,'Animal Register'!$A:$A,0))) | I50: =IF($A50="","",INDEX('Animal Register'!$P:$P,MATCH($A50,'Animal Register'!$A:$A,0))) | J50: =IF($A50="","",IFERROR(INDEX($R$5:$R$104,MATCH($A50,$Q$5:$Q$104,0)),"-")) | K50: =IF($A50="","",IFERROR(INDEX($S$5:$S$104,MATCH($A50,$Q$5:$Q$104,0)),"-")) | L50: =IF($A50="","",IFERROR(INDEX($T$5:$T$104,MATCH($A50,$Q$5:$Q$104,0)),"-")) | M50: =IF($A50="","",IFERROR(INDEX($U$5:$U$104,MATCH($A50,$Q$5:$Q$104,0)),"-")) | N50: =IF($A50="","",IF(ISNUMBER(L50),L50-E50,"-"))
A51: =IFERROR(INDEX('Animal Register'!$A:$A,MATCH(47,'Animal Register'!$U:$U,0)),"") | B51: =IF($A51="","",INDEX('Animal Register'!$C:$C,MATCH($A51,'Animal Register'!$A:$A,0))) | C51: =IF($A51="","",INDEX('Animal Register'!$K:$K,MATCH($A51,'Animal Register'!$A:$A,0))) | D51: =IF($A51="","",INDEX('Animal Register'!$I:$I,MATCH($A51,'Animal Register'!$A:$A,0))) | E51: =IF($A51="","",INDEX('Animal Register'!$J:$J,MATCH($A51,'Animal Register'!$A:$A,0))) | F51: =IF($A51="","",INDEX('Animal Register'!$S:$S,MATCH($A51,'Animal Register'!$A:$A,0))) | G51: =IF($A51="","",INDEX('Animal Register'!$O:$O,MATCH($A51,'Animal Register'!$A:$A,0))) | H51: =IF($A51="","",INDEX('Animal Register'!$N:$N,MATCH($A51,'Animal Register'!$A:$A,0))) | I51: =IF($A51="","",INDEX('Animal Register'!$P:$P,MATCH($A51,'Animal Register'!$A:$A,0))) | J51: =IF($A51="","",IFERROR(INDEX($R$5:$R$104,MATCH($A51,$Q$5:$Q$104,0)),"-")) | K51: =IF($A51="","",IFERROR(INDEX($S$5:$S$104,MATCH($A51,$Q$5:$Q$104,0)),"-")) | L51: =IF($A51="","",IFERROR(INDEX($T$5:$T$104,MATCH($A51,$Q$5:$Q$104,0)),"-")) | M51: =IF($A51="","",IFERROR(INDEX($U$5:$U$104,MATCH($A51,$Q$5:$Q$104,0)),"-")) | N51: =IF($A51="","",IF(ISNUMBER(L51),L51-E51,"-"))
A52: =IFERROR(INDEX('Animal Register'!$A:$A,MATCH(48,'Animal Register'!$U:$U,0)),"") | B52: =IF($A52="","",INDEX('Animal Register'!$C:$C,MATCH($A52,'Animal Register'!$A:$A,0))) | C52: =IF($A52="","",INDEX('Animal Register'!$K:$K,MATCH($A52,'Animal Register'!$A:$A,0))) | D52: =IF($A52="","",INDEX('Animal Register'!$I:$I,MATCH($A52,'Animal Register'!$A:$A,0))) | E52: =IF($A52="","",INDEX('Animal Register'!$J:$J,MATCH($A52,'Animal Register'!$A:$A,0))) | F52: =IF($A52="","",INDEX('Animal Register'!$S:$S,MATCH($A52,'Animal Register'!$A:$A,0))) | G52: =IF($A52="","",INDEX('Animal Register'!$O:$O,MATCH($A52,'Animal Register'!$A:$A,0))) | H52: =IF($A52="","",INDEX('Animal Register'!$N:$N,MATCH($A52,'Animal Register'!$A:$A,0))) | I52: =IF($A52="","",INDEX('Animal Register'!$P:$P,MATCH($A52,'Animal Register'!$A:$A,0))) | J52: =IF($A52="","",IFERROR(INDEX($R$5:$R$104,MATCH($A52,$Q$5:$Q$104,0)),"-")) | K52: =IF($A52="","",IFERROR(INDEX($S$5:$S$104,MATCH($A52,$Q$5:$Q$104,0)),"-")) | L52: =IF($A52="","",IFERROR(INDEX($T$5:$T$104,MATCH($A52,$Q$5:$Q$104,0)),"-")) | M52: =IF($A52="","",IFERROR(INDEX($U$5:$U$104,MATCH($A52,$Q$5:$Q$104,0)),"-")) | N52: =IF($A52="","",IF(ISNUMBER(L52),L52-E52,"-"))
A53: =IFERROR(INDEX('Animal Register'!$A:$A,MATCH(49,'Animal Register'!$U:$U,0)),"") | B53: =IF($A53="","",INDEX('Animal Register'!$C:$C,MATCH($A53,'Animal Register'!$A:$A,0))) | C53: =IF($A53="","",INDEX('Animal Register'!$K:$K,MATCH($A53,'Animal Register'!$A:$A,0))) | D53: =IF($A53="","",INDEX('Animal Register'!$I:$I,MATCH($A53,'Animal Register'!$A:$A,0))) | E53: =IF($A53="","",INDEX('Animal Register'!$J:$J,MATCH($A53,'Animal Register'!$A:$A,0))) | F53: =IF($A53="","",INDEX('Animal Register'!$S:$S,MATCH($A53,'Animal Register'!$A:$A,0))) | G53: =IF($A53="","",INDEX('Animal Register'!$O:$O,MATCH($A53,'Animal Register'!$A:$A,0))) | H53: =IF($A53="","",INDEX('Animal Register'!$N:$N,MATCH($A53,'Animal Register'!$A:$A,0))) | I53: =IF($A53="","",INDEX('Animal Register'!$P:$P,MATCH($A53,'Animal Register'!$A:$A,0))) | J53: =IF($A53="","",IFERROR(INDEX($R$5:$R$104,MATCH($A53,$Q$5:$Q$104,0)),"-")) | K53: =IF($A53="","",IFERROR(INDEX($S$5:$S$104,MATCH($A53,$Q$5:$Q$104,0)),"-")) | L53: =IF($A53="","",IFERROR(INDEX($T$5:$T$104,MATCH($A53,$Q$5:$Q$104,0)),"-")) | M53: =IF($A53="","",IFERROR(INDEX($U$5:$U$104,MATCH($A53,$Q$5:$Q$104,0)),"-")) | N53: =IF($A53="","",IF(ISNUMBER(L53),L53-E53,"-"))
A54: =IFERROR(INDEX('Animal Register'!$A:$A,MATCH(50,'Animal Register'!$U:$U,0)),"") | B54: =IF($A54="","",INDEX('Animal Register'!$C:$C,MATCH($A54,'Animal Register'!$A:$A,0))) | C54: =IF($A54="","",INDEX('Animal Register'!$K:$K,MATCH($A54,'Animal Register'!$A:$A,0))) | D54: =IF($A54="","",INDEX('Animal Register'!$I:$I,MATCH($A54,'Animal Register'!$A:$A,0))) | E54: =IF($A54="","",INDEX('Animal Register'!$J:$J,MATCH($A54,'Animal Register'!$A:$A,0))) | F54: =IF($A54="","",INDEX('Animal Register'!$S:$S,MATCH($A54,'Animal Register'!$A:$A,0))) | G54: =IF($A54="","",INDEX('Animal Register'!$O:$O,MATCH($A54,'Animal Register'!$A:$A,0))) | H54: =IF($A54="","",INDEX('Animal Register'!$N:$N,MATCH($A54,'Animal Register'!$A:$A,0))) | I54: =IF($A54="","",INDEX('Animal Register'!$P:$P,MATCH($A54,'Animal Register'!$A:$A,0))) | J54: =IF($A54="","",IFERROR(INDEX($R$5:$R$104,MATCH($A54,$Q$5:$Q$104,0)),"-")) | K54: =IF($A54="","",IFERROR(INDEX($S$5:$S$104,MATCH($A54,$Q$5:$Q$104,0)),"-")) | L54: =IF($A54="","",IFERROR(INDEX($T$5:$T$104,MATCH($A54,$Q$5:$Q$104,0)),"-")) | M54: =IF($A54="","",IFERROR(INDEX($U$5:$U$104,MATCH($A54,$Q$5:$Q$104,0)),"-")) | N54: =IF($A54="","",IF(ISNUMBER(L54),L54-E54,"-"))
A55: =IFERROR(INDEX('Animal Register'!$A:$A,MATCH(51,'Animal Register'!$U:$U,0)),"") | B55: =IF($A55="","",INDEX('Animal Register'!$C:$C,MATCH($A55,'Animal Register'!$A:$A,0))) | C55: =IF($A55="","",INDEX('Animal Register'!$K:$K,MATCH($A55,'Animal Register'!$A:$A,0))) | D55: =IF($A55="","",INDEX('Animal Register'!$I:$I,MATCH($A55,'Animal Register'!$A:$A,0))) | E55: =IF($A55="","",INDEX('Animal Register'!$J:$J,MATCH($A55,'Animal Register'!$A:$A,0))) | F55: =IF($A55="","",INDEX('Animal Register'!$S:$S,MATCH($A55,'Animal Register'!$A:$A,0))) | G55: =IF($A55="","",INDEX('Animal Register'!$O:$O,MATCH($A55,'Animal Register'!$A:$A,0))) | H55: =IF($A55="","",INDEX('Animal Register'!$N:$N,MATCH($A55,'Animal Register'!$A:$A,0))) | I55: =IF($A55="","",INDEX('Animal Register'!$P:$P,MATCH($A55,'Animal Register'!$A:$A,0))) | J55: =IF($A55="","",IFERROR(INDEX($R$5:$R$104,MATCH($A55,$Q$5:$Q$104,0)),"-")) | K55: =IF($A55="","",IFERROR(INDEX($S$5:$S$104,MATCH($A55,$Q$5:$Q$104,0)),"-")) | L55: =IF($A55="","",IFERROR(INDEX($T$5:$T$104,MATCH($A55,$Q$5:$Q$104,0)),"-")) | M55: =IF($A55="","",IFERROR(INDEX($U$5:$U$104,MATCH($A55,$Q$5:$Q$104,0)),"-")) | N55: =IF($A55="","",IF(ISNUMBER(L55),L55-E55,"-"))
A56: =IFERROR(INDEX('Animal Register'!$A:$A,MATCH(52,'Animal Register'!$U:$U,0)),"") | B56: =IF($A56="","",INDEX('Animal Register'!$C:$C,MATCH($A56,'Animal Register'!$A:$A,0))) | C56: =IF($A56="","",INDEX('Animal Register'!$K:$K,MATCH($A56,'Animal Register'!$A:$A,0))) | D56: =IF($A56="","",INDEX('Animal Register'!$I:$I,MATCH($A56,'Animal Register'!$A:$A,0))) | E56: =IF($A56="","",INDEX('Animal Register'!$J:$J,MATCH($A56,'Animal Register'!$A:$A,0))) | F56: =IF($A56="","",INDEX('Animal Register'!$S:$S,MATCH($A56,'Animal Register'!$A:$A,0))) | G56: =IF($A56="","",INDEX('Animal Register'!$O:$O,MATCH($A56,'Animal Register'!$A:$A,0))) | H56: =IF($A56="","",INDEX('Animal Register'!$N:$N,MATCH($A56,'Animal Register'!$A:$A,0))) | I56: =IF($A56="","",INDEX('Animal Register'!$P:$P,MATCH($A56,'Animal Register'!$A:$A,0))) | J56: =IF($A56="","",IFERROR(INDEX($R$5:$R$104,MATCH($A56,$Q$5:$Q$104,0)),"-")) | K56: =IF($A56="","",IFERROR(INDEX($S$5:$S$104,MATCH($A56,$Q$5:$Q$104,0)),"-")) | L56: =IF($A56="","",IFERROR(INDEX($T$5:$T$104,MATCH($A56,$Q$5:$Q$104,0)),"-")) | M56: =IF($A56="","",IFERROR(INDEX($U$5:$U$104,MATCH($A56,$Q$5:$Q$104,0)),"-")) | N56: =IF($A56="","",IF(ISNUMBER(L56),L56-E56,"-"))
A57: =IFERROR(INDEX('Animal Register'!$A:$A,MATCH(53,'Animal Register'!$U:$U,0)),"") | B57: =IF($A57="","",INDEX('Animal Register'!$C:$C,MATCH($A57,'Animal Register'!$A:$A,0))) | C57: =IF($A57="","",INDEX('Animal Register'!$K:$K,MATCH($A57,'Animal Register'!$A:$A,0))) | D57: =IF($A57="","",INDEX('Animal Register'!$I:$I,MATCH($A57,'Animal Register'!$A:$A,0))) | E57: =IF($A57="","",INDEX('Animal Register'!$J:$J,MATCH($A57,'Animal Register'!$A:$A,0))) | F57: =IF($A57="","",INDEX('Animal Register'!$S:$S,MATCH($A57,'Animal Register'!$A:$A,0))) | G57: =IF($A57="","",INDEX('Animal Register'!$O:$O,MATCH($A57,'Animal Register'!$A:$A,0))) | H57: =IF($A57="","",INDEX('Animal Register'!$N:$N,MATCH($A57,'Animal Register'!$A:$A,0))) | I57: =IF($A57="","",INDEX('Animal Register'!$P:$P,MATCH($A57,'Animal Register'!$A:$A,0))) | J57: =IF($A57="","",IFERROR(INDEX($R$5:$R$104,MATCH($A57,$Q$5:$Q$104,0)),"-")) | K57: =IF($A57="","",IFERROR(INDEX($S$5:$S$104,MATCH($A57,$Q$5:$Q$104,0)),"-")) | L57: =IF($A57="","",IFERROR(INDEX($T$5:$T$104,MATCH($A57,$Q$5:$Q$104,0)),"-")) | M57: =IF($A57="","",IFERROR(INDEX($U$5:$U$104,MATCH($A57,$Q$5:$Q$104,0)),"-")) | N57: =IF($A57="","",IF(ISNUMBER(L57),L57-E57,"-"))
A58: =IFERROR(INDEX('Animal Register'!$A:$A,MATCH(54,'Animal Register'!$U:$U,0)),"") | B58: =IF($A58="","",INDEX('Animal Register'!$C:$C,MATCH($A58,'Animal Register'!$A:$A,0))) | C58: =IF($A58="","",INDEX('Animal Register'!$K:$K,MATCH($A58,'Animal Register'!$A:$A,0))) | D58: =IF($A58="","",INDEX('Animal Register'!$I:$I,MATCH($A58,'Animal Register'!$A:$A,0))) | E58: =IF($A58="","",INDEX('Animal Register'!$J:$J,MATCH($A58,'Animal Register'!$A:$A,0))) | F58: =IF($A58="","",INDEX('Animal Register'!$S:$S,MATCH($A58,'Animal Register'!$A:$A,0))) | G58: =IF($A58="","",INDEX('Animal Register'!$O:$O,MATCH($A58,'Animal Register'!$A:$A,0))) | H58: =IF($A58="","",INDEX('Animal Register'!$N:$N,MATCH($A58,'Animal Register'!$A:$A,0))) | I58: =IF($A58="","",INDEX('Animal Register'!$P:$P,MATCH($A58,'Animal Register'!$A:$A,0))) | J58: =IF($A58="","",IFERROR(INDEX($R$5:$R$104,MATCH($A58,$Q$5:$Q$104,0)),"-")) | K58: =IF($A58="","",IFERROR(INDEX($S$5:$S$104,MATCH($A58,$Q$5:$Q$104,0)),"-")) | L58: =IF($A58="","",IFERROR(INDEX($T$5:$T$104,MATCH($A58,$Q$5:$Q$104,0)),"-")) | M58: =IF($A58="","",IFERROR(INDEX($U$5:$U$104,MATCH($A58,$Q$5:$Q$104,0)),"-")) | N58: =IF($A58="","",IF(ISNUMBER(L58),L58-E58,"-"))
A59: =IFERROR(INDEX('Animal Register'!$A:$A,MATCH(55,'Animal Register'!$U:$U,0)),"") | B59: =IF($A59="","",INDEX('Animal Register'!$C:$C,MATCH($A59,'Animal Register'!$A:$A,0))) | C59: =IF($A59="","",INDEX('Animal Register'!$K:$K,MATCH($A59,'Animal Register'!$A:$A,0))) | D59: =IF($A59="","",INDEX('Animal Register'!$I:$I,MATCH($A59,'Animal Register'!$A:$A,0))) | E59: =IF($A59="","",INDEX('Animal Register'!$J:$J,MATCH($A59,'Animal Register'!$A:$A,0))) | F59: =IF($A59="","",INDEX('Animal Register'!$S:$S,MATCH($A59,'Animal Register'!$A:$A,0))) | G59: =IF($A59="","",INDEX('Animal Register'!$O:$O,MATCH($A59,'Animal Register'!$A:$A,0))) | H59: =IF($A59="","",INDEX('Animal Register'!$N:$N,MATCH($A59,'Animal Register'!$A:$A,0))) | I59: =IF($A59="","",INDEX('Animal Register'!$P:$P,MATCH($A59,'Animal Register'!$A:$A,0))) | J59: =IF($A59="","",IFERROR(INDEX($R$5:$R$104,MATCH($A59,$Q$5:$Q$104,0)),"-")) | K59: =IF($A59="","",IFERROR(INDEX($S$5:$S$104,MATCH($A59,$Q$5:$Q$104,0)),"-")) | L59: =IF($A59="","",IFERROR(INDEX($T$5:$T$104,MATCH($A59,$Q$5:$Q$104,0)),"-")) | M59: =IF($A59="","",IFERROR(INDEX($U$5:$U$104,MATCH($A59,$Q$5:$Q$104,0)),"-")) | N59: =IF($A59="","",IF(ISNUMBER(L59),L59-E59,"-"))
A60: =IFERROR(INDEX('Animal Register'!$A:$A,MATCH(56,'Animal Register'!$U:$U,0)),"") | B60: =IF($A60="","",INDEX('Animal Register'!$C:$C,MATCH($A60,'Animal Register'!$A:$A,0))) | C60: =IF($A60="","",INDEX('Animal Register'!$K:$K,MATCH($A60,'Animal Register'!$A:$A,0))) | D60: =IF($A60="","",INDEX('Animal Register'!$I:$I,MATCH($A60,'Animal Register'!$A:$A,0))) | E60: =IF($A60="","",INDEX('Animal Register'!$J:$J,MATCH($A60,'Animal Register'!$A:$A,0))) | F60: =IF($A60="","",INDEX('Animal Register'!$S:$S,MATCH($A60,'Animal Register'!$A:$A,0))) | G60: =IF($A60="","",INDEX('Animal Register'!$O:$O,MATCH($A60,'Animal Register'!$A:$A,0))) | H60: =IF($A60="","",INDEX('Animal Register'!$N:$N,MATCH($A60,'Animal Register'!$A:$A,0))) | I60: =IF($A60="","",INDEX('Animal Register'!$P:$P,MATCH($A60,'Animal Register'!$A:$A,0))) | J60: =IF($A60="","",IFERROR(INDEX($R$5:$R$104,MATCH($A60,$Q$5:$Q$104,0)),"-")) | K60: =IF($A60="","",IFERROR(INDEX($S$5:$S$104,MATCH($A60,$Q$5:$Q$104,0)),"-")) | L60: =IF($A60="","",IFERROR(INDEX($T$5:$T$104,MATCH($A60,$Q$5:$Q$104,0)),"-")) | M60: =IF($A60="","",IFERROR(INDEX($U$5:$U$104,MATCH($A60,$Q$5:$Q$104,0)),"-")) | N60: =IF($A60="","",IF(ISNUMBER(L60),L60-E60,"-"))
A61: =IFERROR(INDEX('Animal Register'!$A:$A,MATCH(57,'Animal Register'!$U:$U,0)),"") | B61: =IF($A61="","",INDEX('Animal Register'!$C:$C,MATCH($A61,'Animal Register'!$A:$A,0))) | C61: =IF($A61="","",INDEX('Animal Register'!$K:$K,MATCH($A61,'Animal Register'!$A:$A,0))) | D61: =IF($A61="","",INDEX('Animal Register'!$I:$I,MATCH($A61,'Animal Register'!$A:$A,0))) | E61: =IF($A61="","",INDEX('Animal Register'!$J:$J,MATCH($A61,'Animal Register'!$A:$A,0))) | F61: =IF($A61="","",INDEX('Animal Register'!$S:$S,MATCH($A61,'Animal Register'!$A:$A,0))) | G61: =IF($A61="","",INDEX('Animal Register'!$O:$O,MATCH($A61,'Animal Register'!$A:$A,0))) | H61: =IF($A61="","",INDEX('Animal Register'!$N:$N,MATCH($A61,'Animal Register'!$A:$A,0))) | I61: =IF($A61="","",INDEX('Animal Register'!$P:$P,MATCH($A61,'Animal Register'!$A:$A,0))) | J61: =IF($A61="","",IFERROR(INDEX($R$5:$R$104,MATCH($A61,$Q$5:$Q$104,0)),"-")) | K61: =IF($A61="","",IFERROR(INDEX($S$5:$S$104,MATCH($A61,$Q$5:$Q$104,0)),"-")) | L61: =IF($A61="","",IFERROR(INDEX($T$5:$T$104,MATCH($A61,$Q$5:$Q$104,0)),"-")) | M61: =IF($A61="","",IFERROR(INDEX($U$5:$U$104,MATCH($A61,$Q$5:$Q$104,0)),"-")) | N61: =IF($A61="","",IF(ISNUMBER(L61),L61-E61,"-"))
A62: =IFERROR(INDEX('Animal Register'!$A:$A,MATCH(58,'Animal Register'!$U:$U,0)),"") | B62: =IF($A62="","",INDEX('Animal Register'!$C:$C,MATCH($A62,'Animal Register'!$A:$A,0))) | C62: =IF($A62="","",INDEX('Animal Register'!$K:$K,MATCH($A62,'Animal Register'!$A:$A,0))) | D62: =IF($A62="","",INDEX('Animal Register'!$I:$I,MATCH($A62,'Animal Register'!$A:$A,0))) | E62: =IF($A62="","",INDEX('Animal Register'!$J:$J,MATCH($A62,'Animal Register'!$A:$A,0))) | F62: =IF($A62="","",INDEX('Animal Register'!$S:$S,MATCH($A62,'Animal Register'!$A:$A,0))) | G62: =IF($A62="","",INDEX('Animal Register'!$O:$O,MATCH($A62,'Animal Register'!$A:$A,0))) | H62: =IF($A62="","",INDEX('Animal Register'!$N:$N,MATCH($A62,'Animal Register'!$A:$A,0))) | I62: =IF($A62="","",INDEX('Animal Register'!$P:$P,MATCH($A62,'Animal Register'!$A:$A,0))) | J62: =IF($A62="","",IFERROR(INDEX($R$5:$R$104,MATCH($A62,$Q$5:$Q$104,0)),"-")) | K62: =IF($A62="","",IFERROR(INDEX($S$5:$S$104,MATCH($A62,$Q$5:$Q$104,0)),"-")) | L62: =IF($A62="","",IFERROR(INDEX($T$5:$T$104,MATCH($A62,$Q$5:$Q$104,0)),"-")) | M62: =IF($A62="","",IFERROR(INDEX($U$5:$U$104,MATCH($A62,$Q$5:$Q$104,0)),"-")) | N62: =IF($A62="","",IF(ISNUMBER(L62),L62-E62,"-"))
A63: =IFERROR(INDEX('Animal Register'!$A:$A,MATCH(59,'Animal Register'!$U:$U,0)),"") | B63: =IF($A63="","",INDEX('Animal Register'!$C:$C,MATCH($A63,'Animal Register'!$A:$A,0))) | C63: =IF($A63="","",INDEX('Animal Register'!$K:$K,MATCH($A63,'Animal Register'!$A:$A,0))) | D63: =IF($A63="","",INDEX('Animal Register'!$I:$I,MATCH($A63,'Animal Register'!$A:$A,0))) | E63: =IF($A63="","",INDEX('Animal Register'!$J:$J,MATCH($A63,'Animal Register'!$A:$A,0))) | F63: =IF($A63="","",INDEX('Animal Register'!$S:$S,MATCH($A63,'Animal Register'!$A:$A,0))) | G63: =IF($A63="","",INDEX('Animal Register'!$O:$O,MATCH($A63,'Animal Register'!$A:$A,0))) | H63: =IF($A63="","",INDEX('Animal Register'!$N:$N,MATCH($A63,'Animal Register'!$A:$A,0))) | I63: =IF($A63="","",INDEX('Animal Register'!$P:$P,MATCH($A63,'Animal Register'!$A:$A,0))) | J63: =IF($A63="","",IFERROR(INDEX($R$5:$R$104,MATCH($A63,$Q$5:$Q$104,0)),"-")) | K63: =IF($A63="","",IFERROR(INDEX($S$5:$S$104,MATCH($A63,$Q$5:$Q$104,0)),"-")) | L63: =IF($A63="","",IFERROR(INDEX($T$5:$T$104,MATCH($A63,$Q$5:$Q$104,0)),"-")) | M63: =IF($A63="","",IFERROR(INDEX($U$5:$U$104,MATCH($A63,$Q$5:$Q$104,0)),"-")) | N63: =IF($A63="","",IF(ISNUMBER(L63),L63-E63,"-"))
A64: =IFERROR(INDEX('Animal Register'!$A:$A,MATCH(60,'Animal Register'!$U:$U,0)),"") | B64: =IF($A64="","",INDEX('Animal Register'!$C:$C,MATCH($A64,'Animal Register'!$A:$A,0))) | C64: =IF($A64="","",INDEX('Animal Register'!$K:$K,MATCH($A64,'Animal Register'!$A:$A,0))) | D64: =IF($A64="","",INDEX('Animal Register'!$I:$I,MATCH($A64,'Animal Register'!$A:$A,0))) | E64: =IF($A64="","",INDEX('Animal Register'!$J:$J,MATCH($A64,'Animal Register'!$A:$A,0))) | F64: =IF($A64="","",INDEX('Animal Register'!$S:$S,MATCH($A64,'Animal Register'!$A:$A,0))) | G64: =IF($A64="","",INDEX('Animal Register'!$O:$O,MATCH($A64,'Animal Register'!$A:$A,0))) | H64: =IF($A64="","",INDEX('Animal Register'!$N:$N,MATCH($A64,'Animal Register'!$A:$A,0))) | I64: =IF($A64="","",INDEX('Animal Register'!$P:$P,MATCH($A64,'Animal Register'!$A:$A,0))) | J64: =IF($A64="","",IFERROR(INDEX($R$5:$R$104,MATCH($A64,$Q$5:$Q$104,0)),"-")) | K64: =IF($A64="","",IFERROR(INDEX($S$5:$S$104,MATCH($A64,$Q$5:$Q$104,0)),"-")) | L64: =IF($A64="","",IFERROR(INDEX($T$5:$T$104,MATCH($A64,$Q$5:$Q$104,0)),"-")) | M64: =IF($A64="","",IFERROR(INDEX($U$5:$U$104,MATCH($A64,$Q$5:$Q$104,0)),"-")) | N64: =IF($A64="","",IF(ISNUMBER(L64),L64-E64,"-"))
A65: =IFERROR(INDEX('Animal Register'!$A:$A,MATCH(61,'Animal Register'!$U:$U,0)),"") | B65: =IF($A65="","",INDEX('Animal Register'!$C:$C,MATCH($A65,'Animal Register'!$A:$A,0))) | C65: =IF($A65="","",INDEX('Animal Register'!$K:$K,MATCH($A65,'Animal Register'!$A:$A,0))) | D65: =IF($A65="","",INDEX('Animal Register'!$I:$I,MATCH($A65,'Animal Register'!$A:$A,0))) | E65: =IF($A65="","",INDEX('Animal Register'!$J:$J,MATCH($A65,'Animal Register'!$A:$A,0))) | F65: =IF($A65="","",INDEX('Animal Register'!$S:$S,MATCH($A65,'Animal Register'!$A:$A,0))) | G65: =IF($A65="","",INDEX('Animal Register'!$O:$O,MATCH($A65,'Animal Register'!$A:$A,0))) | H65: =IF($A65="","",INDEX('Animal Register'!$N:$N,MATCH($A65,'Animal Register'!$A:$A,0))) | I65: =IF($A65="","",INDEX('Animal Register'!$P:$P,MATCH($A65,'Animal Register'!$A:$A,0))) | J65: =IF($A65="","",IFERROR(INDEX($R$5:$R$104,MATCH($A65,$Q$5:$Q$104,0)),"-")) | K65: =IF($A65="","",IFERROR(INDEX($S$5:$S$104,MATCH($A65,$Q$5:$Q$104,0)),"-")) | L65: =IF($A65="","",IFERROR(INDEX($T$5:$T$104,MATCH($A65,$Q$5:$Q$104,0)),"-")) | M65: =IF($A65="","",IFERROR(INDEX($U$5:$U$104,MATCH($A65,$Q$5:$Q$104,0)),"-")) | N65: =IF($A65="","",IF(ISNUMBER(L65),L65-E65,"-"))
A66: =IFERROR(INDEX('Animal Register'!$A:$A,MATCH(62,'Animal Register'!$U:$U,0)),"") | B66: =IF($A66="","",INDEX('Animal Register'!$C:$C,MATCH($A66,'Animal Register'!$A:$A,0))) | C66: =IF($A66="","",INDEX('Animal Register'!$K:$K,MATCH($A66,'Animal Register'!$A:$A,0))) | D66: =IF($A66="","",INDEX('Animal Register'!$I:$I,MATCH($A66,'Animal Register'!$A:$A,0))) | E66: =IF($A66="","",INDEX('Animal Register'!$J:$J,MATCH($A66,'Animal Register'!$A:$A,0))) | F66: =IF($A66="","",INDEX('Animal Register'!$S:$S,MATCH($A66,'Animal Register'!$A:$A,0))) | G66: =IF($A66="","",INDEX('Animal Register'!$O:$O,MATCH($A66,'Animal Register'!$A:$A,0))) | H66: =IF($A66="","",INDEX('Animal Register'!$N:$N,MATCH($A66,'Animal Register'!$A:$A,0))) | I66: =IF($A66="","",INDEX('Animal Register'!$P:$P,MATCH($A66,'Animal Register'!$A:$A,0))) | J66: =IF($A66="","",IFERROR(INDEX($R$5:$R$104,MATCH($A66,$Q$5:$Q$104,0)),"-")) | K66: =IF($A66="","",IFERROR(INDEX($S$5:$S$104,MATCH($A66,$Q$5:$Q$104,0)),"-")) | L66: =IF($A66="","",IFERROR(INDEX($T$5:$T$104,MATCH($A66,$Q$5:$Q$104,0)),"-")) | M66: =IF($A66="","",IFERROR(INDEX($U$5:$U$104,MATCH($A66,$Q$5:$Q$104,0)),"-")) | N66: =IF($A66="","",IF(ISNUMBER(L66),L66-E66,"-"))
A67: =IFERROR(INDEX('Animal Register'!$A:$A,MATCH(63,'Animal Register'!$U:$U,0)),"") | B67: =IF($A67="","",INDEX('Animal Register'!$C:$C,MATCH($A67,'Animal Register'!$A:$A,0))) | C67: =IF($A67="","",INDEX('Animal Register'!$K:$K,MATCH($A67,'Animal Register'!$A:$A,0))) | D67: =IF($A67="","",INDEX('Animal Register'!$I:$I,MATCH($A67,'Animal Register'!$A:$A,0))) | E67: =IF($A67="","",INDEX('Animal Register'!$J:$J,MATCH($A67,'Animal Register'!$A:$A,0))) | F67: =IF($A67="","",INDEX('Animal Register'!$S:$S,MATCH($A67,'Animal Register'!$A:$A,0))) | G67: =IF($A67="","",INDEX('Animal Register'!$O:$O,MATCH($A67,'Animal Register'!$A:$A,0))) | H67: =IF($A67="","",INDEX('Animal Register'!$N:$N,MATCH($A67,'Animal Register'!$A:$A,0))) | I67: =IF($A67="","",INDEX('Animal Register'!$P:$P,MATCH($A67,'Animal Register'!$A:$A,0))) | J67: =IF($A67="","",IFERROR(INDEX($R$5:$R$104,MATCH($A67,$Q$5:$Q$104,0)),"-")) | K67: =IF($A67="","",IFERROR(INDEX($S$5:$S$104,MATCH($A67,$Q$5:$Q$104,0)),"-")) | L67: =IF($A67="","",IFERROR(INDEX($T$5:$T$104,MATCH($A67,$Q$5:$Q$104,0)),"-")) | M67: =IF($A67="","",IFERROR(INDEX($U$5:$U$104,MATCH($A67,$Q$5:$Q$104,0)),"-")) | N67: =IF($A67="","",IF(ISNUMBER(L67),L67-E67,"-"))
A68: =IFERROR(INDEX('Animal Register'!$A:$A,MATCH(64,'Animal Register'!$U:$U,0)),"") | B68: =IF($A68="","",INDEX('Animal Register'!$C:$C,MATCH($A68,'Animal Register'!$A:$A,0))) | C68: =IF($A68="","",INDEX('Animal Register'!$K:$K,MATCH($A68,'Animal Register'!$A:$A,0))) | D68: =IF($A68="","",INDEX('Animal Register'!$I:$I,MATCH($A68,'Animal Register'!$A:$A,0))) | E68: =IF($A68="","",INDEX('Animal Register'!$J:$J,MATCH($A68,'Animal Register'!$A:$A,0))) | F68: =IF($A68="","",INDEX('Animal Register'!$S:$S,MATCH($A68,'Animal Register'!$A:$A,0))) | G68: =IF($A68="","",INDEX('Animal Register'!$O:$O,MATCH($A68,'Animal Register'!$A:$A,0))) | H68: =IF($A68="","",INDEX('Animal Register'!$N:$N,MATCH($A68,'Animal Register'!$A:$A,0))) | I68: =IF($A68="","",INDEX('Animal Register'!$P:$P,MATCH($A68,'Animal Register'!$A:$A,0))) | J68: =IF($A68="","",IFERROR(INDEX($R$5:$R$104,MATCH($A68,$Q$5:$Q$104,0)),"-")) | K68: =IF($A68="","",IFERROR(INDEX($S$5:$S$104,MATCH($A68,$Q$5:$Q$104,0)),"-")) | L68: =IF($A68="","",IFERROR(INDEX($T$5:$T$104,MATCH($A68,$Q$5:$Q$104,0)),"-")) | M68: =IF($A68="","",IFERROR(INDEX($U$5:$U$104,MATCH($A68,$Q$5:$Q$104,0)),"-")) | N68: =IF($A68="","",IF(ISNUMBER(L68),L68-E68,"-"))
A69: =IFERROR(INDEX('Animal Register'!$A:$A,MATCH(65,'Animal Register'!$U:$U,0)),"") | B69: =IF($A69="","",INDEX('Animal Register'!$C:$C,MATCH($A69,'Animal Register'!$A:$A,0))) | C69: =IF($A69="","",INDEX('Animal Register'!$K:$K,MATCH($A69,'Animal Register'!$A:$A,0))) | D69: =IF($A69="","",INDEX('Animal Register'!$I:$I,MATCH($A69,'Animal Register'!$A:$A,0))) | E69: =IF($A69="","",INDEX('Animal Register'!$J:$J,MATCH($A69,'Animal Register'!$A:$A,0))) | F69: =IF($A69="","",INDEX('Animal Register'!$S:$S,MATCH($A69,'Animal Register'!$A:$A,0))) | G69: =IF($A69="","",INDEX('Animal Register'!$O:$O,MATCH($A69,'Animal Register'!$A:$A,0))) | H69: =IF($A69="","",INDEX('Animal Register'!$N:$N,MATCH($A69,'Animal Register'!$A:$A,0))) | I69: =IF($A69="","",INDEX('Animal Register'!$P:$P,MATCH($A69,'Animal Register'!$A:$A,0))) | J69: =IF($A69="","",IFERROR(INDEX($R$5:$R$104,MATCH($A69,$Q$5:$Q$104,0)),"-")) | K69: =IF($A69="","",IFERROR(INDEX($S$5:$S$104,MATCH($A69,$Q$5:$Q$104,0)),"-")) | L69: =IF($A69="","",IFERROR(INDEX($T$5:$T$104,MATCH($A69,$Q$5:$Q$104,0)),"-")) | M69: =IF($A69="","",IFERROR(INDEX($U$5:$U$104,MATCH($A69,$Q$5:$Q$104,0)),"-")) | N69: =IF($A69="","",IF(ISNUMBER(L69),L69-E69,"-"))
A70: =IFERROR(INDEX('Animal Register'!$A:$A,MATCH(66,'Animal Register'!$U:$U,0)),"") | B70: =IF($A70="","",INDEX('Animal Register'!$C:$C,MATCH($A70,'Animal Register'!$A:$A,0))) | C70: =IF($A70="","",INDEX('Animal Register'!$K:$K,MATCH($A70,'Animal Register'!$A:$A,0))) | D70: =IF($A70="","",INDEX('Animal Register'!$I:$I,MATCH($A70,'Animal Register'!$A:$A,0))) | E70: =IF($A70="","",INDEX('Animal Register'!$J:$J,MATCH($A70,'Animal Register'!$A:$A,0))) | F70: =IF($A70="","",INDEX('Animal Register'!$S:$S,MATCH($A70,'Animal Register'!$A:$A,0))) | G70: =IF($A70="","",INDEX('Animal Register'!$O:$O,MATCH($A70,'Animal Register'!$A:$A,0))) | H70: =IF($A70="","",INDEX('Animal Register'!$N:$N,MATCH($A70,'Animal Register'!$A:$A,0))) | I70: =IF($A70="","",INDEX('Animal Register'!$P:$P,MATCH($A70,'Animal Register'!$A:$A,0))) | J70: =IF($A70="","",IFERROR(INDEX($R$5:$R$104,MATCH($A70,$Q$5:$Q$104,0)),"-")) | K70: =IF($A70="","",IFERROR(INDEX($S$5:$S$104,MATCH($A70,$Q$5:$Q$104,0)),"-")) | L70: =IF($A70="","",IFERROR(INDEX($T$5:$T$104,MATCH($A70,$Q$5:$Q$104,0)),"-")) | M70: =IF($A70="","",IFERROR(INDEX($U$5:$U$104,MATCH($A70,$Q$5:$Q$104,0)),"-")) | N70: =IF($A70="","",IF(ISNUMBER(L70),L70-E70,"-"))
A71: =IFERROR(INDEX('Animal Register'!$A:$A,MATCH(67,'Animal Register'!$U:$U,0)),"") | B71: =IF($A71="","",INDEX('Animal Register'!$C:$C,MATCH($A71,'Animal Register'!$A:$A,0))) | C71: =IF($A71="","",INDEX('Animal Register'!$K:$K,MATCH($A71,'Animal Register'!$A:$A,0))) | D71: =IF($A71="","",INDEX('Animal Register'!$I:$I,MATCH($A71,'Animal Register'!$A:$A,0))) | E71: =IF($A71="","",INDEX('Animal Register'!$J:$J,MATCH($A71,'Animal Register'!$A:$A,0))) | F71: =IF($A71="","",INDEX('Animal Register'!$S:$S,MATCH($A71,'Animal Register'!$A:$A,0))) | G71: =IF($A71="","",INDEX('Animal Register'!$O:$O,MATCH($A71,'Animal Register'!$A:$A,0))) | H71: =IF($A71="","",INDEX('Animal Register'!$N:$N,MATCH($A71,'Animal Register'!$A:$A,0))) | I71: =IF($A71="","",INDEX('Animal Register'!$P:$P,MATCH($A71,'Animal Register'!$A:$A,0))) | J71: =IF($A71="","",IFERROR(INDEX($R$5:$R$104,MATCH($A71,$Q$5:$Q$104,0)),"-")) | K71: =IF($A71="","",IFERROR(INDEX($S$5:$S$104,MATCH($A71,$Q$5:$Q$104,0)),"-")) | L71: =IF($A71="","",IFERROR(INDEX($T$5:$T$104,MATCH($A71,$Q$5:$Q$104,0)),"-")) | M71: =IF($A71="","",IFERROR(INDEX($U$5:$U$104,MATCH($A71,$Q$5:$Q$104,0)),"-")) | N71: =IF($A71="","",IF(ISNUMBER(L71),L71-E71,"-"))
A72: =IFERROR(INDEX('Animal Register'!$A:$A,MATCH(68,'Animal Register'!$U:$U,0)),"") | B72: =IF($A72="","",INDEX('Animal Register'!$C:$C,MATCH($A72,'Animal Register'!$A:$A,0))) | C72: =IF($A72="","",INDEX('Animal Register'!$K:$K,MATCH($A72,'Animal Register'!$A:$A,0))) | D72: =IF($A72="","",INDEX('Animal Register'!$I:$I,MATCH($A72,'Animal Register'!$A:$A,0))) | E72: =IF($A72="","",INDEX('Animal Register'!$J:$J,MATCH($A72,'Animal Register'!$A:$A,0))) | F72: =IF($A72="","",INDEX('Animal Register'!$S:$S,MATCH($A72,'Animal Register'!$A:$A,0))) | G72: =IF($A72="","",INDEX('Animal Register'!$O:$O,MATCH($A72,'Animal Register'!$A:$A,0))) | H72: =IF($A72="","",INDEX('Animal Register'!$N:$N,MATCH($A72,'Animal Register'!$A:$A,0))) | I72: =IF($A72="","",INDEX('Animal Register'!$P:$P,MATCH($A72,'Animal Register'!$A:$A,0))) | J72: =IF($A72="","",IFERROR(INDEX($R$5:$R$104,MATCH($A72,$Q$5:$Q$104,0)),"-")) | K72: =IF($A72="","",IFERROR(INDEX($S$5:$S$104,MATCH($A72,$Q$5:$Q$104,0)),"-")) | L72: =IF($A72="","",IFERROR(INDEX($T$5:$T$104,MATCH($A72,$Q$5:$Q$104,0)),"-")) | M72: =IF($A72="","",IFERROR(INDEX($U$5:$U$104,MATCH($A72,$Q$5:$Q$104,0)),"-")) | N72: =IF($A72="","",IF(ISNUMBER(L72),L72-E72,"-"))
A73: =IFERROR(INDEX('Animal Register'!$A:$A,MATCH(69,'Animal Register'!$U:$U,0)),"") | B73: =IF($A73="","",INDEX('Animal Register'!$C:$C,MATCH($A73,'Animal Register'!$A:$A,0))) | C73: =IF($A73="","",INDEX('Animal Register'!$K:$K,MATCH($A73,'Animal Register'!$A:$A,0))) | D73: =IF($A73="","",INDEX('Animal Register'!$I:$I,MATCH($A73,'Animal Register'!$A:$A,0))) | E73: =IF($A73="","",INDEX('Animal Register'!$J:$J,MATCH($A73,'Animal Register'!$A:$A,0))) | F73: =IF($A73="","",INDEX('Animal Register'!$S:$S,MATCH($A73,'Animal Register'!$A:$A,0))) | G73: =IF($A73="","",INDEX('Animal Register'!$O:$O,MATCH($A73,'Animal Register'!$A:$A,0))) | H73: =IF($A73="","",INDEX('Animal Register'!$N:$N,MATCH($A73,'Animal Register'!$A:$A,0))) | I73: =IF($A73="","",INDEX('Animal Register'!$P:$P,MATCH($A73,'Animal Register'!$A:$A,0))) | J73: =IF($A73="","",IFERROR(INDEX($R$5:$R$104,MATCH($A73,$Q$5:$Q$104,0)),"-")) | K73: =IF($A73="","",IFERROR(INDEX($S$5:$S$104,MATCH($A73,$Q$5:$Q$104,0)),"-")) | L73: =IF($A73="","",IFERROR(INDEX($T$5:$T$104,MATCH($A73,$Q$5:$Q$104,0)),"-")) | M73: =IF($A73="","",IFERROR(INDEX($U$5:$U$104,MATCH($A73,$Q$5:$Q$104,0)),"-")) | N73: =IF($A73="","",IF(ISNUMBER(L73),L73-E73,"-"))
A74: =IFERROR(INDEX('Animal Register'!$A:$A,MATCH(70,'Animal Register'!$U:$U,0)),"") | B74: =IF($A74="","",INDEX('Animal Register'!$C:$C,MATCH($A74,'Animal Register'!$A:$A,0))) | C74: =IF($A74="","",INDEX('Animal Register'!$K:$K,MATCH($A74,'Animal Register'!$A:$A,0))) | D74: =IF($A74="","",INDEX('Animal Register'!$I:$I,MATCH($A74,'Animal Register'!$A:$A,0))) | E74: =IF($A74="","",INDEX('Animal Register'!$J:$J,MATCH($A74,'Animal Register'!$A:$A,0))) | F74: =IF($A74="","",INDEX('Animal Register'!$S:$S,MATCH($A74,'Animal Register'!$A:$A,0))) | G74: =IF($A74="","",INDEX('Animal Register'!$O:$O,MATCH($A74,'Animal Register'!$A:$A,0))) | H74: =IF($A74="","",INDEX('Animal Register'!$N:$N,MATCH($A74,'Animal Register'!$A:$A,0))) | I74: =IF($A74="","",INDEX('Animal Register'!$P:$P,MATCH($A74,'Animal Register'!$A:$A,0))) | J74: =IF($A74="","",IFERROR(INDEX($R$5:$R$104,MATCH($A74,$Q$5:$Q$104,0)),"-")) | K74: =IF($A74="","",IFERROR(INDEX($S$5:$S$104,MATCH($A74,$Q$5:$Q$104,0)),"-")) | L74: =IF($A74="","",IFERROR(INDEX($T$5:$T$104,MATCH($A74,$Q$5:$Q$104,0)),"-")) | M74: =IF($A74="","",IFERROR(INDEX($U$5:$U$104,MATCH($A74,$Q$5:$Q$104,0)),"-")) | N74: =IF($A74="","",IF(ISNUMBER(L74),L74-E74,"-"))

Sheet Dairy Module
A1: DAIRY MODULE
A2: Animal Register mein jo bhi Purpose='Dairy' likha jayega, wo yahan khud aa jayega.
A4: Animal ID | B4: Breed | C4: Source | D4: Date of Birth / Acquired | E4: Current Weight (kg) | F4: Status | G4: Avg Daily Milk Yield (L) | H4: Last Milking Date | I4: Total Milk - Lifetime (L)
A5: =IFERROR(INDEX('Animal Register'!$A:$A,MATCH(1,'Animal Register'!$V:$V,0)),"") | B5: =IF($A5="","",INDEX('Animal Register'!$C:$C,MATCH($A5,'Animal Register'!$A:$A,0))) | C5: =IF($A5="","",INDEX('Animal Register'!$E:$E,MATCH($A5,'Animal Register'!$A:$A,0))) | D5: =IF($A5="","",INDEX('Animal Register'!$F:$F,MATCH($A5,'Animal Register'!$A:$A,0))) | E5: =IF($A5="","",INDEX('Animal Register'!$S:$S,MATCH($A5,'Animal Register'!$A:$A,0))) | F5: =IF($A5="","",INDEX('Animal Register'!$Q:$Q,MATCH($A5,'Animal Register'!$A:$A,0))) | G5: =IF($A5="","",IFERROR(ROUND(AVERAGEIF('Milk Production Log'!$B:$B,$A5,'Milk Production Log'!$E:$E),1),"-")) | H5: =IF($A5="","",IF(SUMPRODUCT(MAX(('Milk Production Log'!$B$5:$B$404=$A5)*ROW('Milk Production Log'!$B$5:$B$404)))=0,"-",INDEX('Milk Production Log'!$A:$A,SUMPRODUCT(MAX(('Milk Production Log'!$B$5:$B$404=$A5)*ROW('Milk Production Log'!$B$5:$B$404)))))) | I5: =IF($A5="","",ROUND(SUMIF('Milk Production Log'!$B:$B,$A5,'Milk Production Log'!$E:$E),1))
A6: =IFERROR(INDEX('Animal Register'!$A:$A,MATCH(2,'Animal Register'!$V:$V,0)),"") | B6: =IF($A6="","",INDEX('Animal Register'!$C:$C,MATCH($A6,'Animal Register'!$A:$A,0))) | C6: =IF($A6="","",INDEX('Animal Register'!$E:$E,MATCH($A6,'Animal Register'!$A:$A,0))) | D6: =IF($A6="","",INDEX('Animal Register'!$F:$F,MATCH($A6,'Animal Register'!$A:$A,0))) | E6: =IF($A6="","",INDEX('Animal Register'!$S:$S,MATCH($A6,'Animal Register'!$A:$A,0))) | F6: =IF($A6="","",INDEX('Animal Register'!$Q:$Q,MATCH($A6,'Animal Register'!$A:$A,0))) | G6: =IF($A6="","",IFERROR(ROUND(AVERAGEIF('Milk Production Log'!$B:$B,$A6,'Milk Production Log'!$E:$E),1),"-")) | H6: =IF($A6="","",IF(SUMPRODUCT(MAX(('Milk Production Log'!$B$5:$B$404=$A6)*ROW('Milk Production Log'!$B$5:$B$404)))=0,"-",INDEX('Milk Production Log'!$A:$A,SUMPRODUCT(MAX(('Milk Production Log'!$B$5:$B$404=$A6)*ROW('Milk Production Log'!$B$5:$B$404)))))) | I6: =IF($A6="","",ROUND(SUMIF('Milk Production Log'!$B:$B,$A6,'Milk Production Log'!$E:$E),1))
A7: =IFERROR(INDEX('Animal Register'!$A:$A,MATCH(3,'Animal Register'!$V:$V,0)),"") | B7: =IF($A7="","",INDEX('Animal Register'!$C:$C,MATCH($A7,'Animal Register'!$A:$A,0))) | C7: =IF($A7="","",INDEX('Animal Register'!$E:$E,MATCH($A7,'Animal Register'!$A:$A,0))) | D7: =IF($A7="","",INDEX('Animal Register'!$F:$F,MATCH($A7,'Animal Register'!$A:$A,0))) | E7: =IF($A7="","",INDEX('Animal Register'!$S:$S,MATCH($A7,'Animal Register'!$A:$A,0))) | F7: =IF($A7="","",INDEX('Animal Register'!$Q:$Q,MATCH($A7,'Animal Register'!$A:$A,0))) | G7: =IF($A7="","",IFERROR(ROUND(AVERAGEIF('Milk Production Log'!$B:$B,$A7,'Milk Production Log'!$E:$E),1),"-")) | H7: =IF($A7="","",IF(SUMPRODUCT(MAX(('Milk Production Log'!$B$5:$B$404=$A7)*ROW('Milk Production Log'!$B$5:$B$404)))=0,"-",INDEX('Milk Production Log'!$A:$A,SUMPRODUCT(MAX(('Milk Production Log'!$B$5:$B$404=$A7)*ROW('Milk Production Log'!$B$5:$B$404)))))) | I7: =IF($A7="","",ROUND(SUMIF('Milk Production Log'!$B:$B,$A7,'Milk Production Log'!$E:$E),1))
A8: =IFERROR(INDEX('Animal Register'!$A:$A,MATCH(4,'Animal Register'!$V:$V,0)),"") | B8: =IF($A8="","",INDEX('Animal Register'!$C:$C,MATCH($A8,'Animal Register'!$A:$A,0))) | C8: =IF($A8="","",INDEX('Animal Register'!$E:$E,MATCH($A8,'Animal Register'!$A:$A,0))) | D8: =IF($A8="","",INDEX('Animal Register'!$F:$F,MATCH($A8,'Animal Register'!$A:$A,0))) | E8: =IF($A8="","",INDEX('Animal Register'!$S:$S,MATCH($A8,'Animal Register'!$A:$A,0))) | F8: =IF($A8="","",INDEX('Animal Register'!$Q:$Q,MATCH($A8,'Animal Register'!$A:$A,0))) | G8: =IF($A8="","",IFERROR(ROUND(AVERAGEIF('Milk Production Log'!$B:$B,$A8,'Milk Production Log'!$E:$E),1),"-")) | H8: =IF($A8="","",IF(SUMPRODUCT(MAX(('Milk Production Log'!$B$5:$B$404=$A8)*ROW('Milk Production Log'!$B$5:$B$404)))=0,"-",INDEX('Milk Production Log'!$A:$A,SUMPRODUCT(MAX(('Milk Production Log'!$B$5:$B$404=$A8)*ROW('Milk Production Log'!$B$5:$B$404)))))) | I8: =IF($A8="","",ROUND(SUMIF('Milk Production Log'!$B:$B,$A8,'Milk Production Log'!$E:$E),1))
A9: =IFERROR(INDEX('Animal Register'!$A:$A,MATCH(5,'Animal Register'!$V:$V,0)),"") | B9: =IF($A9="","",INDEX('Animal Register'!$C:$C,MATCH($A9,'Animal Register'!$A:$A,0))) | C9: =IF($A9="","",INDEX('Animal Register'!$E:$E,MATCH($A9,'Animal Register'!$A:$A,0))) | D9: =IF($A9="","",INDEX('Animal Register'!$F:$F,MATCH($A9,'Animal Register'!$A:$A,0))) | E9: =IF($A9="","",INDEX('Animal Register'!$S:$S,MATCH($A9,'Animal Register'!$A:$A,0))) | F9: =IF($A9="","",INDEX('Animal Register'!$Q:$Q,MATCH($A9,'Animal Register'!$A:$A,0))) | G9: =IF($A9="","",IFERROR(ROUND(AVERAGEIF('Milk Production Log'!$B:$B,$A9,'Milk Production Log'!$E:$E),1),"-")) | H9: =IF($A9="","",IF(SUMPRODUCT(MAX(('Milk Production Log'!$B$5:$B$404=$A9)*ROW('Milk Production Log'!$B$5:$B$404)))=0,"-",INDEX('Milk Production Log'!$A:$A,SUMPRODUCT(MAX(('Milk Production Log'!$B$5:$B$404=$A9)*ROW('Milk Production Log'!$B$5:$B$404)))))) | I9: =IF($A9="","",ROUND(SUMIF('Milk Production Log'!$B:$B,$A9,'Milk Production Log'!$E:$E),1))
A10: =IFERROR(INDEX('Animal Register'!$A:$A,MATCH(6,'Animal Register'!$V:$V,0)),"") | B10: =IF($A10="","",INDEX('Animal Register'!$C:$C,MATCH($A10,'Animal Register'!$A:$A,0))) | C10: =IF($A10="","",INDEX('Animal Register'!$E:$E,MATCH($A10,'Animal Register'!$A:$A,0))) | D10: =IF($A10="","",INDEX('Animal Register'!$F:$F,MATCH($A10,'Animal Register'!$A:$A,0))) | E10: =IF($A10="","",INDEX('Animal Register'!$S:$S,MATCH($A10,'Animal Register'!$A:$A,0))) | F10: =IF($A10="","",INDEX('Animal Register'!$Q:$Q,MATCH($A10,'Animal Register'!$A:$A,0))) | G10: =IF($A10="","",IFERROR(ROUND(AVERAGEIF('Milk Production Log'!$B:$B,$A10,'Milk Production Log'!$E:$E),1),"-")) | H10: =IF($A10="","",IF(SUMPRODUCT(MAX(('Milk Production Log'!$B$5:$B$404=$A10)*ROW('Milk Production Log'!$B$5:$B$404)))=0,"-",INDEX('Milk Production Log'!$A:$A,SUMPRODUCT(MAX(('Milk Production Log'!$B$5:$B$404=$A10)*ROW('Milk Production Log'!$B$5:$B$404)))))) | I10: =IF($A10="","",ROUND(SUMIF('Milk Production Log'!$B:$B,$A10,'Milk Production Log'!$E:$E),1))
A11: =IFERROR(INDEX('Animal Register'!$A:$A,MATCH(7,'Animal Register'!$V:$V,0)),"") | B11: =IF($A11="","",INDEX('Animal Register'!$C:$C,MATCH($A11,'Animal Register'!$A:$A,0))) | C11: =IF($A11="","",INDEX('Animal Register'!$E:$E,MATCH($A11,'Animal Register'!$A:$A,0))) | D11: =IF($A11="","",INDEX('Animal Register'!$F:$F,MATCH($A11,'Animal Register'!$A:$A,0))) | E11: =IF($A11="","",INDEX('Animal Register'!$S:$S,MATCH($A11,'Animal Register'!$A:$A,0))) | F11: =IF($A11="","",INDEX('Animal Register'!$Q:$Q,MATCH($A11,'Animal Register'!$A:$A,0))) | G11: =IF($A11="","",IFERROR(ROUND(AVERAGEIF('Milk Production Log'!$B:$B,$A11,'Milk Production Log'!$E:$E),1),"-")) | H11: =IF($A11="","",IF(SUMPRODUCT(MAX(('Milk Production Log'!$B$5:$B$404=$A11)*ROW('Milk Production Log'!$B$5:$B$404)))=0,"-",INDEX('Milk Production Log'!$A:$A,SUMPRODUCT(MAX(('Milk Production Log'!$B$5:$B$404=$A11)*ROW('Milk Production Log'!$B$5:$B$404)))))) | I11: =IF($A11="","",ROUND(SUMIF('Milk Production Log'!$B:$B,$A11,'Milk Production Log'!$E:$E),1))
A12: =IFERROR(INDEX('Animal Register'!$A:$A,MATCH(8,'Animal Register'!$V:$V,0)),"") | B12: =IF($A12="","",INDEX('Animal Register'!$C:$C,MATCH($A12,'Animal Register'!$A:$A,0))) | C12: =IF($A12="","",INDEX('Animal Register'!$E:$E,MATCH($A12,'Animal Register'!$A:$A,0))) | D12: =IF($A12="","",INDEX('Animal Register'!$F:$F,MATCH($A12,'Animal Register'!$A:$A,0))) | E12: =IF($A12="","",INDEX('Animal Register'!$S:$S,MATCH($A12,'Animal Register'!$A:$A,0))) | F12: =IF($A12="","",INDEX('Animal Register'!$Q:$Q,MATCH($A12,'Animal Register'!$A:$A,0))) | G12: =IF($A12="","",IFERROR(ROUND(AVERAGEIF('Milk Production Log'!$B:$B,$A12,'Milk Production Log'!$E:$E),1),"-")) | H12: =IF($A12="","",IF(SUMPRODUCT(MAX(('Milk Production Log'!$B$5:$B$404=$A12)*ROW('Milk Production Log'!$B$5:$B$404)))=0,"-",INDEX('Milk Production Log'!$A:$A,SUMPRODUCT(MAX(('Milk Production Log'!$B$5:$B$404=$A12)*ROW('Milk Production Log'!$B$5:$B$404)))))) | I12: =IF($A12="","",ROUND(SUMIF('Milk Production Log'!$B:$B,$A12,'Milk Production Log'!$E:$E),1))
A13: =IFERROR(INDEX('Animal Register'!$A:$A,MATCH(9,'Animal Register'!$V:$V,0)),"") | B13: =IF($A13="","",INDEX('Animal Register'!$C:$C,MATCH($A13,'Animal Register'!$A:$A,0))) | C13: =IF($A13="","",INDEX('Animal Register'!$E:$E,MATCH($A13,'Animal Register'!$A:$A,0))) | D13: =IF($A13="","",INDEX('Animal Register'!$F:$F,MATCH($A13,'Animal Register'!$A:$A,0))) | E13: =IF($A13="","",INDEX('Animal Register'!$S:$S,MATCH($A13,'Animal Register'!$A:$A,0))) | F13: =IF($A13="","",INDEX('Animal Register'!$Q:$Q,MATCH($A13,'Animal Register'!$A:$A,0))) | G13: =IF($A13="","",IFERROR(ROUND(AVERAGEIF('Milk Production Log'!$B:$B,$A13,'Milk Production Log'!$E:$E),1),"-")) | H13: =IF($A13="","",IF(SUMPRODUCT(MAX(('Milk Production Log'!$B$5:$B$404=$A13)*ROW('Milk Production Log'!$B$5:$B$404)))=0,"-",INDEX('Milk Production Log'!$A:$A,SUMPRODUCT(MAX(('Milk Production Log'!$B$5:$B$404=$A13)*ROW('Milk Production Log'!$B$5:$B$404)))))) | I13: =IF($A13="","",ROUND(SUMIF('Milk Production Log'!$B:$B,$A13,'Milk Production Log'!$E:$E),1))
A14: =IFERROR(INDEX('Animal Register'!$A:$A,MATCH(10,'Animal Register'!$V:$V,0)),"") | B14: =IF($A14="","",INDEX('Animal Register'!$C:$C,MATCH($A14,'Animal Register'!$A:$A,0))) | C14: =IF($A14="","",INDEX('Animal Register'!$E:$E,MATCH($A14,'Animal Register'!$A:$A,0))) | D14: =IF($A14="","",INDEX('Animal Register'!$F:$F,MATCH($A14,'Animal Register'!$A:$A,0))) | E14: =IF($A14="","",INDEX('Animal Register'!$S:$S,MATCH($A14,'Animal Register'!$A:$A,0))) | F14: =IF($A14="","",INDEX('Animal Register'!$Q:$Q,MATCH($A14,'Animal Register'!$A:$A,0))) | G14: =IF($A14="","",IFERROR(ROUND(AVERAGEIF('Milk Production Log'!$B:$B,$A14,'Milk Production Log'!$E:$E),1),"-")) | H14: =IF($A14="","",IF(SUMPRODUCT(MAX(('Milk Production Log'!$B$5:$B$404=$A14)*ROW('Milk Production Log'!$B$5:$B$404)))=0,"-",INDEX('Milk Production Log'!$A:$A,SUMPRODUCT(MAX(('Milk Production Log'!$B$5:$B$404=$A14)*ROW('Milk Production Log'!$B$5:$B$404)))))) | I14: =IF($A14="","",ROUND(SUMIF('Milk Production Log'!$B:$B,$A14,'Milk Production Log'!$E:$E),1))
A15: =IFERROR(INDEX('Animal Register'!$A:$A,MATCH(11,'Animal Register'!$V:$V,0)),"") | B15: =IF($A15="","",INDEX('Animal Register'!$C:$C,MATCH($A15,'Animal Register'!$A:$A,0))) | C15: =IF($A15="","",INDEX('Animal Register'!$E:$E,MATCH($A15,'Animal Register'!$A:$A,0))) | D15: =IF($A15="","",INDEX('Animal Register'!$F:$F,MATCH($A15,'Animal Register'!$A:$A,0))) | E15: =IF($A15="","",INDEX('Animal Register'!$S:$S,MATCH($A15,'Animal Register'!$A:$A,0))) | F15: =IF($A15="","",INDEX('Animal Register'!$Q:$Q,MATCH($A15,'Animal Register'!$A:$A,0))) | G15: =IF($A15="","",IFERROR(ROUND(AVERAGEIF('Milk Production Log'!$B:$B,$A15,'Milk Production Log'!$E:$E),1),"-")) | H15: =IF($A15="","",IF(SUMPRODUCT(MAX(('Milk Production Log'!$B$5:$B$404=$A15)*ROW('Milk Production Log'!$B$5:$B$404)))=0,"-",INDEX('Milk Production Log'!$A:$A,SUMPRODUCT(MAX(('Milk Production Log'!$B$5:$B$404=$A15)*ROW('Milk Production Log'!$B$5:$B$404)))))) | I15: =IF($A15="","",ROUND(SUMIF('Milk Production Log'!$B:$B,$A15,'Milk Production Log'!$E:$E),1))
A16: =IFERROR(INDEX('Animal Register'!$A:$A,MATCH(12,'Animal Register'!$V:$V,0)),"") | B16: =IF($A16="","",INDEX('Animal Register'!$C:$C,MATCH($A16,'Animal Register'!$A:$A,0))) | C16: =IF($A16="","",INDEX('Animal Register'!$E:$E,MATCH($A16,'Animal Register'!$A:$A,0))) | D16: =IF($A16="","",INDEX('Animal Register'!$F:$F,MATCH($A16,'Animal Register'!$A:$A,0))) | E16: =IF($A16="","",INDEX('Animal Register'!$S:$S,MATCH($A16,'Animal Register'!$A:$A,0))) | F16: =IF($A16="","",INDEX('Animal Register'!$Q:$Q,MATCH($A16,'Animal Register'!$A:$A,0))) | G16: =IF($A16="","",IFERROR(ROUND(AVERAGEIF('Milk Production Log'!$B:$B,$A16,'Milk Production Log'!$E:$E),1),"-")) | H16: =IF($A16="","",IF(SUMPRODUCT(MAX(('Milk Production Log'!$B$5:$B$404=$A16)*ROW('Milk Production Log'!$B$5:$B$404)))=0,"-",INDEX('Milk Production Log'!$A:$A,SUMPRODUCT(MAX(('Milk Production Log'!$B$5:$B$404=$A16)*ROW('Milk Production Log'!$B$5:$B$404)))))) | I16: =IF($A16="","",ROUND(SUMIF('Milk Production Log'!$B:$B,$A16,'Milk Production Log'!$E:$E),1))
A17: =IFERROR(INDEX('Animal Register'!$A:$A,MATCH(13,'Animal Register'!$V:$V,0)),"") | B17: =IF($A17="","",INDEX('Animal Register'!$C:$C,MATCH($A17,'Animal Register'!$A:$A,0))) | C17: =IF($A17="","",INDEX('Animal Register'!$E:$E,MATCH($A17,'Animal Register'!$A:$A,0))) | D17: =IF($A17="","",INDEX('Animal Register'!$F:$F,MATCH($A17,'Animal Register'!$A:$A,0))) | E17: =IF($A17="","",INDEX('Animal Register'!$S:$S,MATCH($A17,'Animal Register'!$A:$A,0))) | F17: =IF($A17="","",INDEX('Animal Register'!$Q:$Q,MATCH($A17,'Animal Register'!$A:$A,0))) | G17: =IF($A17="","",IFERROR(ROUND(AVERAGEIF('Milk Production Log'!$B:$B,$A17,'Milk Production Log'!$E:$E),1),"-")) | H17: =IF($A17="","",IF(SUMPRODUCT(MAX(('Milk Production Log'!$B$5:$B$404=$A17)*ROW('Milk Production Log'!$B$5:$B$404)))=0,"-",INDEX('Milk Production Log'!$A:$A,SUMPRODUCT(MAX(('Milk Production Log'!$B$5:$B$404=$A17)*ROW('Milk Production Log'!$B$5:$B$404)))))) | I17: =IF($A17="","",ROUND(SUMIF('Milk Production Log'!$B:$B,$A17,'Milk Production Log'!$E:$E),1))
A18: =IFERROR(INDEX('Animal Register'!$A:$A,MATCH(14,'Animal Register'!$V:$V,0)),"") | B18: =IF($A18="","",INDEX('Animal Register'!$C:$C,MATCH($A18,'Animal Register'!$A:$A,0))) | C18: =IF($A18="","",INDEX('Animal Register'!$E:$E,MATCH($A18,'Animal Register'!$A:$A,0))) | D18: =IF($A18="","",INDEX('Animal Register'!$F:$F,MATCH($A18,'Animal Register'!$A:$A,0))) | E18: =IF($A18="","",INDEX('Animal Register'!$S:$S,MATCH($A18,'Animal Register'!$A:$A,0))) | F18: =IF($A18="","",INDEX('Animal Register'!$Q:$Q,MATCH($A18,'Animal Register'!$A:$A,0))) | G18: =IF($A18="","",IFERROR(ROUND(AVERAGEIF('Milk Production Log'!$B:$B,$A18,'Milk Production Log'!$E:$E),1),"-")) | H18: =IF($A18="","",IF(SUMPRODUCT(MAX(('Milk Production Log'!$B$5:$B$404=$A18)*ROW('Milk Production Log'!$B$5:$B$404)))=0,"-",INDEX('Milk Production Log'!$A:$A,SUMPRODUCT(MAX(('Milk Production Log'!$B$5:$B$404=$A18)*ROW('Milk Production Log'!$B$5:$B$404)))))) | I18: =IF($A18="","",ROUND(SUMIF('Milk Production Log'!$B:$B,$A18,'Milk Production Log'!$E:$E),1))
A19: =IFERROR(INDEX('Animal Register'!$A:$A,MATCH(15,'Animal Register'!$V:$V,0)),"") | B19: =IF($A19="","",INDEX('Animal Register'!$C:$C,MATCH($A19,'Animal Register'!$A:$A,0))) | C19: =IF($A19="","",INDEX('Animal Register'!$E:$E,MATCH($A19,'Animal Register'!$A:$A,0))) | D19: =IF($A19="","",INDEX('Animal Register'!$F:$F,MATCH($A19,'Animal Register'!$A:$A,0))) | E19: =IF($A19="","",INDEX('Animal Register'!$S:$S,MATCH($A19,'Animal Register'!$A:$A,0))) | F19: =IF($A19="","",INDEX('Animal Register'!$Q:$Q,MATCH($A19,'Animal Register'!$A:$A,0))) | G19: =IF($A19="","",IFERROR(ROUND(AVERAGEIF('Milk Production Log'!$B:$B,$A19,'Milk Production Log'!$E:$E),1),"-")) | H19: =IF($A19="","",IF(SUMPRODUCT(MAX(('Milk Production Log'!$B$5:$B$404=$A19)*ROW('Milk Production Log'!$B$5:$B$404)))=0,"-",INDEX('Milk Production Log'!$A:$A,SUMPRODUCT(MAX(('Milk Production Log'!$B$5:$B$404=$A19)*ROW('Milk Production Log'!$B$5:$B$404)))))) | I19: =IF($A19="","",ROUND(SUMIF('Milk Production Log'!$B:$B,$A19,'Milk Production Log'!$E:$E),1))
A20: =IFERROR(INDEX('Animal Register'!$A:$A,MATCH(16,'Animal Register'!$V:$V,0)),"") | B20: =IF($A20="","",INDEX('Animal Register'!$C:$C,MATCH($A20,'Animal Register'!$A:$A,0))) | C20: =IF($A20="","",INDEX('Animal Register'!$E:$E,MATCH($A20,'Animal Register'!$A:$A,0))) | D20: =IF($A20="","",INDEX('Animal Register'!$F:$F,MATCH($A20,'Animal Register'!$A:$A,0))) | E20: =IF($A20="","",INDEX('Animal Register'!$S:$S,MATCH($A20,'Animal Register'!$A:$A,0))) | F20: =IF($A20="","",INDEX('Animal Register'!$Q:$Q,MATCH($A20,'Animal Register'!$A:$A,0))) | G20: =IF($A20="","",IFERROR(ROUND(AVERAGEIF('Milk Production Log'!$B:$B,$A20,'Milk Production Log'!$E:$E),1),"-")) | H20: =IF($A20="","",IF(SUMPRODUCT(MAX(('Milk Production Log'!$B$5:$B$404=$A20)*ROW('Milk Production Log'!$B$5:$B$404)))=0,"-",INDEX('Milk Production Log'!$A:$A,SUMPRODUCT(MAX(('Milk Production Log'!$B$5:$B$404=$A20)*ROW('Milk Production Log'!$B$5:$B$404)))))) | I20: =IF($A20="","",ROUND(SUMIF('Milk Production Log'!$B:$B,$A20,'Milk Production Log'!$E:$E),1))
A21: =IFERROR(INDEX('Animal Register'!$A:$A,MATCH(17,'Animal Register'!$V:$V,0)),"") | B21: =IF($A21="","",INDEX('Animal Register'!$C:$C,MATCH($A21,'Animal Register'!$A:$A,0))) | C21: =IF($A21="","",INDEX('Animal Register'!$E:$E,MATCH($A21,'Animal Register'!$A:$A,0))) | D21: =IF($A21="","",INDEX('Animal Register'!$F:$F,MATCH($A21,'Animal Register'!$A:$A,0))) | E21: =IF($A21="","",INDEX('Animal Register'!$S:$S,MATCH($A21,'Animal Register'!$A:$A,0))) | F21: =IF($A21="","",INDEX('Animal Register'!$Q:$Q,MATCH($A21,'Animal Register'!$A:$A,0))) | G21: =IF($A21="","",IFERROR(ROUND(AVERAGEIF('Milk Production Log'!$B:$B,$A21,'Milk Production Log'!$E:$E),1),"-")) | H21: =IF($A21="","",IF(SUMPRODUCT(MAX(('Milk Production Log'!$B$5:$B$404=$A21)*ROW('Milk Production Log'!$B$5:$B$404)))=0,"-",INDEX('Milk Production Log'!$A:$A,SUMPRODUCT(MAX(('Milk Production Log'!$B$5:$B$404=$A21)*ROW('Milk Production Log'!$B$5:$B$404)))))) | I21: =IF($A21="","",ROUND(SUMIF('Milk Production Log'!$B:$B,$A21,'Milk Production Log'!$E:$E),1))
A22: =IFERROR(INDEX('Animal Register'!$A:$A,MATCH(18,'Animal Register'!$V:$V,0)),"") | B22: =IF($A22="","",INDEX('Animal Register'!$C:$C,MATCH($A22,'Animal Register'!$A:$A,0))) | C22: =IF($A22="","",INDEX('Animal Register'!$E:$E,MATCH($A22,'Animal Register'!$A:$A,0))) | D22: =IF($A22="","",INDEX('Animal Register'!$F:$F,MATCH($A22,'Animal Register'!$A:$A,0))) | E22: =IF($A22="","",INDEX('Animal Register'!$S:$S,MATCH($A22,'Animal Register'!$A:$A,0))) | F22: =IF($A22="","",INDEX('Animal Register'!$Q:$Q,MATCH($A22,'Animal Register'!$A:$A,0))) | G22: =IF($A22="","",IFERROR(ROUND(AVERAGEIF('Milk Production Log'!$B:$B,$A22,'Milk Production Log'!$E:$E),1),"-")) | H22: =IF($A22="","",IF(SUMPRODUCT(MAX(('Milk Production Log'!$B$5:$B$404=$A22)*ROW('Milk Production Log'!$B$5:$B$404)))=0,"-",INDEX('Milk Production Log'!$A:$A,SUMPRODUCT(MAX(('Milk Production Log'!$B$5:$B$404=$A22)*ROW('Milk Production Log'!$B$5:$B$404)))))) | I22: =IF($A22="","",ROUND(SUMIF('Milk Production Log'!$B:$B,$A22,'Milk Production Log'!$E:$E),1))
A23: =IFERROR(INDEX('Animal Register'!$A:$A,MATCH(19,'Animal Register'!$V:$V,0)),"") | B23: =IF($A23="","",INDEX('Animal Register'!$C:$C,MATCH($A23,'Animal Register'!$A:$A,0))) | C23: =IF($A23="","",INDEX('Animal Register'!$E:$E,MATCH($A23,'Animal Register'!$A:$A,0))) | D23: =IF($A23="","",INDEX('Animal Register'!$F:$F,MATCH($A23,'Animal Register'!$A:$A,0))) | E23: =IF($A23="","",INDEX('Animal Register'!$S:$S,MATCH($A23,'Animal Register'!$A:$A,0))) | F23: =IF($A23="","",INDEX('Animal Register'!$Q:$Q,MATCH($A23,'Animal Register'!$A:$A,0))) | G23: =IF($A23="","",IFERROR(ROUND(AVERAGEIF('Milk Production Log'!$B:$B,$A23,'Milk Production Log'!$E:$E),1),"-")) | H23: =IF($A23="","",IF(SUMPRODUCT(MAX(('Milk Production Log'!$B$5:$B$404=$A23)*ROW('Milk Production Log'!$B$5:$B$404)))=0,"-",INDEX('Milk Production Log'!$A:$A,SUMPRODUCT(MAX(('Milk Production Log'!$B$5:$B$404=$A23)*ROW('Milk Production Log'!$B$5:$B$404)))))) | I23: =IF($A23="","",ROUND(SUMIF('Milk Production Log'!$B:$B,$A23,'Milk Production Log'!$E:$E),1))
A24: =IFERROR(INDEX('Animal Register'!$A:$A,MATCH(20,'Animal Register'!$V:$V,0)),"") | B24: =IF($A24="","",INDEX('Animal Register'!$C:$C,MATCH($A24,'Animal Register'!$A:$A,0))) | C24: =IF($A24="","",INDEX('Animal Register'!$E:$E,MATCH($A24,'Animal Register'!$A:$A,0))) | D24: =IF($A24="","",INDEX('Animal Register'!$F:$F,MATCH($A24,'Animal Register'!$A:$A,0))) | E24: =IF($A24="","",INDEX('Animal Register'!$S:$S,MATCH($A24,'Animal Register'!$A:$A,0))) | F24: =IF($A24="","",INDEX('Animal Register'!$Q:$Q,MATCH($A24,'Animal Register'!$A:$A,0))) | G24: =IF($A24="","",IFERROR(ROUND(AVERAGEIF('Milk Production Log'!$B:$B,$A24,'Milk Production Log'!$E:$E),1),"-")) | H24: =IF($A24="","",IF(SUMPRODUCT(MAX(('Milk Production Log'!$B$5:$B$404=$A24)*ROW('Milk Production Log'!$B$5:$B$404)))=0,"-",INDEX('Milk Production Log'!$A:$A,SUMPRODUCT(MAX(('Milk Production Log'!$B$5:$B$404=$A24)*ROW('Milk Production Log'!$B$5:$B$404)))))) | I24: =IF($A24="","",ROUND(SUMIF('Milk Production Log'!$B:$B,$A24,'Milk Production Log'!$E:$E),1))
A25: =IFERROR(INDEX('Animal Register'!$A:$A,MATCH(21,'Animal Register'!$V:$V,0)),"") | B25: =IF($A25="","",INDEX('Animal Register'!$C:$C,MATCH($A25,'Animal Register'!$A:$A,0))) | C25: =IF($A25="","",INDEX('Animal Register'!$E:$E,MATCH($A25,'Animal Register'!$A:$A,0))) | D25: =IF($A25="","",INDEX('Animal Register'!$F:$F,MATCH($A25,'Animal Register'!$A:$A,0))) | E25: =IF($A25="","",INDEX('Animal Register'!$S:$S,MATCH($A25,'Animal Register'!$A:$A,0))) | F25: =IF($A25="","",INDEX('Animal Register'!$Q:$Q,MATCH($A25,'Animal Register'!$A:$A,0))) | G25: =IF($A25="","",IFERROR(ROUND(AVERAGEIF('Milk Production Log'!$B:$B,$A25,'Milk Production Log'!$E:$E),1),"-")) | H25: =IF($A25="","",IF(SUMPRODUCT(MAX(('Milk Production Log'!$B$5:$B$404=$A25)*ROW('Milk Production Log'!$B$5:$B$404)))=0,"-",INDEX('Milk Production Log'!$A:$A,SUMPRODUCT(MAX(('Milk Production Log'!$B$5:$B$404=$A25)*ROW('Milk Production Log'!$B$5:$B$404)))))) | I25: =IF($A25="","",ROUND(SUMIF('Milk Production Log'!$B:$B,$A25,'Milk Production Log'!$E:$E),1))
A26: =IFERROR(INDEX('Animal Register'!$A:$A,MATCH(22,'Animal Register'!$V:$V,0)),"") | B26: =IF($A26="","",INDEX('Animal Register'!$C:$C,MATCH($A26,'Animal Register'!$A:$A,0))) | C26: =IF($A26="","",INDEX('Animal Register'!$E:$E,MATCH($A26,'Animal Register'!$A:$A,0))) | D26: =IF($A26="","",INDEX('Animal Register'!$F:$F,MATCH($A26,'Animal Register'!$A:$A,0))) | E26: =IF($A26="","",INDEX('Animal Register'!$S:$S,MATCH($A26,'Animal Register'!$A:$A,0))) | F26: =IF($A26="","",INDEX('Animal Register'!$Q:$Q,MATCH($A26,'Animal Register'!$A:$A,0))) | G26: =IF($A26="","",IFERROR(ROUND(AVERAGEIF('Milk Production Log'!$B:$B,$A26,'Milk Production Log'!$E:$E),1),"-")) | H26: =IF($A26="","",IF(SUMPRODUCT(MAX(('Milk Production Log'!$B$5:$B$404=$A26)*ROW('Milk Production Log'!$B$5:$B$404)))=0,"-",INDEX('Milk Production Log'!$A:$A,SUMPRODUCT(MAX(('Milk Production Log'!$B$5:$B$404=$A26)*ROW('Milk Production Log'!$B$5:$B$404)))))) | I26: =IF($A26="","",ROUND(SUMIF('Milk Production Log'!$B:$B,$A26,'Milk Production Log'!$E:$E),1))
A27: =IFERROR(INDEX('Animal Register'!$A:$A,MATCH(23,'Animal Register'!$V:$V,0)),"") | B27: =IF($A27="","",INDEX('Animal Register'!$C:$C,MATCH($A27,'Animal Register'!$A:$A,0))) | C27: =IF($A27="","",INDEX('Animal Register'!$E:$E,MATCH($A27,'Animal Register'!$A:$A,0))) | D27: =IF($A27="","",INDEX('Animal Register'!$F:$F,MATCH($A27,'Animal Register'!$A:$A,0))) | E27: =IF($A27="","",INDEX('Animal Register'!$S:$S,MATCH($A27,'Animal Register'!$A:$A,0))) | F27: =IF($A27="","",INDEX('Animal Register'!$Q:$Q,MATCH($A27,'Animal Register'!$A:$A,0))) | G27: =IF($A27="","",IFERROR(ROUND(AVERAGEIF('Milk Production Log'!$B:$B,$A27,'Milk Production Log'!$E:$E),1),"-")) | H27: =IF($A27="","",IF(SUMPRODUCT(MAX(('Milk Production Log'!$B$5:$B$404=$A27)*ROW('Milk Production Log'!$B$5:$B$404)))=0,"-",INDEX('Milk Production Log'!$A:$A,SUMPRODUCT(MAX(('Milk Production Log'!$B$5:$B$404=$A27)*ROW('Milk Production Log'!$B$5:$B$404)))))) | I27: =IF($A27="","",ROUND(SUMIF('Milk Production Log'!$B:$B,$A27,'Milk Production Log'!$E:$E),1))
A28: =IFERROR(INDEX('Animal Register'!$A:$A,MATCH(24,'Animal Register'!$V:$V,0)),"") | B28: =IF($A28="","",INDEX('Animal Register'!$C:$C,MATCH($A28,'Animal Register'!$A:$A,0))) | C28: =IF($A28="","",INDEX('Animal Register'!$E:$E,MATCH($A28,'Animal Register'!$A:$A,0))) | D28: =IF($A28="","",INDEX('Animal Register'!$F:$F,MATCH($A28,'Animal Register'!$A:$A,0))) | E28: =IF($A28="","",INDEX('Animal Register'!$S:$S,MATCH($A28,'Animal Register'!$A:$A,0))) | F28: =IF($A28="","",INDEX('Animal Register'!$Q:$Q,MATCH($A28,'Animal Register'!$A:$A,0))) | G28: =IF($A28="","",IFERROR(ROUND(AVERAGEIF('Milk Production Log'!$B:$B,$A28,'Milk Production Log'!$E:$E),1),"-")) | H28: =IF($A28="","",IF(SUMPRODUCT(MAX(('Milk Production Log'!$B$5:$B$404=$A28)*ROW('Milk Production Log'!$B$5:$B$404)))=0,"-",INDEX('Milk Production Log'!$A:$A,SUMPRODUCT(MAX(('Milk Production Log'!$B$5:$B$404=$A28)*ROW('Milk Production Log'!$B$5:$B$404)))))) | I28: =IF($A28="","",ROUND(SUMIF('Milk Production Log'!$B:$B,$A28,'Milk Production Log'!$E:$E),1))
A29: =IFERROR(INDEX('Animal Register'!$A:$A,MATCH(25,'Animal Register'!$V:$V,0)),"") | B29: =IF($A29="","",INDEX('Animal Register'!$C:$C,MATCH($A29,'Animal Register'!$A:$A,0))) | C29: =IF($A29="","",INDEX('Animal Register'!$E:$E,MATCH($A29,'Animal Register'!$A:$A,0))) | D29: =IF($A29="","",INDEX('Animal Register'!$F:$F,MATCH($A29,'Animal Register'!$A:$A,0))) | E29: =IF($A29="","",INDEX('Animal Register'!$S:$S,MATCH($A29,'Animal Register'!$A:$A,0))) | F29: =IF($A29="","",INDEX('Animal Register'!$Q:$Q,MATCH($A29,'Animal Register'!$A:$A,0))) | G29: =IF($A29="","",IFERROR(ROUND(AVERAGEIF('Milk Production Log'!$B:$B,$A29,'Milk Production Log'!$E:$E),1),"-")) | H29: =IF($A29="","",IF(SUMPRODUCT(MAX(('Milk Production Log'!$B$5:$B$404=$A29)*ROW('Milk Production Log'!$B$5:$B$404)))=0,"-",INDEX('Milk Production Log'!$A:$A,SUMPRODUCT(MAX(('Milk Production Log'!$B$5:$B$404=$A29)*ROW('Milk Production Log'!$B$5:$B$404)))))) | I29: =IF($A29="","",ROUND(SUMIF('Milk Production Log'!$B:$B,$A29,'Milk Production Log'!$E:$E),1))
A30: =IFERROR(INDEX('Animal Register'!$A:$A,MATCH(26,'Animal Register'!$V:$V,0)),"") | B30: =IF($A30="","",INDEX('Animal Register'!$C:$C,MATCH($A30,'Animal Register'!$A:$A,0))) | C30: =IF($A30="","",INDEX('Animal Register'!$E:$E,MATCH($A30,'Animal Register'!$A:$A,0))) | D30: =IF($A30="","",INDEX('Animal Register'!$F:$F,MATCH($A30,'Animal Register'!$A:$A,0))) | E30: =IF($A30="","",INDEX('Animal Register'!$S:$S,MATCH($A30,'Animal Register'!$A:$A,0))) | F30: =IF($A30="","",INDEX('Animal Register'!$Q:$Q,MATCH($A30,'Animal Register'!$A:$A,0))) | G30: =IF($A30="","",IFERROR(ROUND(AVERAGEIF('Milk Production Log'!$B:$B,$A30,'Milk Production Log'!$E:$E),1),"-")) | H30: =IF($A30="","",IF(SUMPRODUCT(MAX(('Milk Production Log'!$B$5:$B$404=$A30)*ROW('Milk Production Log'!$B$5:$B$404)))=0,"-",INDEX('Milk Production Log'!$A:$A,SUMPRODUCT(MAX(('Milk Production Log'!$B$5:$B$404=$A30)*ROW('Milk Production Log'!$B$5:$B$404)))))) | I30: =IF($A30="","",ROUND(SUMIF('Milk Production Log'!$B:$B,$A30,'Milk Production Log'!$E:$E),1))
A31: =IFERROR(INDEX('Animal Register'!$A:$A,MATCH(27,'Animal Register'!$V:$V,0)),"") | B31: =IF($A31="","",INDEX('Animal Register'!$C:$C,MATCH($A31,'Animal Register'!$A:$A,0))) | C31: =IF($A31="","",INDEX('Animal Register'!$E:$E,MATCH($A31,'Animal Register'!$A:$A,0))) | D31: =IF($A31="","",INDEX('Animal Register'!$F:$F,MATCH($A31,'Animal Register'!$A:$A,0))) | E31: =IF($A31="","",INDEX('Animal Register'!$S:$S,MATCH($A31,'Animal Register'!$A:$A,0))) | F31: =IF($A31="","",INDEX('Animal Register'!$Q:$Q,MATCH($A31,'Animal Register'!$A:$A,0))) | G31: =IF($A31="","",IFERROR(ROUND(AVERAGEIF('Milk Production Log'!$B:$B,$A31,'Milk Production Log'!$E:$E),1),"-")) | H31: =IF($A31="","",IF(SUMPRODUCT(MAX(('Milk Production Log'!$B$5:$B$404=$A31)*ROW('Milk Production Log'!$B$5:$B$404)))=0,"-",INDEX('Milk Production Log'!$A:$A,SUMPRODUCT(MAX(('Milk Production Log'!$B$5:$B$404=$A31)*ROW('Milk Production Log'!$B$5:$B$404)))))) | I31: =IF($A31="","",ROUND(SUMIF('Milk Production Log'!$B:$B,$A31,'Milk Production Log'!$E:$E),1))
A32: =IFERROR(INDEX('Animal Register'!$A:$A,MATCH(28,'Animal Register'!$V:$V,0)),"") | B32: =IF($A32="","",INDEX('Animal Register'!$C:$C,MATCH($A32,'Animal Register'!$A:$A,0))) | C32: =IF($A32="","",INDEX('Animal Register'!$E:$E,MATCH($A32,'Animal Register'!$A:$A,0))) | D32: =IF($A32="","",INDEX('Animal Register'!$F:$F,MATCH($A32,'Animal Register'!$A:$A,0))) | E32: =IF($A32="","",INDEX('Animal Register'!$S:$S,MATCH($A32,'Animal Register'!$A:$A,0))) | F32: =IF($A32="","",INDEX('Animal Register'!$Q:$Q,MATCH($A32,'Animal Register'!$A:$A,0))) | G32: =IF($A32="","",IFERROR(ROUND(AVERAGEIF('Milk Production Log'!$B:$B,$A32,'Milk Production Log'!$E:$E),1),"-")) | H32: =IF($A32="","",IF(SUMPRODUCT(MAX(('Milk Production Log'!$B$5:$B$404=$A32)*ROW('Milk Production Log'!$B$5:$B$404)))=0,"-",INDEX('Milk Production Log'!$A:$A,SUMPRODUCT(MAX(('Milk Production Log'!$B$5:$B$404=$A32)*ROW('Milk Production Log'!$B$5:$B$404)))))) | I32: =IF($A32="","",ROUND(SUMIF('Milk Production Log'!$B:$B,$A32,'Milk Production Log'!$E:$E),1))
A33: =IFERROR(INDEX('Animal Register'!$A:$A,MATCH(29,'Animal Register'!$V:$V,0)),"") | B33: =IF($A33="","",INDEX('Animal Register'!$C:$C,MATCH($A33,'Animal Register'!$A:$A,0))) | C33: =IF($A33="","",INDEX('Animal Register'!$E:$E,MATCH($A33,'Animal Register'!$A:$A,0))) | D33: =IF($A33="","",INDEX('Animal Register'!$F:$F,MATCH($A33,'Animal Register'!$A:$A,0))) | E33: =IF($A33="","",INDEX('Animal Register'!$S:$S,MATCH($A33,'Animal Register'!$A:$A,0))) | F33: =IF($A33="","",INDEX('Animal Register'!$Q:$Q,MATCH($A33,'Animal Register'!$A:$A,0))) | G33: =IF($A33="","",IFERROR(ROUND(AVERAGEIF('Milk Production Log'!$B:$B,$A33,'Milk Production Log'!$E:$E),1),"-")) | H33: =IF($A33="","",IF(SUMPRODUCT(MAX(('Milk Production Log'!$B$5:$B$404=$A33)*ROW('Milk Production Log'!$B$5:$B$404)))=0,"-",INDEX('Milk Production Log'!$A:$A,SUMPRODUCT(MAX(('Milk Production Log'!$B$5:$B$404=$A33)*ROW('Milk Production Log'!$B$5:$B$404)))))) | I33: =IF($A33="","",ROUND(SUMIF('Milk Production Log'!$B:$B,$A33,'Milk Production Log'!$E:$E),1))
A34: =IFERROR(INDEX('Animal Register'!$A:$A,MATCH(30,'Animal Register'!$V:$V,0)),"") | B34: =IF($A34="","",INDEX('Animal Register'!$C:$C,MATCH($A34,'Animal Register'!$A:$A,0))) | C34: =IF($A34="","",INDEX('Animal Register'!$E:$E,MATCH($A34,'Animal Register'!$A:$A,0))) | D34: =IF($A34="","",INDEX('Animal Register'!$F:$F,MATCH($A34,'Animal Register'!$A:$A,0))) | E34: =IF($A34="","",INDEX('Animal Register'!$S:$S,MATCH($A34,'Animal Register'!$A:$A,0))) | F34: =IF($A34="","",INDEX('Animal Register'!$Q:$Q,MATCH($A34,'Animal Register'!$A:$A,0))) | G34: =IF($A34="","",IFERROR(ROUND(AVERAGEIF('Milk Production Log'!$B:$B,$A34,'Milk Production Log'!$E:$E),1),"-")) | H34: =IF($A34="","",IF(SUMPRODUCT(MAX(('Milk Production Log'!$B$5:$B$404=$A34)*ROW('Milk Production Log'!$B$5:$B$404)))=0,"-",INDEX('Milk Production Log'!$A:$A,SUMPRODUCT(MAX(('Milk Production Log'!$B$5:$B$404=$A34)*ROW('Milk Production Log'!$B$5:$B$404)))))) | I34: =IF($A34="","",ROUND(SUMIF('Milk Production Log'!$B:$B,$A34,'Milk Production Log'!$E:$E),1))
A35: =IFERROR(INDEX('Animal Register'!$A:$A,MATCH(31,'Animal Register'!$V:$V,0)),"") | B35: =IF($A35="","",INDEX('Animal Register'!$C:$C,MATCH($A35,'Animal Register'!$A:$A,0))) | C35: =IF($A35="","",INDEX('Animal Register'!$E:$E,MATCH($A35,'Animal Register'!$A:$A,0))) | D35: =IF($A35="","",INDEX('Animal Register'!$F:$F,MATCH($A35,'Animal Register'!$A:$A,0))) | E35: =IF($A35="","",INDEX('Animal Register'!$S:$S,MATCH($A35,'Animal Register'!$A:$A,0))) | F35: =IF($A35="","",INDEX('Animal Register'!$Q:$Q,MATCH($A35,'Animal Register'!$A:$A,0))) | G35: =IF($A35="","",IFERROR(ROUND(AVERAGEIF('Milk Production Log'!$B:$B,$A35,'Milk Production Log'!$E:$E),1),"-")) | H35: =IF($A35="","",IF(SUMPRODUCT(MAX(('Milk Production Log'!$B$5:$B$404=$A35)*ROW('Milk Production Log'!$B$5:$B$404)))=0,"-",INDEX('Milk Production Log'!$A:$A,SUMPRODUCT(MAX(('Milk Production Log'!$B$5:$B$404=$A35)*ROW('Milk Production Log'!$B$5:$B$404)))))) | I35: =IF($A35="","",ROUND(SUMIF('Milk Production Log'!$B:$B,$A35,'Milk Production Log'!$E:$E),1))
A36: =IFERROR(INDEX('Animal Register'!$A:$A,MATCH(32,'Animal Register'!$V:$V,0)),"") | B36: =IF($A36="","",INDEX('Animal Register'!$C:$C,MATCH($A36,'Animal Register'!$A:$A,0))) | C36: =IF($A36="","",INDEX('Animal Register'!$E:$E,MATCH($A36,'Animal Register'!$A:$A,0))) | D36: =IF($A36="","",INDEX('Animal Register'!$F:$F,MATCH($A36,'Animal Register'!$A:$A,0))) | E36: =IF($A36="","",INDEX('Animal Register'!$S:$S,MATCH($A36,'Animal Register'!$A:$A,0))) | F36: =IF($A36="","",INDEX('Animal Register'!$Q:$Q,MATCH($A36,'Animal Register'!$A:$A,0))) | G36: =IF($A36="","",IFERROR(ROUND(AVERAGEIF('Milk Production Log'!$B:$B,$A36,'Milk Production Log'!$E:$E),1),"-")) | H36: =IF($A36="","",IF(SUMPRODUCT(MAX(('Milk Production Log'!$B$5:$B$404=$A36)*ROW('Milk Production Log'!$B$5:$B$404)))=0,"-",INDEX('Milk Production Log'!$A:$A,SUMPRODUCT(MAX(('Milk Production Log'!$B$5:$B$404=$A36)*ROW('Milk Production Log'!$B$5:$B$404)))))) | I36: =IF($A36="","",ROUND(SUMIF('Milk Production Log'!$B:$B,$A36,'Milk Production Log'!$E:$E),1))
A37: =IFERROR(INDEX('Animal Register'!$A:$A,MATCH(33,'Animal Register'!$V:$V,0)),"") | B37: =IF($A37="","",INDEX('Animal Register'!$C:$C,MATCH($A37,'Animal Register'!$A:$A,0))) | C37: =IF($A37="","",INDEX('Animal Register'!$E:$E,MATCH($A37,'Animal Register'!$A:$A,0))) | D37: =IF($A37="","",INDEX('Animal Register'!$F:$F,MATCH($A37,'Animal Register'!$A:$A,0))) | E37: =IF($A37="","",INDEX('Animal Register'!$S:$S,MATCH($A37,'Animal Register'!$A:$A,0))) | F37: =IF($A37="","",INDEX('Animal Register'!$Q:$Q,MATCH($A37,'Animal Register'!$A:$A,0))) | G37: =IF($A37="","",IFERROR(ROUND(AVERAGEIF('Milk Production Log'!$B:$B,$A37,'Milk Production Log'!$E:$E),1),"-")) | H37: =IF($A37="","",IF(SUMPRODUCT(MAX(('Milk Production Log'!$B$5:$B$404=$A37)*ROW('Milk Production Log'!$B$5:$B$404)))=0,"-",INDEX('Milk Production Log'!$A:$A,SUMPRODUCT(MAX(('Milk Production Log'!$B$5:$B$404=$A37)*ROW('Milk Production Log'!$B$5:$B$404)))))) | I37: =IF($A37="","",ROUND(SUMIF('Milk Production Log'!$B:$B,$A37,'Milk Production Log'!$E:$E),1))
A38: =IFERROR(INDEX('Animal Register'!$A:$A,MATCH(34,'Animal Register'!$V:$V,0)),"") | B38: =IF($A38="","",INDEX('Animal Register'!$C:$C,MATCH($A38,'Animal Register'!$A:$A,0))) | C38: =IF($A38="","",INDEX('Animal Register'!$E:$E,MATCH($A38,'Animal Register'!$A:$A,0))) | D38: =IF($A38="","",INDEX('Animal Register'!$F:$F,MATCH($A38,'Animal Register'!$A:$A,0))) | E38: =IF($A38="","",INDEX('Animal Register'!$S:$S,MATCH($A38,'Animal Register'!$A:$A,0))) | F38: =IF($A38="","",INDEX('Animal Register'!$Q:$Q,MATCH($A38,'Animal Register'!$A:$A,0))) | G38: =IF($A38="","",IFERROR(ROUND(AVERAGEIF('Milk Production Log'!$B:$B,$A38,'Milk Production Log'!$E:$E),1),"-")) | H38: =IF($A38="","",IF(SUMPRODUCT(MAX(('Milk Production Log'!$B$5:$B$404=$A38)*ROW('Milk Production Log'!$B$5:$B$404)))=0,"-",INDEX('Milk Production Log'!$A:$A,SUMPRODUCT(MAX(('Milk Production Log'!$B$5:$B$404=$A38)*ROW('Milk Production Log'!$B$5:$B$404)))))) | I38: =IF($A38="","",ROUND(SUMIF('Milk Production Log'!$B:$B,$A38,'Milk Production Log'!$E:$E),1))
A39: =IFERROR(INDEX('Animal Register'!$A:$A,MATCH(35,'Animal Register'!$V:$V,0)),"") | B39: =IF($A39="","",INDEX('Animal Register'!$C:$C,MATCH($A39,'Animal Register'!$A:$A,0))) | C39: =IF($A39="","",INDEX('Animal Register'!$E:$E,MATCH($A39,'Animal Register'!$A:$A,0))) | D39: =IF($A39="","",INDEX('Animal Register'!$F:$F,MATCH($A39,'Animal Register'!$A:$A,0))) | E39: =IF($A39="","",INDEX('Animal Register'!$S:$S,MATCH($A39,'Animal Register'!$A:$A,0))) | F39: =IF($A39="","",INDEX('Animal Register'!$Q:$Q,MATCH($A39,'Animal Register'!$A:$A,0))) | G39: =IF($A39="","",IFERROR(ROUND(AVERAGEIF('Milk Production Log'!$B:$B,$A39,'Milk Production Log'!$E:$E),1),"-")) | H39: =IF($A39="","",IF(SUMPRODUCT(MAX(('Milk Production Log'!$B$5:$B$404=$A39)*ROW('Milk Production Log'!$B$5:$B$404)))=0,"-",INDEX('Milk Production Log'!$A:$A,SUMPRODUCT(MAX(('Milk Production Log'!$B$5:$B$404=$A39)*ROW('Milk Production Log'!$B$5:$B$404)))))) | I39: =IF($A39="","",ROUND(SUMIF('Milk Production Log'!$B:$B,$A39,'Milk Production Log'!$E:$E),1))
A40: =IFERROR(INDEX('Animal Register'!$A:$A,MATCH(36,'Animal Register'!$V:$V,0)),"") | B40: =IF($A40="","",INDEX('Animal Register'!$C:$C,MATCH($A40,'Animal Register'!$A:$A,0))) | C40: =IF($A40="","",INDEX('Animal Register'!$E:$E,MATCH($A40,'Animal Register'!$A:$A,0))) | D40: =IF($A40="","",INDEX('Animal Register'!$F:$F,MATCH($A40,'Animal Register'!$A:$A,0))) | E40: =IF($A40="","",INDEX('Animal Register'!$S:$S,MATCH($A40,'Animal Register'!$A:$A,0))) | F40: =IF($A40="","",INDEX('Animal Register'!$Q:$Q,MATCH($A40,'Animal Register'!$A:$A,0))) | G40: =IF($A40="","",IFERROR(ROUND(AVERAGEIF('Milk Production Log'!$B:$B,$A40,'Milk Production Log'!$E:$E),1),"-")) | H40: =IF($A40="","",IF(SUMPRODUCT(MAX(('Milk Production Log'!$B$5:$B$404=$A40)*ROW('Milk Production Log'!$B$5:$B$404)))=0,"-",INDEX('Milk Production Log'!$A:$A,SUMPRODUCT(MAX(('Milk Production Log'!$B$5:$B$404=$A40)*ROW('Milk Production Log'!$B$5:$B$404)))))) | I40: =IF($A40="","",ROUND(SUMIF('Milk Production Log'!$B:$B,$A40,'Milk Production Log'!$E:$E),1))
A41: =IFERROR(INDEX('Animal Register'!$A:$A,MATCH(37,'Animal Register'!$V:$V,0)),"") | B41: =IF($A41="","",INDEX('Animal Register'!$C:$C,MATCH($A41,'Animal Register'!$A:$A,0))) | C41: =IF($A41="","",INDEX('Animal Register'!$E:$E,MATCH($A41,'Animal Register'!$A:$A,0))) | D41: =IF($A41="","",INDEX('Animal Register'!$F:$F,MATCH($A41,'Animal Register'!$A:$A,0))) | E41: =IF($A41="","",INDEX('Animal Register'!$S:$S,MATCH($A41,'Animal Register'!$A:$A,0))) | F41: =IF($A41="","",INDEX('Animal Register'!$Q:$Q,MATCH($A41,'Animal Register'!$A:$A,0))) | G41: =IF($A41="","",IFERROR(ROUND(AVERAGEIF('Milk Production Log'!$B:$B,$A41,'Milk Production Log'!$E:$E),1),"-")) | H41: =IF($A41="","",IF(SUMPRODUCT(MAX(('Milk Production Log'!$B$5:$B$404=$A41)*ROW('Milk Production Log'!$B$5:$B$404)))=0,"-",INDEX('Milk Production Log'!$A:$A,SUMPRODUCT(MAX(('Milk Production Log'!$B$5:$B$404=$A41)*ROW('Milk Production Log'!$B$5:$B$404)))))) | I41: =IF($A41="","",ROUND(SUMIF('Milk Production Log'!$B:$B,$A41,'Milk Production Log'!$E:$E),1))
A42: =IFERROR(INDEX('Animal Register'!$A:$A,MATCH(38,'Animal Register'!$V:$V,0)),"") | B42: =IF($A42="","",INDEX('Animal Register'!$C:$C,MATCH($A42,'Animal Register'!$A:$A,0))) | C42: =IF($A42="","",INDEX('Animal Register'!$E:$E,MATCH($A42,'Animal Register'!$A:$A,0))) | D42: =IF($A42="","",INDEX('Animal Register'!$F:$F,MATCH($A42,'Animal Register'!$A:$A,0))) | E42: =IF($A42="","",INDEX('Animal Register'!$S:$S,MATCH($A42,'Animal Register'!$A:$A,0))) | F42: =IF($A42="","",INDEX('Animal Register'!$Q:$Q,MATCH($A42,'Animal Register'!$A:$A,0))) | G42: =IF($A42="","",IFERROR(ROUND(AVERAGEIF('Milk Production Log'!$B:$B,$A42,'Milk Production Log'!$E:$E),1),"-")) | H42: =IF($A42="","",IF(SUMPRODUCT(MAX(('Milk Production Log'!$B$5:$B$404=$A42)*ROW('Milk Production Log'!$B$5:$B$404)))=0,"-",INDEX('Milk Production Log'!$A:$A,SUMPRODUCT(MAX(('Milk Production Log'!$B$5:$B$404=$A42)*ROW('Milk Production Log'!$B$5:$B$404)))))) | I42: =IF($A42="","",ROUND(SUMIF('Milk Production Log'!$B:$B,$A42,'Milk Production Log'!$E:$E),1))
A43: =IFERROR(INDEX('Animal Register'!$A:$A,MATCH(39,'Animal Register'!$V:$V,0)),"") | B43: =IF($A43="","",INDEX('Animal Register'!$C:$C,MATCH($A43,'Animal Register'!$A:$A,0))) | C43: =IF($A43="","",INDEX('Animal Register'!$E:$E,MATCH($A43,'Animal Register'!$A:$A,0))) | D43: =IF($A43="","",INDEX('Animal Register'!$F:$F,MATCH($A43,'Animal Register'!$A:$A,0))) | E43: =IF($A43="","",INDEX('Animal Register'!$S:$S,MATCH($A43,'Animal Register'!$A:$A,0))) | F43: =IF($A43="","",INDEX('Animal Register'!$Q:$Q,MATCH($A43,'Animal Register'!$A:$A,0))) | G43: =IF($A43="","",IFERROR(ROUND(AVERAGEIF('Milk Production Log'!$B:$B,$A43,'Milk Production Log'!$E:$E),1),"-")) | H43: =IF($A43="","",IF(SUMPRODUCT(MAX(('Milk Production Log'!$B$5:$B$404=$A43)*ROW('Milk Production Log'!$B$5:$B$404)))=0,"-",INDEX('Milk Production Log'!$A:$A,SUMPRODUCT(MAX(('Milk Production Log'!$B$5:$B$404=$A43)*ROW('Milk Production Log'!$B$5:$B$404)))))) | I43: =IF($A43="","",ROUND(SUMIF('Milk Production Log'!$B:$B,$A43,'Milk Production Log'!$E:$E),1))
A44: =IFERROR(INDEX('Animal Register'!$A:$A,MATCH(40,'Animal Register'!$V:$V,0)),"") | B44: =IF($A44="","",INDEX('Animal Register'!$C:$C,MATCH($A44,'Animal Register'!$A:$A,0))) | C44: =IF($A44="","",INDEX('Animal Register'!$E:$E,MATCH($A44,'Animal Register'!$A:$A,0))) | D44: =IF($A44="","",INDEX('Animal Register'!$F:$F,MATCH($A44,'Animal Register'!$A:$A,0))) | E44: =IF($A44="","",INDEX('Animal Register'!$S:$S,MATCH($A44,'Animal Register'!$A:$A,0))) | F44: =IF($A44="","",INDEX('Animal Register'!$Q:$Q,MATCH($A44,'Animal Register'!$A:$A,0))) | G44: =IF($A44="","",IFERROR(ROUND(AVERAGEIF('Milk Production Log'!$B:$B,$A44,'Milk Production Log'!$E:$E),1),"-")) | H44: =IF($A44="","",IF(SUMPRODUCT(MAX(('Milk Production Log'!$B$5:$B$404=$A44)*ROW('Milk Production Log'!$B$5:$B$404)))=0,"-",INDEX('Milk Production Log'!$A:$A,SUMPRODUCT(MAX(('Milk Production Log'!$B$5:$B$404=$A44)*ROW('Milk Production Log'!$B$5:$B$404)))))) | I44: =IF($A44="","",ROUND(SUMIF('Milk Production Log'!$B:$B,$A44,'Milk Production Log'!$E:$E),1))
A45: =IFERROR(INDEX('Animal Register'!$A:$A,MATCH(41,'Animal Register'!$V:$V,0)),"") | B45: =IF($A45="","",INDEX('Animal Register'!$C:$C,MATCH($A45,'Animal Register'!$A:$A,0))) | C45: =IF($A45="","",INDEX('Animal Register'!$E:$E,MATCH($A45,'Animal Register'!$A:$A,0))) | D45: =IF($A45="","",INDEX('Animal Register'!$F:$F,MATCH($A45,'Animal Register'!$A:$A,0))) | E45: =IF($A45="","",INDEX('Animal Register'!$S:$S,MATCH($A45,'Animal Register'!$A:$A,0))) | F45: =IF($A45="","",INDEX('Animal Register'!$Q:$Q,MATCH($A45,'Animal Register'!$A:$A,0))) | G45: =IF($A45="","",IFERROR(ROUND(AVERAGEIF('Milk Production Log'!$B:$B,$A45,'Milk Production Log'!$E:$E),1),"-")) | H45: =IF($A45="","",IF(SUMPRODUCT(MAX(('Milk Production Log'!$B$5:$B$404=$A45)*ROW('Milk Production Log'!$B$5:$B$404)))=0,"-",INDEX('Milk Production Log'!$A:$A,SUMPRODUCT(MAX(('Milk Production Log'!$B$5:$B$404=$A45)*ROW('Milk Production Log'!$B$5:$B$404)))))) | I45: =IF($A45="","",ROUND(SUMIF('Milk Production Log'!$B:$B,$A45,'Milk Production Log'!$E:$E),1))
A46: =IFERROR(INDEX('Animal Register'!$A:$A,MATCH(42,'Animal Register'!$V:$V,0)),"") | B46: =IF($A46="","",INDEX('Animal Register'!$C:$C,MATCH($A46,'Animal Register'!$A:$A,0))) | C46: =IF($A46="","",INDEX('Animal Register'!$E:$E,MATCH($A46,'Animal Register'!$A:$A,0))) | D46: =IF($A46="","",INDEX('Animal Register'!$F:$F,MATCH($A46,'Animal Register'!$A:$A,0))) | E46: =IF($A46="","",INDEX('Animal Register'!$S:$S,MATCH($A46,'Animal Register'!$A:$A,0))) | F46: =IF($A46="","",INDEX('Animal Register'!$Q:$Q,MATCH($A46,'Animal Register'!$A:$A,0))) | G46: =IF($A46="","",IFERROR(ROUND(AVERAGEIF('Milk Production Log'!$B:$B,$A46,'Milk Production Log'!$E:$E),1),"-")) | H46: =IF($A46="","",IF(SUMPRODUCT(MAX(('Milk Production Log'!$B$5:$B$404=$A46)*ROW('Milk Production Log'!$B$5:$B$404)))=0,"-",INDEX('Milk Production Log'!$A:$A,SUMPRODUCT(MAX(('Milk Production Log'!$B$5:$B$404=$A46)*ROW('Milk Production Log'!$B$5:$B$404)))))) | I46: =IF($A46="","",ROUND(SUMIF('Milk Production Log'!$B:$B,$A46,'Milk Production Log'!$E:$E),1))
A47: =IFERROR(INDEX('Animal Register'!$A:$A,MATCH(43,'Animal Register'!$V:$V,0)),"") | B47: =IF($A47="","",INDEX('Animal Register'!$C:$C,MATCH($A47,'Animal Register'!$A:$A,0))) | C47: =IF($A47="","",INDEX('Animal Register'!$E:$E,MATCH($A47,'Animal Register'!$A:$A,0))) | D47: =IF($A47="","",INDEX('Animal Register'!$F:$F,MATCH($A47,'Animal Register'!$A:$A,0))) | E47: =IF($A47="","",INDEX('Animal Register'!$S:$S,MATCH($A47,'Animal Register'!$A:$A,0))) | F47: =IF($A47="","",INDEX('Animal Register'!$Q:$Q,MATCH($A47,'Animal Register'!$A:$A,0))) | G47: =IF($A47="","",IFERROR(ROUND(AVERAGEIF('Milk Production Log'!$B:$B,$A47,'Milk Production Log'!$E:$E),1),"-")) | H47: =IF($A47="","",IF(SUMPRODUCT(MAX(('Milk Production Log'!$B$5:$B$404=$A47)*ROW('Milk Production Log'!$B$5:$B$404)))=0,"-",INDEX('Milk Production Log'!$A:$A,SUMPRODUCT(MAX(('Milk Production Log'!$B$5:$B$404=$A47)*ROW('Milk Production Log'!$B$5:$B$404)))))) | I47: =IF($A47="","",ROUND(SUMIF('Milk Production Log'!$B:$B,$A47,'Milk Production Log'!$E:$E),1))
A48: =IFERROR(INDEX('Animal Register'!$A:$A,MATCH(44,'Animal Register'!$V:$V,0)),"") | B48: =IF($A48="","",INDEX('Animal Register'!$C:$C,MATCH($A48,'Animal Register'!$A:$A,0))) | C48: =IF($A48="","",INDEX('Animal Register'!$E:$E,MATCH($A48,'Animal Register'!$A:$A,0))) | D48: =IF($A48="","",INDEX('Animal Register'!$F:$F,MATCH($A48,'Animal Register'!$A:$A,0))) | E48: =IF($A48="","",INDEX('Animal Register'!$S:$S,MATCH($A48,'Animal Register'!$A:$A,0))) | F48: =IF($A48="","",INDEX('Animal Register'!$Q:$Q,MATCH($A48,'Animal Register'!$A:$A,0))) | G48: =IF($A48="","",IFERROR(ROUND(AVERAGEIF('Milk Production Log'!$B:$B,$A48,'Milk Production Log'!$E:$E),1),"-")) | H48: =IF($A48="","",IF(SUMPRODUCT(MAX(('Milk Production Log'!$B$5:$B$404=$A48)*ROW('Milk Production Log'!$B$5:$B$404)))=0,"-",INDEX('Milk Production Log'!$A:$A,SUMPRODUCT(MAX(('Milk Production Log'!$B$5:$B$404=$A48)*ROW('Milk Production Log'!$B$5:$B$404)))))) | I48: =IF($A48="","",ROUND(SUMIF('Milk Production Log'!$B:$B,$A48,'Milk Production Log'!$E:$E),1))
A49: =IFERROR(INDEX('Animal Register'!$A:$A,MATCH(45,'Animal Register'!$V:$V,0)),"") | B49: =IF($A49="","",INDEX('Animal Register'!$C:$C,MATCH($A49,'Animal Register'!$A:$A,0))) | C49: =IF($A49="","",INDEX('Animal Register'!$E:$E,MATCH($A49,'Animal Register'!$A:$A,0))) | D49: =IF($A49="","",INDEX('Animal Register'!$F:$F,MATCH($A49,'Animal Register'!$A:$A,0))) | E49: =IF($A49="","",INDEX('Animal Register'!$S:$S,MATCH($A49,'Animal Register'!$A:$A,0))) | F49: =IF($A49="","",INDEX('Animal Register'!$Q:$Q,MATCH($A49,'Animal Register'!$A:$A,0))) | G49: =IF($A49="","",IFERROR(ROUND(AVERAGEIF('Milk Production Log'!$B:$B,$A49,'Milk Production Log'!$E:$E),1),"-")) | H49: =IF($A49="","",IF(SUMPRODUCT(MAX(('Milk Production Log'!$B$5:$B$404=$A49)*ROW('Milk Production Log'!$B$5:$B$404)))=0,"-",INDEX('Milk Production Log'!$A:$A,SUMPRODUCT(MAX(('Milk Production Log'!$B$5:$B$404=$A49)*ROW('Milk Production Log'!$B$5:$B$404)))))) | I49: =IF($A49="","",ROUND(SUMIF('Milk Production Log'!$B:$B,$A49,'Milk Production Log'!$E:$E),1))
A50: =IFERROR(INDEX('Animal Register'!$A:$A,MATCH(46,'Animal Register'!$V:$V,0)),"") | B50: =IF($A50="","",INDEX('Animal Register'!$C:$C,MATCH($A50,'Animal Register'!$A:$A,0))) | C50: =IF($A50="","",INDEX('Animal Register'!$E:$E,MATCH($A50,'Animal Register'!$A:$A,0))) | D50: =IF($A50="","",INDEX('Animal Register'!$F:$F,MATCH($A50,'Animal Register'!$A:$A,0))) | E50: =IF($A50="","",INDEX('Animal Register'!$S:$S,MATCH($A50,'Animal Register'!$A:$A,0))) | F50: =IF($A50="","",INDEX('Animal Register'!$Q:$Q,MATCH($A50,'Animal Register'!$A:$A,0))) | G50: =IF($A50="","",IFERROR(ROUND(AVERAGEIF('Milk Production Log'!$B:$B,$A50,'Milk Production Log'!$E:$E),1),"-")) | H50: =IF($A50="","",IF(SUMPRODUCT(MAX(('Milk Production Log'!$B$5:$B$404=$A50)*ROW('Milk Production Log'!$B$5:$B$404)))=0,"-",INDEX('Milk Production Log'!$A:$A,SUMPRODUCT(MAX(('Milk Production Log'!$B$5:$B$404=$A50)*ROW('Milk Production Log'!$B$5:$B$404)))))) | I50: =IF($A50="","",ROUND(SUMIF('Milk Production Log'!$B:$B,$A50,'Milk Production Log'!$E:$E),1))
A51: =IFERROR(INDEX('Animal Register'!$A:$A,MATCH(47,'Animal Register'!$V:$V,0)),"") | B51: =IF($A51="","",INDEX('Animal Register'!$C:$C,MATCH($A51,'Animal Register'!$A:$A,0))) | C51: =IF($A51="","",INDEX('Animal Register'!$E:$E,MATCH($A51,'Animal Register'!$A:$A,0))) | D51: =IF($A51="","",INDEX('Animal Register'!$F:$F,MATCH($A51,'Animal Register'!$A:$A,0))) | E51: =IF($A51="","",INDEX('Animal Register'!$S:$S,MATCH($A51,'Animal Register'!$A:$A,0))) | F51: =IF($A51="","",INDEX('Animal Register'!$Q:$Q,MATCH($A51,'Animal Register'!$A:$A,0))) | G51: =IF($A51="","",IFERROR(ROUND(AVERAGEIF('Milk Production Log'!$B:$B,$A51,'Milk Production Log'!$E:$E),1),"-")) | H51: =IF($A51="","",IF(SUMPRODUCT(MAX(('Milk Production Log'!$B$5:$B$404=$A51)*ROW('Milk Production Log'!$B$5:$B$404)))=0,"-",INDEX('Milk Production Log'!$A:$A,SUMPRODUCT(MAX(('Milk Production Log'!$B$5:$B$404=$A51)*ROW('Milk Production Log'!$B$5:$B$404)))))) | I51: =IF($A51="","",ROUND(SUMIF('Milk Production Log'!$B:$B,$A51,'Milk Production Log'!$E:$E),1))
A52: =IFERROR(INDEX('Animal Register'!$A:$A,MATCH(48,'Animal Register'!$V:$V,0)),"") | B52: =IF($A52="","",INDEX('Animal Register'!$C:$C,MATCH($A52,'Animal Register'!$A:$A,0))) | C52: =IF($A52="","",INDEX('Animal Register'!$E:$E,MATCH($A52,'Animal Register'!$A:$A,0))) | D52: =IF($A52="","",INDEX('Animal Register'!$F:$F,MATCH($A52,'Animal Register'!$A:$A,0))) | E52: =IF($A52="","",INDEX('Animal Register'!$S:$S,MATCH($A52,'Animal Register'!$A:$A,0))) | F52: =IF($A52="","",INDEX('Animal Register'!$Q:$Q,MATCH($A52,'Animal Register'!$A:$A,0))) | G52: =IF($A52="","",IFERROR(ROUND(AVERAGEIF('Milk Production Log'!$B:$B,$A52,'Milk Production Log'!$E:$E),1),"-")) | H52: =IF($A52="","",IF(SUMPRODUCT(MAX(('Milk Production Log'!$B$5:$B$404=$A52)*ROW('Milk Production Log'!$B$5:$B$404)))=0,"-",INDEX('Milk Production Log'!$A:$A,SUMPRODUCT(MAX(('Milk Production Log'!$B$5:$B$404=$A52)*ROW('Milk Production Log'!$B$5:$B$404)))))) | I52: =IF($A52="","",ROUND(SUMIF('Milk Production Log'!$B:$B,$A52,'Milk Production Log'!$E:$E),1))
A53: =IFERROR(INDEX('Animal Register'!$A:$A,MATCH(49,'Animal Register'!$V:$V,0)),"") | B53: =IF($A53="","",INDEX('Animal Register'!$C:$C,MATCH($A53,'Animal Register'!$A:$A,0))) | C53: =IF($A53="","",INDEX('Animal Register'!$E:$E,MATCH($A53,'Animal Register'!$A:$A,0))) | D53: =IF($A53="","",INDEX('Animal Register'!$F:$F,MATCH($A53,'Animal Register'!$A:$A,0))) | E53: =IF($A53="","",INDEX('Animal Register'!$S:$S,MATCH($A53,'Animal Register'!$A:$A,0))) | F53: =IF($A53="","",INDEX('Animal Register'!$Q:$Q,MATCH($A53,'Animal Register'!$A:$A,0))) | G53: =IF($A53="","",IFERROR(ROUND(AVERAGEIF('Milk Production Log'!$B:$B,$A53,'Milk Production Log'!$E:$E),1),"-")) | H53: =IF($A53="","",IF(SUMPRODUCT(MAX(('Milk Production Log'!$B$5:$B$404=$A53)*ROW('Milk Production Log'!$B$5:$B$404)))=0,"-",INDEX('Milk Production Log'!$A:$A,SUMPRODUCT(MAX(('Milk Production Log'!$B$5:$B$404=$A53)*ROW('Milk Production Log'!$B$5:$B$404)))))) | I53: =IF($A53="","",ROUND(SUMIF('Milk Production Log'!$B:$B,$A53,'Milk Production Log'!$E:$E),1))
A54: =IFERROR(INDEX('Animal Register'!$A:$A,MATCH(50,'Animal Register'!$V:$V,0)),"") | B54: =IF($A54="","",INDEX('Animal Register'!$C:$C,MATCH($A54,'Animal Register'!$A:$A,0))) | C54: =IF($A54="","",INDEX('Animal Register'!$E:$E,MATCH($A54,'Animal Register'!$A:$A,0))) | D54: =IF($A54="","",INDEX('Animal Register'!$F:$F,MATCH($A54,'Animal Register'!$A:$A,0))) | E54: =IF($A54="","",INDEX('Animal Register'!$S:$S,MATCH($A54,'Animal Register'!$A:$A,0))) | F54: =IF($A54="","",INDEX('Animal Register'!$Q:$Q,MATCH($A54,'Animal Register'!$A:$A,0))) | G54: =IF($A54="","",IFERROR(ROUND(AVERAGEIF('Milk Production Log'!$B:$B,$A54,'Milk Production Log'!$E:$E),1),"-")) | H54: =IF($A54="","",IF(SUMPRODUCT(MAX(('Milk Production Log'!$B$5:$B$404=$A54)*ROW('Milk Production Log'!$B$5:$B$404)))=0,"-",INDEX('Milk Production Log'!$A:$A,SUMPRODUCT(MAX(('Milk Production Log'!$B$5:$B$404=$A54)*ROW('Milk Production Log'!$B$5:$B$404)))))) | I54: =IF($A54="","",ROUND(SUMIF('Milk Production Log'!$B:$B,$A54,'Milk Production Log'!$E:$E),1))
A55: =IFERROR(INDEX('Animal Register'!$A:$A,MATCH(51,'Animal Register'!$V:$V,0)),"") | B55: =IF($A55="","",INDEX('Animal Register'!$C:$C,MATCH($A55,'Animal Register'!$A:$A,0))) | C55: =IF($A55="","",INDEX('Animal Register'!$E:$E,MATCH($A55,'Animal Register'!$A:$A,0))) | D55: =IF($A55="","",INDEX('Animal Register'!$F:$F,MATCH($A55,'Animal Register'!$A:$A,0))) | E55: =IF($A55="","",INDEX('Animal Register'!$S:$S,MATCH($A55,'Animal Register'!$A:$A,0))) | F55: =IF($A55="","",INDEX('Animal Register'!$Q:$Q,MATCH($A55,'Animal Register'!$A:$A,0))) | G55: =IF($A55="","",IFERROR(ROUND(AVERAGEIF('Milk Production Log'!$B:$B,$A55,'Milk Production Log'!$E:$E),1),"-")) | H55: =IF($A55="","",IF(SUMPRODUCT(MAX(('Milk Production Log'!$B$5:$B$404=$A55)*ROW('Milk Production Log'!$B$5:$B$404)))=0,"-",INDEX('Milk Production Log'!$A:$A,SUMPRODUCT(MAX(('Milk Production Log'!$B$5:$B$404=$A55)*ROW('Milk Production Log'!$B$5:$B$404)))))) | I55: =IF($A55="","",ROUND(SUMIF('Milk Production Log'!$B:$B,$A55,'Milk Production Log'!$E:$E),1))
A56: =IFERROR(INDEX('Animal Register'!$A:$A,MATCH(52,'Animal Register'!$V:$V,0)),"") | B56: =IF($A56="","",INDEX('Animal Register'!$C:$C,MATCH($A56,'Animal Register'!$A:$A,0))) | C56: =IF($A56="","",INDEX('Animal Register'!$E:$E,MATCH($A56,'Animal Register'!$A:$A,0))) | D56: =IF($A56="","",INDEX('Animal Register'!$F:$F,MATCH($A56,'Animal Register'!$A:$A,0))) | E56: =IF($A56="","",INDEX('Animal Register'!$S:$S,MATCH($A56,'Animal Register'!$A:$A,0))) | F56: =IF($A56="","",INDEX('Animal Register'!$Q:$Q,MATCH($A56,'Animal Register'!$A:$A,0))) | G56: =IF($A56="","",IFERROR(ROUND(AVERAGEIF('Milk Production Log'!$B:$B,$A56,'Milk Production Log'!$E:$E),1),"-")) | H56: =IF($A56="","",IF(SUMPRODUCT(MAX(('Milk Production Log'!$B$5:$B$404=$A56)*ROW('Milk Production Log'!$B$5:$B$404)))=0,"-",INDEX('Milk Production Log'!$A:$A,SUMPRODUCT(MAX(('Milk Production Log'!$B$5:$B$404=$A56)*ROW('Milk Production Log'!$B$5:$B$404)))))) | I56: =IF($A56="","",ROUND(SUMIF('Milk Production Log'!$B:$B,$A56,'Milk Production Log'!$E:$E),1))
A57: =IFERROR(INDEX('Animal Register'!$A:$A,MATCH(53,'Animal Register'!$V:$V,0)),"") | B57: =IF($A57="","",INDEX('Animal Register'!$C:$C,MATCH($A57,'Animal Register'!$A:$A,0))) | C57: =IF($A57="","",INDEX('Animal Register'!$E:$E,MATCH($A57,'Animal Register'!$A:$A,0))) | D57: =IF($A57="","",INDEX('Animal Register'!$F:$F,MATCH($A57,'Animal Register'!$A:$A,0))) | E57: =IF($A57="","",INDEX('Animal Register'!$S:$S,MATCH($A57,'Animal Register'!$A:$A,0))) | F57: =IF($A57="","",INDEX('Animal Register'!$Q:$Q,MATCH($A57,'Animal Register'!$A:$A,0))) | G57: =IF($A57="","",IFERROR(ROUND(AVERAGEIF('Milk Production Log'!$B:$B,$A57,'Milk Production Log'!$E:$E),1),"-")) | H57: =IF($A57="","",IF(SUMPRODUCT(MAX(('Milk Production Log'!$B$5:$B$404=$A57)*ROW('Milk Production Log'!$B$5:$B$404)))=0,"-",INDEX('Milk Production Log'!$A:$A,SUMPRODUCT(MAX(('Milk Production Log'!$B$5:$B$404=$A57)*ROW('Milk Production Log'!$B$5:$B$404)))))) | I57: =IF($A57="","",ROUND(SUMIF('Milk Production Log'!$B:$B,$A57,'Milk Production Log'!$E:$E),1))
A58: =IFERROR(INDEX('Animal Register'!$A:$A,MATCH(54,'Animal Register'!$V:$V,0)),"") | B58: =IF($A58="","",INDEX('Animal Register'!$C:$C,MATCH($A58,'Animal Register'!$A:$A,0))) | C58: =IF($A58="","",INDEX('Animal Register'!$E:$E,MATCH($A58,'Animal Register'!$A:$A,0))) | D58: =IF($A58="","",INDEX('Animal Register'!$F:$F,MATCH($A58,'Animal Register'!$A:$A,0))) | E58: =IF($A58="","",INDEX('Animal Register'!$S:$S,MATCH($A58,'Animal Register'!$A:$A,0))) | F58: =IF($A58="","",INDEX('Animal Register'!$Q:$Q,MATCH($A58,'Animal Register'!$A:$A,0))) | G58: =IF($A58="","",IFERROR(ROUND(AVERAGEIF('Milk Production Log'!$B:$B,$A58,'Milk Production Log'!$E:$E),1),"-")) | H58: =IF($A58="","",IF(SUMPRODUCT(MAX(('Milk Production Log'!$B$5:$B$404=$A58)*ROW('Milk Production Log'!$B$5:$B$404)))=0,"-",INDEX('Milk Production Log'!$A:$A,SUMPRODUCT(MAX(('Milk Production Log'!$B$5:$B$404=$A58)*ROW('Milk Production Log'!$B$5:$B$404)))))) | I58: =IF($A58="","",ROUND(SUMIF('Milk Production Log'!$B:$B,$A58,'Milk Production Log'!$E:$E),1))
A59: =IFERROR(INDEX('Animal Register'!$A:$A,MATCH(55,'Animal Register'!$V:$V,0)),"") | B59: =IF($A59="","",INDEX('Animal Register'!$C:$C,MATCH($A59,'Animal Register'!$A:$A,0))) | C59: =IF($A59="","",INDEX('Animal Register'!$E:$E,MATCH($A59,'Animal Register'!$A:$A,0))) | D59: =IF($A59="","",INDEX('Animal Register'!$F:$F,MATCH($A59,'Animal Register'!$A:$A,0))) | E59: =IF($A59="","",INDEX('Animal Register'!$S:$S,MATCH($A59,'Animal Register'!$A:$A,0))) | F59: =IF($A59="","",INDEX('Animal Register'!$Q:$Q,MATCH($A59,'Animal Register'!$A:$A,0))) | G59: =IF($A59="","",IFERROR(ROUND(AVERAGEIF('Milk Production Log'!$B:$B,$A59,'Milk Production Log'!$E:$E),1),"-")) | H59: =IF($A59="","",IF(SUMPRODUCT(MAX(('Milk Production Log'!$B$5:$B$404=$A59)*ROW('Milk Production Log'!$B$5:$B$404)))=0,"-",INDEX('Milk Production Log'!$A:$A,SUMPRODUCT(MAX(('Milk Production Log'!$B$5:$B$404=$A59)*ROW('Milk Production Log'!$B$5:$B$404)))))) | I59: =IF($A59="","",ROUND(SUMIF('Milk Production Log'!$B:$B,$A59,'Milk Production Log'!$E:$E),1))
A60: =IFERROR(INDEX('Animal Register'!$A:$A,MATCH(56,'Animal Register'!$V:$V,0)),"") | B60: =IF($A60="","",INDEX('Animal Register'!$C:$C,MATCH($A60,'Animal Register'!$A:$A,0))) | C60: =IF($A60="","",INDEX('Animal Register'!$E:$E,MATCH($A60,'Animal Register'!$A:$A,0))) | D60: =IF($A60="","",INDEX('Animal Register'!$F:$F,MATCH($A60,'Animal Register'!$A:$A,0))) | E60: =IF($A60="","",INDEX('Animal Register'!$S:$S,MATCH($A60,'Animal Register'!$A:$A,0))) | F60: =IF($A60="","",INDEX('Animal Register'!$Q:$Q,MATCH($A60,'Animal Register'!$A:$A,0))) | G60: =IF($A60="","",IFERROR(ROUND(AVERAGEIF('Milk Production Log'!$B:$B,$A60,'Milk Production Log'!$E:$E),1),"-")) | H60: =IF($A60="","",IF(SUMPRODUCT(MAX(('Milk Production Log'!$B$5:$B$404=$A60)*ROW('Milk Production Log'!$B$5:$B$404)))=0,"-",INDEX('Milk Production Log'!$A:$A,SUMPRODUCT(MAX(('Milk Production Log'!$B$5:$B$404=$A60)*ROW('Milk Production Log'!$B$5:$B$404)))))) | I60: =IF($A60="","",ROUND(SUMIF('Milk Production Log'!$B:$B,$A60,'Milk Production Log'!$E:$E),1))
A61: =IFERROR(INDEX('Animal Register'!$A:$A,MATCH(57,'Animal Register'!$V:$V,0)),"") | B61: =IF($A61="","",INDEX('Animal Register'!$C:$C,MATCH($A61,'Animal Register'!$A:$A,0))) | C61: =IF($A61="","",INDEX('Animal Register'!$E:$E,MATCH($A61,'Animal Register'!$A:$A,0))) | D61: =IF($A61="","",INDEX('Animal Register'!$F:$F,MATCH($A61,'Animal Register'!$A:$A,0))) | E61: =IF($A61="","",INDEX('Animal Register'!$S:$S,MATCH($A61,'Animal Register'!$A:$A,0))) | F61: =IF($A61="","",INDEX('Animal Register'!$Q:$Q,MATCH($A61,'Animal Register'!$A:$A,0))) | G61: =IF($A61="","",IFERROR(ROUND(AVERAGEIF('Milk Production Log'!$B:$B,$A61,'Milk Production Log'!$E:$E),1),"-")) | H61: =IF($A61="","",IF(SUMPRODUCT(MAX(('Milk Production Log'!$B$5:$B$404=$A61)*ROW('Milk Production Log'!$B$5:$B$404)))=0,"-",INDEX('Milk Production Log'!$A:$A,SUMPRODUCT(MAX(('Milk Production Log'!$B$5:$B$404=$A61)*ROW('Milk Production Log'!$B$5:$B$404)))))) | I61: =IF($A61="","",ROUND(SUMIF('Milk Production Log'!$B:$B,$A61,'Milk Production Log'!$E:$E),1))
A62: =IFERROR(INDEX('Animal Register'!$A:$A,MATCH(58,'Animal Register'!$V:$V,0)),"") | B62: =IF($A62="","",INDEX('Animal Register'!$C:$C,MATCH($A62,'Animal Register'!$A:$A,0))) | C62: =IF($A62="","",INDEX('Animal Register'!$E:$E,MATCH($A62,'Animal Register'!$A:$A,0))) | D62: =IF($A62="","",INDEX('Animal Register'!$F:$F,MATCH($A62,'Animal Register'!$A:$A,0))) | E62: =IF($A62="","",INDEX('Animal Register'!$S:$S,MATCH($A62,'Animal Register'!$A:$A,0))) | F62: =IF($A62="","",INDEX('Animal Register'!$Q:$Q,MATCH($A62,'Animal Register'!$A:$A,0))) | G62: =IF($A62="","",IFERROR(ROUND(AVERAGEIF('Milk Production Log'!$B:$B,$A62,'Milk Production Log'!$E:$E),1),"-")) | H62: =IF($A62="","",IF(SUMPRODUCT(MAX(('Milk Production Log'!$B$5:$B$404=$A62)*ROW('Milk Production Log'!$B$5:$B$404)))=0,"-",INDEX('Milk Production Log'!$A:$A,SUMPRODUCT(MAX(('Milk Production Log'!$B$5:$B$404=$A62)*ROW('Milk Production Log'!$B$5:$B$404)))))) | I62: =IF($A62="","",ROUND(SUMIF('Milk Production Log'!$B:$B,$A62,'Milk Production Log'!$E:$E),1))
A63: =IFERROR(INDEX('Animal Register'!$A:$A,MATCH(59,'Animal Register'!$V:$V,0)),"") | B63: =IF($A63="","",INDEX('Animal Register'!$C:$C,MATCH($A63,'Animal Register'!$A:$A,0))) | C63: =IF($A63="","",INDEX('Animal Register'!$E:$E,MATCH($A63,'Animal Register'!$A:$A,0))) | D63: =IF($A63="","",INDEX('Animal Register'!$F:$F,MATCH($A63,'Animal Register'!$A:$A,0))) | E63: =IF($A63="","",INDEX('Animal Register'!$S:$S,MATCH($A63,'Animal Register'!$A:$A,0))) | F63: =IF($A63="","",INDEX('Animal Register'!$Q:$Q,MATCH($A63,'Animal Register'!$A:$A,0))) | G63: =IF($A63="","",IFERROR(ROUND(AVERAGEIF('Milk Production Log'!$B:$B,$A63,'Milk Production Log'!$E:$E),1),"-")) | H63: =IF($A63="","",IF(SUMPRODUCT(MAX(('Milk Production Log'!$B$5:$B$404=$A63)*ROW('Milk Production Log'!$B$5:$B$404)))=0,"-",INDEX('Milk Production Log'!$A:$A,SUMPRODUCT(MAX(('Milk Production Log'!$B$5:$B$404=$A63)*ROW('Milk Production Log'!$B$5:$B$404)))))) | I63: =IF($A63="","",ROUND(SUMIF('Milk Production Log'!$B:$B,$A63,'Milk Production Log'!$E:$E),1))
A64: =IFERROR(INDEX('Animal Register'!$A:$A,MATCH(60,'Animal Register'!$V:$V,0)),"") | B64: =IF($A64="","",INDEX('Animal Register'!$C:$C,MATCH($A64,'Animal Register'!$A:$A,0))) | C64: =IF($A64="","",INDEX('Animal Register'!$E:$E,MATCH($A64,'Animal Register'!$A:$A,0))) | D64: =IF($A64="","",INDEX('Animal Register'!$F:$F,MATCH($A64,'Animal Register'!$A:$A,0))) | E64: =IF($A64="","",INDEX('Animal Register'!$S:$S,MATCH($A64,'Animal Register'!$A:$A,0))) | F64: =IF($A64="","",INDEX('Animal Register'!$Q:$Q,MATCH($A64,'Animal Register'!$A:$A,0))) | G64: =IF($A64="","",IFERROR(ROUND(AVERAGEIF('Milk Production Log'!$B:$B,$A64,'Milk Production Log'!$E:$E),1),"-")) | H64: =IF($A64="","",IF(SUMPRODUCT(MAX(('Milk Production Log'!$B$5:$B$404=$A64)*ROW('Milk Production Log'!$B$5:$B$404)))=0,"-",INDEX('Milk Production Log'!$A:$A,SUMPRODUCT(MAX(('Milk Production Log'!$B$5:$B$404=$A64)*ROW('Milk Production Log'!$B$5:$B$404)))))) | I64: =IF($A64="","",ROUND(SUMIF('Milk Production Log'!$B:$B,$A64,'Milk Production Log'!$E:$E),1))
A65: =IFERROR(INDEX('Animal Register'!$A:$A,MATCH(61,'Animal Register'!$V:$V,0)),"") | B65: =IF($A65="","",INDEX('Animal Register'!$C:$C,MATCH($A65,'Animal Register'!$A:$A,0))) | C65: =IF($A65="","",INDEX('Animal Register'!$E:$E,MATCH($A65,'Animal Register'!$A:$A,0))) | D65: =IF($A65="","",INDEX('Animal Register'!$F:$F,MATCH($A65,'Animal Register'!$A:$A,0))) | E65: =IF($A65="","",INDEX('Animal Register'!$S:$S,MATCH($A65,'Animal Register'!$A:$A,0))) | F65: =IF($A65="","",INDEX('Animal Register'!$Q:$Q,MATCH($A65,'Animal Register'!$A:$A,0))) | G65: =IF($A65="","",IFERROR(ROUND(AVERAGEIF('Milk Production Log'!$B:$B,$A65,'Milk Production Log'!$E:$E),1),"-")) | H65: =IF($A65="","",IF(SUMPRODUCT(MAX(('Milk Production Log'!$B$5:$B$404=$A65)*ROW('Milk Production Log'!$B$5:$B$404)))=0,"-",INDEX('Milk Production Log'!$A:$A,SUMPRODUCT(MAX(('Milk Production Log'!$B$5:$B$404=$A65)*ROW('Milk Production Log'!$B$5:$B$404)))))) | I65: =IF($A65="","",ROUND(SUMIF('Milk Production Log'!$B:$B,$A65,'Milk Production Log'!$E:$E),1))
A66: =IFERROR(INDEX('Animal Register'!$A:$A,MATCH(62,'Animal Register'!$V:$V,0)),"") | B66: =IF($A66="","",INDEX('Animal Register'!$C:$C,MATCH($A66,'Animal Register'!$A:$A,0))) | C66: =IF($A66="","",INDEX('Animal Register'!$E:$E,MATCH($A66,'Animal Register'!$A:$A,0))) | D66: =IF($A66="","",INDEX('Animal Register'!$F:$F,MATCH($A66,'Animal Register'!$A:$A,0))) | E66: =IF($A66="","",INDEX('Animal Register'!$S:$S,MATCH($A66,'Animal Register'!$A:$A,0))) | F66: =IF($A66="","",INDEX('Animal Register'!$Q:$Q,MATCH($A66,'Animal Register'!$A:$A,0))) | G66: =IF($A66="","",IFERROR(ROUND(AVERAGEIF('Milk Production Log'!$B:$B,$A66,'Milk Production Log'!$E:$E),1),"-")) | H66: =IF($A66="","",IF(SUMPRODUCT(MAX(('Milk Production Log'!$B$5:$B$404=$A66)*ROW('Milk Production Log'!$B$5:$B$404)))=0,"-",INDEX('Milk Production Log'!$A:$A,SUMPRODUCT(MAX(('Milk Production Log'!$B$5:$B$404=$A66)*ROW('Milk Production Log'!$B$5:$B$404)))))) | I66: =IF($A66="","",ROUND(SUMIF('Milk Production Log'!$B:$B,$A66,'Milk Production Log'!$E:$E),1))
A67: =IFERROR(INDEX('Animal Register'!$A:$A,MATCH(63,'Animal Register'!$V:$V,0)),"") | B67: =IF($A67="","",INDEX('Animal Register'!$C:$C,MATCH($A67,'Animal Register'!$A:$A,0))) | C67: =IF($A67="","",INDEX('Animal Register'!$E:$E,MATCH($A67,'Animal Register'!$A:$A,0))) | D67: =IF($A67="","",INDEX('Animal Register'!$F:$F,MATCH($A67,'Animal Register'!$A:$A,0))) | E67: =IF($A67="","",INDEX('Animal Register'!$S:$S,MATCH($A67,'Animal Register'!$A:$A,0))) | F67: =IF($A67="","",INDEX('Animal Register'!$Q:$Q,MATCH($A67,'Animal Register'!$A:$A,0))) | G67: =IF($A67="","",IFERROR(ROUND(AVERAGEIF('Milk Production Log'!$B:$B,$A67,'Milk Production Log'!$E:$E),1),"-")) | H67: =IF($A67="","",IF(SUMPRODUCT(MAX(('Milk Production Log'!$B$5:$B$404=$A67)*ROW('Milk Production Log'!$B$5:$B$404)))=0,"-",INDEX('Milk Production Log'!$A:$A,SUMPRODUCT(MAX(('Milk Production Log'!$B$5:$B$404=$A67)*ROW('Milk Production Log'!$B$5:$B$404)))))) | I67: =IF($A67="","",ROUND(SUMIF('Milk Production Log'!$B:$B,$A67,'Milk Production Log'!$E:$E),1))
A68: =IFERROR(INDEX('Animal Register'!$A:$A,MATCH(64,'Animal Register'!$V:$V,0)),"") | B68: =IF($A68="","",INDEX('Animal Register'!$C:$C,MATCH($A68,'Animal Register'!$A:$A,0))) | C68: =IF($A68="","",INDEX('Animal Register'!$E:$E,MATCH($A68,'Animal Register'!$A:$A,0))) | D68: =IF($A68="","",INDEX('Animal Register'!$F:$F,MATCH($A68,'Animal Register'!$A:$A,0))) | E68: =IF($A68="","",INDEX('Animal Register'!$S:$S,MATCH($A68,'Animal Register'!$A:$A,0))) | F68: =IF($A68="","",INDEX('Animal Register'!$Q:$Q,MATCH($A68,'Animal Register'!$A:$A,0))) | G68: =IF($A68="","",IFERROR(ROUND(AVERAGEIF('Milk Production Log'!$B:$B,$A68,'Milk Production Log'!$E:$E),1),"-")) | H68: =IF($A68="","",IF(SUMPRODUCT(MAX(('Milk Production Log'!$B$5:$B$404=$A68)*ROW('Milk Production Log'!$B$5:$B$404)))=0,"-",INDEX('Milk Production Log'!$A:$A,SUMPRODUCT(MAX(('Milk Production Log'!$B$5:$B$404=$A68)*ROW('Milk Production Log'!$B$5:$B$404)))))) | I68: =IF($A68="","",ROUND(SUMIF('Milk Production Log'!$B:$B,$A68,'Milk Production Log'!$E:$E),1))
A69: =IFERROR(INDEX('Animal Register'!$A:$A,MATCH(65,'Animal Register'!$V:$V,0)),"") | B69: =IF($A69="","",INDEX('Animal Register'!$C:$C,MATCH($A69,'Animal Register'!$A:$A,0))) | C69: =IF($A69="","",INDEX('Animal Register'!$E:$E,MATCH($A69,'Animal Register'!$A:$A,0))) | D69: =IF($A69="","",INDEX('Animal Register'!$F:$F,MATCH($A69,'Animal Register'!$A:$A,0))) | E69: =IF($A69="","",INDEX('Animal Register'!$S:$S,MATCH($A69,'Animal Register'!$A:$A,0))) | F69: =IF($A69="","",INDEX('Animal Register'!$Q:$Q,MATCH($A69,'Animal Register'!$A:$A,0))) | G69: =IF($A69="","",IFERROR(ROUND(AVERAGEIF('Milk Production Log'!$B:$B,$A69,'Milk Production Log'!$E:$E),1),"-")) | H69: =IF($A69="","",IF(SUMPRODUCT(MAX(('Milk Production Log'!$B$5:$B$404=$A69)*ROW('Milk Production Log'!$B$5:$B$404)))=0,"-",INDEX('Milk Production Log'!$A:$A,SUMPRODUCT(MAX(('Milk Production Log'!$B$5:$B$404=$A69)*ROW('Milk Production Log'!$B$5:$B$404)))))) | I69: =IF($A69="","",ROUND(SUMIF('Milk Production Log'!$B:$B,$A69,'Milk Production Log'!$E:$E),1))
A70: =IFERROR(INDEX('Animal Register'!$A:$A,MATCH(66,'Animal Register'!$V:$V,0)),"") | B70: =IF($A70="","",INDEX('Animal Register'!$C:$C,MATCH($A70,'Animal Register'!$A:$A,0))) | C70: =IF($A70="","",INDEX('Animal Register'!$E:$E,MATCH($A70,'Animal Register'!$A:$A,0))) | D70: =IF($A70="","",INDEX('Animal Register'!$F:$F,MATCH($A70,'Animal Register'!$A:$A,0))) | E70: =IF($A70="","",INDEX('Animal Register'!$S:$S,MATCH($A70,'Animal Register'!$A:$A,0))) | F70: =IF($A70="","",INDEX('Animal Register'!$Q:$Q,MATCH($A70,'Animal Register'!$A:$A,0))) | G70: =IF($A70="","",IFERROR(ROUND(AVERAGEIF('Milk Production Log'!$B:$B,$A70,'Milk Production Log'!$E:$E),1),"-")) | H70: =IF($A70="","",IF(SUMPRODUCT(MAX(('Milk Production Log'!$B$5:$B$404=$A70)*ROW('Milk Production Log'!$B$5:$B$404)))=0,"-",INDEX('Milk Production Log'!$A:$A,SUMPRODUCT(MAX(('Milk Production Log'!$B$5:$B$404=$A70)*ROW('Milk Production Log'!$B$5:$B$404)))))) | I70: =IF($A70="","",ROUND(SUMIF('Milk Production Log'!$B:$B,$A70,'Milk Production Log'!$E:$E),1))
A71: =IFERROR(INDEX('Animal Register'!$A:$A,MATCH(67,'Animal Register'!$V:$V,0)),"") | B71: =IF($A71="","",INDEX('Animal Register'!$C:$C,MATCH($A71,'Animal Register'!$A:$A,0))) | C71: =IF($A71="","",INDEX('Animal Register'!$E:$E,MATCH($A71,'Animal Register'!$A:$A,0))) | D71: =IF($A71="","",INDEX('Animal Register'!$F:$F,MATCH($A71,'Animal Register'!$A:$A,0))) | E71: =IF($A71="","",INDEX('Animal Register'!$S:$S,MATCH($A71,'Animal Register'!$A:$A,0))) | F71: =IF($A71="","",INDEX('Animal Register'!$Q:$Q,MATCH($A71,'Animal Register'!$A:$A,0))) | G71: =IF($A71="","",IFERROR(ROUND(AVERAGEIF('Milk Production Log'!$B:$B,$A71,'Milk Production Log'!$E:$E),1),"-")) | H71: =IF($A71="","",IF(SUMPRODUCT(MAX(('Milk Production Log'!$B$5:$B$404=$A71)*ROW('Milk Production Log'!$B$5:$B$404)))=0,"-",INDEX('Milk Production Log'!$A:$A,SUMPRODUCT(MAX(('Milk Production Log'!$B$5:$B$404=$A71)*ROW('Milk Production Log'!$B$5:$B$404)))))) | I71: =IF($A71="","",ROUND(SUMIF('Milk Production Log'!$B:$B,$A71,'Milk Production Log'!$E:$E),1))
A72: =IFERROR(INDEX('Animal Register'!$A:$A,MATCH(68,'Animal Register'!$V:$V,0)),"") | B72: =IF($A72="","",INDEX('Animal Register'!$C:$C,MATCH($A72,'Animal Register'!$A:$A,0))) | C72: =IF($A72="","",INDEX('Animal Register'!$E:$E,MATCH($A72,'Animal Register'!$A:$A,0))) | D72: =IF($A72="","",INDEX('Animal Register'!$F:$F,MATCH($A72,'Animal Register'!$A:$A,0))) | E72: =IF($A72="","",INDEX('Animal Register'!$S:$S,MATCH($A72,'Animal Register'!$A:$A,0))) | F72: =IF($A72="","",INDEX('Animal Register'!$Q:$Q,MATCH($A72,'Animal Register'!$A:$A,0))) | G72: =IF($A72="","",IFERROR(ROUND(AVERAGEIF('Milk Production Log'!$B:$B,$A72,'Milk Production Log'!$E:$E),1),"-")) | H72: =IF($A72="","",IF(SUMPRODUCT(MAX(('Milk Production Log'!$B$5:$B$404=$A72)*ROW('Milk Production Log'!$B$5:$B$404)))=0,"-",INDEX('Milk Production Log'!$A:$A,SUMPRODUCT(MAX(('Milk Production Log'!$B$5:$B$404=$A72)*ROW('Milk Production Log'!$B$5:$B$404)))))) | I72: =IF($A72="","",ROUND(SUMIF('Milk Production Log'!$B:$B,$A72,'Milk Production Log'!$E:$E),1))
A73: =IFERROR(INDEX('Animal Register'!$A:$A,MATCH(69,'Animal Register'!$V:$V,0)),"") | B73: =IF($A73="","",INDEX('Animal Register'!$C:$C,MATCH($A73,'Animal Register'!$A:$A,0))) | C73: =IF($A73="","",INDEX('Animal Register'!$E:$E,MATCH($A73,'Animal Register'!$A:$A,0))) | D73: =IF($A73="","",INDEX('Animal Register'!$F:$F,MATCH($A73,'Animal Register'!$A:$A,0))) | E73: =IF($A73="","",INDEX('Animal Register'!$S:$S,MATCH($A73,'Animal Register'!$A:$A,0))) | F73: =IF($A73="","",INDEX('Animal Register'!$Q:$Q,MATCH($A73,'Animal Register'!$A:$A,0))) | G73: =IF($A73="","",IFERROR(ROUND(AVERAGEIF('Milk Production Log'!$B:$B,$A73,'Milk Production Log'!$E:$E),1),"-")) | H73: =IF($A73="","",IF(SUMPRODUCT(MAX(('Milk Production Log'!$B$5:$B$404=$A73)*ROW('Milk Production Log'!$B$5:$B$404)))=0,"-",INDEX('Milk Production Log'!$A:$A,SUMPRODUCT(MAX(('Milk Production Log'!$B$5:$B$404=$A73)*ROW('Milk Production Log'!$B$5:$B$404)))))) | I73: =IF($A73="","",ROUND(SUMIF('Milk Production Log'!$B:$B,$A73,'Milk Production Log'!$E:$E),1))
A74: =IFERROR(INDEX('Animal Register'!$A:$A,MATCH(70,'Animal Register'!$V:$V,0)),"") | B74: =IF($A74="","",INDEX('Animal Register'!$C:$C,MATCH($A74,'Animal Register'!$A:$A,0))) | C74: =IF($A74="","",INDEX('Animal Register'!$E:$E,MATCH($A74,'Animal Register'!$A:$A,0))) | D74: =IF($A74="","",INDEX('Animal Register'!$F:$F,MATCH($A74,'Animal Register'!$A:$A,0))) | E74: =IF($A74="","",INDEX('Animal Register'!$S:$S,MATCH($A74,'Animal Register'!$A:$A,0))) | F74: =IF($A74="","",INDEX('Animal Register'!$Q:$Q,MATCH($A74,'Animal Register'!$A:$A,0))) | G74: =IF($A74="","",IFERROR(ROUND(AVERAGEIF('Milk Production Log'!$B:$B,$A74,'Milk Production Log'!$E:$E),1),"-")) | H74: =IF($A74="","",IF(SUMPRODUCT(MAX(('Milk Production Log'!$B$5:$B$404=$A74)*ROW('Milk Production Log'!$B$5:$B$404)))=0,"-",INDEX('Milk Production Log'!$A:$A,SUMPRODUCT(MAX(('Milk Production Log'!$B$5:$B$404=$A74)*ROW('Milk Production Log'!$B$5:$B$404)))))) | I74: =IF($A74="","",ROUND(SUMIF('Milk Production Log'!$B:$B,$A74,'Milk Production Log'!$E:$E),1))

Sheet Milk Production Log
A1: MILK PRODUCTION LOG
A2: Har cow/buffalo ki roz ki milking yahan likhein — Dairy Module mein average khud aa jayega.
A4: Date | B4: Animal ID | C4: Morning Yield (L) | D4: Evening Yield (L) | E4: Total Yield (L) | F4: Fat % | G4: SNF % | H4: Notes
A5: 46240 | E5: =IF($B5="","",C5+D5) | H5: Example row
E6: =IF($B6="","",C6+D6)
E7: =IF($B7="","",C7+D7)
E8: =IF($B8="","",C8+D8)
E9: =IF($B9="","",C9+D9)
E10: =IF($B10="","",C10+D10)
E11: =IF($B11="","",C11+D11)
E12: =IF($B12="","",C12+D12)
E13: =IF($B13="","",C13+D13)
E14: =IF($B14="","",C14+D14)
E15: =IF($B15="","",C15+D15)
E16: =IF($B16="","",C16+D16)
E17: =IF($B17="","",C17+D17)
... E404: =IF($B404="","",C404+D404)

Sheet Milk Customers
A1: MILK CUSTOMERS
A3: Customer Name | B3: Phone | C3: Address | D3: Daily Order Qty (L) | E3: Rate per L (Rs) | F3: Delivery Route/Time | G3: Status | H3: Notes | J3: Total Daily Milk Sold (L) | K3: =SUMIF(G4:G103,"Active",D4:D103) -> 0
J4: Total Daily Revenue (Rs) | K4: =SUMPRODUCT((G4:G103="Active")*D4:D103*E4:E103) -> 0

Sheet Breeding Module
A1: BREEDING MODULE
A2: Animal Register mein jo bhi Purpose='Breeding Stock' likha jayega, wo yahan khud aa jayega.
A4: Animal ID | B4: Breed | C4: Sex | D4: Current Weight (kg) | E4: Status | F4: Last Breeding Date | G4: Expected Calving Date | H4: Pregnancy Status | I4: Total Calvings
